Workbook
Name CleanedNikeSales: Cleaned_Nike_Sales!$B$1
Name CleanedSales: Cleaned_Nike_Sales!$B$1:$AA$42
Name Discount_Analysis: Nike_Sales_PreCleaned!$N$2:$N$2501
Name Discount_Applied: Nike_Sales_PreCleaned!$L$2:$L$2501
Name Discount_Verification: Nike_Sales_PreCleaned!$M$2:$M$2501
Name Gender_Category: Nike_Sales_PreCleaned!$B$2:$B$2501
Name MRP: Nike_Sales_PreCleaned!$K$2:$K$2501
Name NikeCleaned: Cleaned_Nike_Sales!#REF!
Name OD_Status: Nike_Sales_PreCleaned!$T$2:$T$2501
Name Order_Date: Nike_Sales_PreCleaned!$S$2:$S$2501
Name Order_ID: Nike_Sales_PreCleaned!$A$2:$A$2501
Name Product_Line: Nike_Sales_PreCleaned!$C$2:$C$2501
Name Product_Name: Nike_Sales_PreCleaned!$D$2:$D$2501
Name Product_Status: Nike_Sales_PreCleaned!$J$2:$J$2501
Name Profit: Nike_Sales_PreCleaned!$Y$2:$Y$2501
Name Profit_Analysis: Nike_Sales_PreCleaned!$AA$2:$AA$2501
Name Profit_Status: Nike_Sales_PreCleaned!$Z$2:$Z$2501
Name Region: Nike_Sales_PreCleaned!$W$2:$W$2501
Name Region_Formatted: Nike_Sales_PreCleaned!$X$2:$X$2501
Name Rev_Recalc: Nike_Sales_PreCleaned!$P$2:$P$2501
Name Rev_Verify: Nike_Sales_PreCleaned!$Q$2:$Q$2501
Name Revenue: Nike_Sales_PreCleaned!$O$2:$O$2501
Name Revenue_Analysis: Nike_Sales_PreCleaned!$R$2:$R$2501
Name Sales_Channel: Nike_Sales_PreCleaned!$V$2:$V$2501
Name Size: Nike_Sales_PreCleaned!$E$2:$E$2501
Name Size_Type: Nike_Sales_PreCleaned!$F$2:$F$2501
Name Size_Verification: Nike_Sales_PreCleaned!$G$2:$G$2501
Name Units_Sold: Nike_Sales_PreCleaned!$I$2:$I$2501
Name Valid_OD_Analysis: Nike_Sales_PreCleaned!$U$2:$U$2501
Name Valid_Size_Analysis: Nike_Sales_PreCleaned!$H$2:$H$2501

Sheet Nike_Sales_RawData
A1: Order_ID | B1: Gender_Category | C1: Product_Line | D1: Product_Name | E1: Size | F1: Units_Sold | G1: MRP | H1: Discount_Applied | I1: Revenue | J1: Order_Date | K1: Sales_Channel | L1: Region | M1: Profit
A2: 2053 | B2: Men | C2: Lifestyle | D2: Air Force 1 | E2: XL | F2: 3 | G2: 6009.58 | I2: 0 | J2: 45567 | K2: Online | L2: Delhi | M2: 3384.92
A3: 2108 | B3: Kids | C3: Lifestyle | D3: Air Force 1 | E3: XL | H3: 0.27 | I3: 0 | J3: 45611 | K3: Retail | L3: Mumbai | M3: -338.77
A4: 2166 | B4: Women | C4: Lifestyle | D4: Air Force 1 | E4: M | G4: 7312.38 | I4: 0 | J4: 45689 | K4: Online | L4: Mumbai | M4: 3364.05
A5: 2170 | B5: Kids | C5: Lifestyle | D5: Air Force 1 | E5: M | F5: 0 | I5: 0 | J5: 45836 | K5: Online | L5: Kolkata | M5: 3218.82
A6: 2022 | B6: Women | C6: Lifestyle | D6: Air Force 1 | E6: L | G6: 9378.52 | H6: 1.06 | I6: 0 | J6: 45228 | K6: Retail | L6: Mumbai | M6: 128.92
A7: 2181 | B7: Women | C7: Lifestyle | D7: Air Force 1 | E7: XL | F7: 2 | I7: 0 | J7: 45663 | K7: Retail | L7: Delhi | M7: 419.58
A8: 2191 | B8: Men | C8: Lifestyle | D8: Air Force 1 | E8: 8 | F8: 3 | I8: 0 | J8: 45563 | K8: Retail | L8: Pune | M8: -1032.88
A9: 2203 | B9: Men | C9: Lifestyle | D9: Air Force 1 | E9: M | F9: 0 | G9: 6903.22 | I9: 0 | K9: Online | L9: Pune | M9: 1556.95
A10: 2216 | B10: Women | C10: Lifestyle | D10: Air Force 1 | E10: M | F10: 1 | G10: 3111.62 | I10: 0 | K10: Online | L10: Hyd | M10: 2617.56
A11: 2233 | B11: Men | C11: Lifestyle | D11: Air Force 1 | E11: XL | F11: 0 | I11: 0 | K11: Online | L11: Kolkata | M11: 2398.07
A12: 2276 | B12: Kids | C12: Lifestyle | D12: Air Force 1 | E12: L | F12: -1 | G12: 6066.5 | I12: 0 | J12: 45167 | K12: Retail | L12: Kolkata | M12: 1181.87
A13: 2357 | B13: Women | C13: Lifestyle | D13: Air Force 1 | E13: M | H13: 1.23 | I13: 0 | J13: 45775 | K13: Retail | L13: Bangalore | M13: -1199.32
A14: 2373 | B14: Women | C14: Lifestyle | D14: Air Force 1 | E14: XL | G14: 8637.25 | H14: 0.35 | I14: 0 | J14: 45557 | K14: Retail | L14: Kolkata | M14: 2738.82
A15: 2379 | B15: Men | C15: Lifestyle | D15: Air Force 1 | E15: L | F15: 4 | I15: 0 | J15: 45391 | K15: Online | L15: Mumbai | M15: 3289.77
A16: 2394 | B16: Kids | C16: Lifestyle | D16: Air Force 1 | E16: XL | H16: 0.2 | I16: 0 | J16: 45156 | K16: Online | L16: Delhi | M16: -133.03
A17: 2482 | B17: Men | C17: Lifestyle | D17: Air Force 1 | E17: XL | I17: 0 | J17: 45549 | K17: Online | L17: Mumbai | M17: 2642.8
A18: 2489 | B18: Men | C18: Lifestyle | D18: Air Force 1 | F18: 4 | H18: 0.18 | I18: 0 | J18: 45567 | K18: Retail | L18: hyderbad | M18: 1415.34
A19: 2501 | B19: Women | C19: Lifestyle | D19: Air Force 1 | E19: L | G19: 6453.36 | I19: 0 | J19: 45812 | K19: Retail | L19: Kolkata | M19: 2321.06
A20: 2517 | B20: Men | C20: Lifestyle | D20: Air Force 1 | E20: 7 | F20: 1 | G20: 3059.89 | I20: 0 | K20: Online | L20: hyderbad | M20: 1968.82
A21: 2524 | B21: Women | C21: Lifestyle | D21: Air Force 1 | E21: XL | I21: 0 | J21: 45617 | K21: Online | L21: Kolkata | M21: 997.53
A22: 2527 | B22: Men | C22: Lifestyle | D22: Air Force 1 | E22: XL | G22: 7408.91 | I22: 0 | J22: 45369 | K22: Online | L22: Delhi | M22: -138.78
A23: 2540 | B23: Women | C23: Lifestyle | D23: Air Force 1 | E23: L | G23: 8794.64 | I23: 0 | J23: 45666 | K23: Online | L23: Mumbai | M23: -938.07
A24: 2556 | B24: Kids | C24: Lifestyle | D24: Air Force 1 | E24: 10 | F24: 1 | I24: 0 | K24: Retail | L24: Kolkata | M24: 1327.26
A25: 2559 | B25: Men | C25: Lifestyle | D25: Air Force 1 | E25: 7 | F25: 3 | G25: 6011.84 | I25: 0 | J25: 45698 | K25: Online | L25: Kolkata | M25: -99.73
A26: 2600 | B26: Kids | C26: Lifestyle | D26: Air Force 1 | E26: M | F26: 3 | I26: 0 | J26: 45600 | K26: Online | L26: Pune | M26: 803.62
A27: 2606 | B27: Women | C27: Lifestyle | D27: Air Force 1 | E27: L | G27: 4040.65 | I27: 0 | J27: 45812 | K27: Retail | L27: Mumbai | M27: 805.92
A28: 2642 | B28: Women | C28: Lifestyle | D28: Air Force 1 | E28: XL | I28: 0 | J28: 45794 | K28: Retail | L28: Pune | M28: -785.16
A29: 2667 | B29: Women | C29: Lifestyle | D29: Air Force 1 | E29: XL | F29: 3 | G29: 9367.66 | I29: 0 | J29: 45739 | K29: Online | L29: Delhi | M29: -623.95
A30: 2672 | B30: Women | C30: Lifestyle | D30: Air Force 1 | E30: XL | F30: 2 | I30: 0 | J30: 45508 | K30: Online | L30: Mumbai | M30: 67.58
A31: 2677 | B31: Men | C31: Lifestyle | D31: Air Force 1 | E31: M | F31: 2 | G31: 5618.62 | I31: 0 | K31: Retail | L31: bengaluru | M31: 1745.96
A32: 2713 | B32: Men | C32: Lifestyle | D32: Air Force 1 | E32: L | F32: 1 | G32: 7877.36 | H32: 0.55 | I32: 3544.81 | J32: 45787 | K32: Retail | L32: Kolkata | M32: 3663.49
A33: 2740 | B33: Women | C33: Lifestyle | D33: Air Force 1 | E33: XL | F33: 1 | G33: 4922.19 | I33: 0 | K33: Retail | L33: bengaluru | M33: 3820.48
A34: 2775 | B34: Men | C34: Lifestyle | D34: Air Force 1 | H34: 0.73 | I34: 0 | K34: Online | L34: Pune | M34: 2329.33
A35: 2821 | B35: Kids | C35: Lifestyle | D35: Air Force 1 | F35: 0 | G35: 3360.35 | I35: 0 | J35: 45755 | K35: Online | L35: Delhi | M35: 2991.25
A36: 2835 | B36: Women | C36: Lifestyle | D36: Air Force 1 | G36: 9240.64 | H36: 0.63 | I36: 0 | J36: 45572 | K36: Retail | L36: Pune | M36: 1873.76
A37: 2858 | B37: Kids | C37: Lifestyle | D37: Air Force 1 | F37: 0 | H37: 0.6 | I37: 0 | J37: 45591 | K37: Retail | L37: Pune | M37: 2847.01
A38: 2859 | B38: Women | C38: Lifestyle | D38: Air Force 1 | E38: 7 | I38: 0 | K38: Online | L38: Pune | M38: 566.34
A39: 2860 | B39: Kids | C39: Lifestyle | D39: Air Force 1 | E39: XL | F39: -1 | G39: 7568.04 | I39: 0 | J39: 45754 | K39: Retail | L39: hyderbad | M39: 1365.3
A40: 2894 | B40: Women | C40: Lifestyle | D40: Air Force 1 | E40: L | I40: 0 | J40: 45616 | K40: Retail | L40: hyderbad | M40: 1796.17
A41: 2962 | B41: Women | C41: Lifestyle | D41: Air Force 1 | E41: 9 | F41: -1 | G41: 2446.23 | I41: 0 | K41: Online | L41: Hyderabad | M41: 727.92
A42: 2994 | B42: Women | C42: Lifestyle | D42: Air Force 1 | E42: 11 | G42: 2932.39 | H42: 0.98 | I42: 0 | J42: 45633 | K42: Retail | L42: Mumbai | M42: 2962.69
A43: 3038 | B43: Kids | C43: Lifestyle | D43: Air Force 1 | E43: M | F43: 0 | G43: 4195.03 | I43: 0 | J43: 45684 | K43: Retail | L43: Delhi | M43: 1068.18
A44: 3042 | B44: Men | C44: Lifestyle | D44: Air Force 1 | E44: M | F44: 1 | I44: 0 | K44: Online | L44: Delhi | M44: 3750.11
A45: 3044 | B45: Kids | C45: Lifestyle | D45: Air Force 1 | E45: 7 | F45: 3 | G45: 4222.2 | I45: 0 | K45: Retail | L45: Hyderabad | M45: 931.4
A46: 3049 | B46: Kids | C46: Lifestyle | D46: Air Force 1 | E46: 11 | H46: 1.06 | I46: 0 | J46: 45830 | K46: Online | L46: Pune | M46: -156.45
A47: 3053 | B47: Women | C47: Lifestyle | D47: Air Force 1 | E47: L | G47: 6323.09 | H47: 1 | I47: 0 | J47: 45553 | K47: Retail | L47: Mumbai | M47: 1283.62
A48: 3068 | B48: Kids | C48: Lifestyle | D48: Air Force 1 | E48: L | F48: 4 | G48: 4867.07 | H48: 1.21 | I48: -4088.34 | J48: 45802 | K48: Online | L48: Delhi | M48: 2863.56
A49: 3118 | B49: Kids | C49: Lifestyle | D49: Air Force 1 | E49: 8 | I49: 0 | K49: Online | L49: Bangalore | M49: 2058.99
A50: 3119 | B50: Kids | C50: Lifestyle | D50: Air Force 1 | I50: 0 | J50: 45150 | K50: Online | L50: hyderbad | M50: 3995.49
A51: 3151 | B51: Men | C51: Lifestyle | D51: Air Force 1 | E51: L | I51: 0 | J51: 45857 | K51: Online | L51: Kolkata | M51: 2968.24
A52: 3158 | B52: Kids | C52: Lifestyle | D52: Air Force 1 | E52: 12 | F52: 2 | I52: 0 | K52: Online | L52: Pune | M52: 324.37
A53: 3168 | B53: Women | C53: Lifestyle | D53: Air Force 1 | E53: 7 | F53: 2 | G53: 6125.15 | I53: 0 | J53: 45716 | K53: Retail | L53: Delhi | M53: 61.83
A54: 3171 | B54: Men | C54: Lifestyle | D54: Air Force 1 | I54: 0 | J54: 45246 | K54: Online | L54: Bangalore | M54: -445.89
A55: 3177 | B55: Kids | C55: Lifestyle | D55: Air Force 1 | E55: L | F55: 3 | G55: 7042.12 | H55: 0.89 | I55: 2323.9 | K55: Online | L55: Mumbai | M55: -411.55
A56: 3188 | B56: Kids | C56: Lifestyle | D56: Air Force 1 | E56: L | G56: 8024.17 | H56: 0.6 | I56: 0 | J56: 45697 | K56: Retail | L56: Pune | M56: 2328.33
A57: 3232 | B57: Kids | C57: Lifestyle | D57: Air Force 1 | F57: 0 | I57: 0 | J57: 45241 | K57: Online | L57: Pune | M57: 2083.57
A58: 3243 | B58: Men | C58: Lifestyle | D58: Air Force 1 | E58: L | F58: 3 | I58: 0 | J58: 45590 | K58: Retail | L58: Pune | M58: 1943.22
A59: 3250 | B59: Women | C59: Lifestyle | D59: Air Force 1 | E59: L | I59: 0 | J59: 45553 | K59: Online | L59: Pune | M59: 1172.07
A60: 3259 | B60: Women | C60: Lifestyle | D60: Air Force 1 | E60: 6 | F60: 0 | G60: 7305.78 | I60: 0 | J60: 45842 | K60: Retail | L60: Mumbai | M60: 573.79
A61: 3267 | B61: Kids | C61: Lifestyle | D61: Air Force 1 | H61: 0.52 | I61: 0 | J61: 45703 | K61: Retail | L61: Pune | M61: 345.92
A62: 3290 | B62: Kids | C62: Lifestyle | D62: Air Force 1 | E62: XL | F62: 2 | G62: 7377.71 | I62: 0 | K62: Online | L62: Pune | M62: 2588.85
A63: 3297 | B63: Men | C63: Lifestyle | D63: Air Force 1 | E63: L | G63: 5875.99 | I63: 0 | J63: 45695 | K63: Online | L63: Delhi | M63: 3803.18
A64: 3309 | B64: Men | C64: Lifestyle | D64: Air Force 1 | G64: 5594.08 | I64: 0 | J64: 45181 | K64: Retail | L64: Hyd | M64: 626.95
A65: 3339 | B65: Men | C65: Lifestyle | D65: Air Force 1 | G65: 6656.01 | I65: 0 | J65: 45792 | K65: Retail | L65: Delhi | M65: 2014.52
A66: 3362 | B66: Men | C66: Lifestyle | D66: Air Force 1 | E66: L | I66: 0 | J66: 45361 | K66: Retail | L66: Delhi | M66: 2730.12
A67: 3383 | B67: Women | C67: Lifestyle | D67: Air Force 1 | E67: XL | I67: 0 | J67: 45516 | K67: Retail | L67: Bangalore | M67: 3793.87
A68: 3407 | B68: Women | C68: Lifestyle | D68: Air Force 1 | E68: 11 | F68: 0 | G68: 5704.39 | H68: 1.11 | I68: 0 | J68: 45675 | K68: Retail | L68: Delhi | M68: -4.1
A69: 2038 | B69: Kids | C69: Lifestyle | D69: Air Force 1 | G69: 7609.9 | H69: 0.05 | I69: 0 | K69: Online | L69: Delhi | M69: 788.86
A70: 3467 | B70: Men | C70: Lifestyle | D70: Air Force 1 | E70: M | F70: 2 | I70: 0 | J70: 45729 | K70: Online | L70: bengaluru | M70: 1472.83
A71: 3481 | B71: Women | C71: Lifestyle | D71: Air Force 1 | E71: XL | F71: 4 | I71: 0 | J71: 45214 | K71: Online | L71: bengaluru | M71: 2564.61
A72: 3483 | B72: Men | C72: Lifestyle | D72: Air Force 1 | E72: L | F72: 4 | G72: 4733.92 | I72: 0 | J72: 45630 | K72: Online | L72: Kolkata | M72: 738.19
A73: 3539 | B73: Kids | C73: Lifestyle | D73: Air Force 1 | E73: XL | F73: 3 | G73: 7706.3 | H73: 1.15 | I73: -3467.83 | K73: Retail | L73: Hyderabad | M73: 2366.58
A74: 3542 | B74: Men | C74: Lifestyle | D74: Air Force 1 | G74: 7199.03 | H74: 0.61 | I74: 0 | J74: 45624 | K74: Retail | L74: Mumbai | M74: 1826.07
A75: 3550 | B75: Women | C75: Lifestyle | D75: Air Force 1 | E75: M | G75: 8645.09 | I75: 0 | K75: Online | L75: bengaluru | M75: 3289.86
A76: 3567 | B76: Men | C76: Lifestyle | D76: Air Force 1 | E76: L | F76: 2 | H76: 0.56 | I76: 0 | K76: Online | L76: Kolkata | M76: 1353.32
A77: 3619 | B77: Kids | C77: Lifestyle | D77: Air Force 1 | E77: L | F77: 0 | G77: 8915.88 | I77: 0 | J77: 45695 | K77: Online | L77: Kolkata | M77: 824.23
A78: 3655 | B78: Women | C78: Lifestyle | D78: Air Force 1 | E78: 6 | I78: 0 | J78: 45785 | K78: Retail | L78: Pune | M78: 3499.88
A79: 3715 | B79: Men | C79: Lifestyle | D79: Air Force 1 | E79: L | F79: 4 | I79: 0 | J79: 45831 | K79: Online | L79: Bangalore | M79: 2774.43
A80: 3741 | B80: Kids | C80: Lifestyle | D80: Air Force 1 | E80: L | F80: 2 | G80: 8927.22 | H80: 0.2 | I80: 14283.55 | J80: 45851 | K80: Retail | L80: Kolkata | M80: 821.32
A81: 3747 | B81: Men | C81: Lifestyle | D81: Air Force 1 | F81: 4 | G81: 5776.58 | I81: 0 | J81: 45816 | K81: Retail | L81: Hyderabad | M81: 616.71
A82: 3751 | B82: Kids | C82: Lifestyle | D82: Air Force 1 | E82: XL | F82: -1 | H82: 0.4 | I82: 0 | K82: Retail | L82: Delhi | M82: -399.23
A83: 3762 | B83: Men | C83: Lifestyle | D83: Air Force 1 | E83: 9 | F83: 1 | G83: 2725.1 | I83: 0 | J83: 45844 | K83: Retail | L83: Mumbai | M83: -997.11
A84: 3786 | B84: Men | C84: Lifestyle | D84: Air Force 1 | E84: M | H84: 0.76 | I84: 0 | J84: 45819 | K84: Retail | L84: Kolkata | M84: 155.59
A85: 3789 | B85: Women | C85: Lifestyle | D85: Air Force 1 | E85: XL | F85: 2 | G85: 2738.79 | I85: 0 | J85: 45515 | K85: Retail | L85: hyderbad | M85: 863.29
A86: 3821 | B86: Women | C86: Lifestyle | D86: Air Force 1 | E86: L | F86: -1 | G86: 7539.55 | I86: 0 | J86: 45584 | K86: Retail | L86: Kolkata | M86: -17.8
A87: 3839 | B87: Women | C87: Lifestyle | D87: Air Force 1 | E87: L | G87: 3907.78 | H87: 0.34 | I87: 0 | K87: Online | L87: Delhi | M87: -870.71
A88: 3846 | B88: Women | C88: Lifestyle | D88: Air Force 1 | E88: 6 | G88: 8357.96 | H88: 0.28 | I88: 0 | J88: 45535 | K88: Retail | L88: Bangalore | M88: -306.33
A89: 3852 | B89: Men | C89: Lifestyle | D89: Air Force 1 | F89: 1 | G89: 7834.8 | I89: 0 | J89: 45582 | K89: Online | L89: Kolkata | M89: 2786.52
A90: 3956 | B90: Women | C90: Lifestyle | D90: Air Force 1 | F90: 2 | I90: 0 | J90: 45722 | K90: Online | L90: Hyd | M90: 2842.28
A91: 3995 | B91: Men | C91: Lifestyle | D91: Air Force 1 | E91: 11 | F91: -1 | H91: 0.47 | I91: 0 | K91: Online | L91: Delhi | M91: 3242.46
A92: 4003 | B92: Men | C92: Lifestyle | D92: Air Force 1 | E92: L | G92: 7165.28 | H92: 1.17 | I92: 0 | J92: 45691 | K92: Retail | L92: Mumbai | M92: 839.48
A93: 4015 | B93: Men | C93: Lifestyle | D93: Air Force 1 | E93: L | F93: 4 | G93: 5505.76 | I93: 0 | J93: 45843 | K93: Online | L93: bengaluru | M93: 1194.93
A94: 4039 | B94: Women | C94: Lifestyle | D94: Air Force 1 | E94: L | G94: 5103.01 | I94: 0 | J94: 45632 | K94: Online | L94: Delhi | M94: -134.82
A95: 4042 | B95: Kids | C95: Lifestyle | D95: Air Force 1 | E95: 9 | F95: 0 | G95: 2566.15 | I95: 0 | K95: Online | L95: hyderbad | M95: -198.88
A96: 4063 | B96: Kids | C96: Lifestyle | D96: Air Force 1 | E96: L | F96: 0 | H96: 0.38 | I96: 0 | K96: Online | L96: Mumbai | M96: -617.86
A97: 4078 | B97: Women | C97: Lifestyle | D97: Air Force 1 | E97: 9 | H97: 0.56 | I97: 0 | J97: 45658 | K97: Online | L97: Mumbai | M97: 2742.28
A98: 4090 | B98: Men | C98: Lifestyle | D98: Air Force 1 | E98: L | G98: 5109.51 | I98: 0 | J98: 45834 | K98: Retail | L98: Delhi | M98: -1164.28
A99: 4092 | B99: Women | C99: Lifestyle | D99: Air Force 1 | E99: XL | F99: -1 | G99: 9861.8 | I99: 0 | J99: 45588 | K99: Online | L99: Delhi | M99: 48.02
A100: 4116 | B100: Women | C100: Lifestyle | D100: Air Force 1 | E100: 9 | G100: 3854.22 | I100: 0 | J100: 45523 | K100: Online | L100: Pune | M100: -43.41
...

Sheet Pivot Checks
A3: Row Labels | B3: Count of Gender_Category | D3: Row Labels | E3: Count of Size | G3: Count of Order_ID | H3: Column Labels | U3: Count of Size_Type | V3: Column Labels
A4: Kids | B4: 841 | D4: 6 | E4: 59 | G4: Row Labels | H4: 10 | I4: 11 | J4: 12 | K4: 6 | L4: 7 | M4: 8 | N4: 9 | O4: L | P4: M | Q4: Unknown | R4: XL | S4: Grand Total | U4: Row Labels | V4: Alphabet | W4: Missing | X4: Number | Y4: Grand Total
A5: Men | B5: 840 | D5: 7 | E5: 86 | G5: Air Force 1 | H5: 1 | I5: 5 | J5: 1 | K5: 5 | L5: 5 | M5: 2 | N5: 8 | O5: 32 | P5: 18 | Q5: 20 | R5: 24 | S5: 121 | U5: Basketball | V5: 319 | W5: 103 | X5: 85 | Y5: 507
A6: Women | B6: 819 | D6: 8 | E6: 60 | G6: Air Jordan | H6: 7 | I6: 7 | J6: 3 | K6: 3 | L6: 1 | M6: 2 | N6: 5 | O6: 28 | P6: 15 | Q6: 24 | R6: 38 | S6: 133 | U6: Lifestyle | V6: 311 | W6: 93 | X6: 97 | Y6: 501
A7: Grand Total | B7: 2500 | D7: 9 | E7: 68 | G7: Air Zoom | H7: 5 | I7: 2 | J7: 5 | K7: 2 | L7: 6 | M7: 2 | N7: 1 | O7: 23 | P7: 22 | Q7: 18 | R7: 21 | S7: 107 | U7: Running | V7: 282 | W7: 99 | X7: 93 | Y7: 474
D8: 10 | E8: 76 | G8: Blazer Mid | H8: 4 | I8: 1 | J8: 3 | K8: 2 | L8: 4 | M8: 4 | N8: 5 | O8: 30 | P8: 20 | Q8: 22 | R8: 32 | S8: 127 | U8: Soccer | V8: 273 | W8: 100 | X8: 99 | Y8: 472
A9: Row Labels | B9: Count of Product_Line | D9: 11 | E9: 77 | G9: Dunk Low | H9: 4 | I9: 4 | J9: 5 | L9: 5 | M9: 5 | N9: 3 | O9: 22 | P9: 21 | Q9: 25 | R9: 22 | S9: 116 | U9: Training | V9: 318 | W9: 115 | X9: 113 | Y9: 546
A10: Basketball | B10: 507 | D10: 12 | E10: 61 | G10: Flex Trainer | H10: 3 | I10: 8 | J10: 7 | K10: 1 | L10: 2 | M10: 3 | N10: 6 | O10: 27 | P10: 30 | Q10: 23 | R10: 31 | S10: 141 | U10: Grand Total | V10: 1503 | W10: 510 | X10: 487 | Y10: 2500
A11: Lifestyle | B11: 501 | D11: L | E11: 513 | G11: Free RN | H11: 6 | I11: 3 | J11: 4 | K11: 4 | L11: 5 | M11: 3 | N11: 1 | O11: 24 | P11: 21 | Q11: 29 | R11: 24 | S11: 124
A12: Running | B12: 474 | D12: M | E12: 478 | G12: Kyrie Flytrap | H12: 2 | I12: 3 | J12: 4 | K12: 3 | L12: 3 | M12: 2 | N12: 1 | O12: 30 | P12: 17 | Q12: 22 | R12: 29 | S12: 116
A13: Soccer | B13: 472 | D13: XL | E13: 512 | G13: LeBron 20 | H13: 2 | I13: 3 | J13: 2 | K13: 6 | L13: 5 | M13: 1 | N13: 1 | O13: 30 | P13: 30 | Q13: 29 | R13: 35 | S13: 144
A14: Training | B14: 546 | D14: (blank) | G14: Mercurial Superfly | H14: 5 | I14: 1 | J14: 2 | K14: 1 | L14: 3 | M14: 2 | N14: 5 | O14: 17 | P14: 32 | Q14: 28 | R14: 13 | S14: 109
A15: Grand Total | B15: 2500 | D15: Grand Total | E15: 1990 | G15: Metcon 7 | H15: 1 | I15: 1 | J15: 3 | K15: 6 | L15: 4 | M15: 5 | N15: 2 | O15: 18 | P15: 29 | Q15: 20 | R15: 28 | S15: 117
G16: Pegasus Turbo | H16: 3 | I16: 4 | K16: 2 | L16: 5 | M16: 4 | N16: 5 | O16: 27 | P16: 15 | Q16: 26 | R16: 18 | S16: 109
A17: Row Labels | B17: Count of Product_Name | D17: Row Labels | E17: Count of Region_Formatted | G17: Phantom GT | H17: 2 | I17: 3 | J17: 3 | K17: 5 | L17: 9 | M17: 5 | N17: 3 | O17: 20 | P17: 22 | Q17: 32 | R17: 26 | S17: 130
A18: Air Force 1 | B18: 121 | D18: Bangalore | E18: 216 | G18: Premier III | H18: 4 | I18: 6 | J18: 2 | K18: 2 | L18: 4 | M18: 4 | N18: 3 | O18: 23 | P18: 25 | Q18: 23 | R18: 25 | S18: 121
A19: Air Jordan | B19: 133 | D19: Bengaluru | E19: 220 | G19: React Infinity | H19: 3 | I19: 3 | J19: 2 | K19: 4 | L19: 3 | M19: 3 | N19: 3 | O19: 32 | P19: 27 | Q19: 26 | R19: 28 | S19: 134
A20: Air Zoom | B20: 107 | D20: Delhi | E20: 438 | G20: SuperRep Go | H20: 9 | I20: 9 | J20: 3 | K20: 2 | L20: 9 | M20: 4 | N20: 2 | O20: 25 | P20: 28 | Q20: 42 | R20: 15 | S20: 148
A21: Blazer Mid | B21: 127 | D21: Hyderabad | E21: 403 | G21: Tiempo Legend | H21: 6 | I21: 2 | J21: 5 | K21: 1 | L21: 4 | M21: 3 | N21: 4 | O21: 21 | P21: 28 | Q21: 17 | R21: 21 | S21: 112
A22: Dunk Low | B22: 116 | D22: Kolkata | E22: 417 | G22: Waffle One | H22: 4 | I22: 3 | J22: 1 | K22: 6 | L22: 4 | M22: 1 | N22: 2 | O22: 36 | P22: 25 | Q22: 26 | R22: 29 | S22: 137 | U22: Row Labels | V22: Count of Order_ID | W22: Sum of Revenue | X22: Average of Revenue2
A23: Flex Trainer | B23: 141 | D23: Mumbai | E23: 418 | G23: Zoom Freak | H23: 3 | I23: 4 | J23: 3 | K23: 1 | L23: 1 | M23: 3 | N23: 4 | O23: 21 | P23: 23 | Q23: 28 | R23: 23 | S23: 114 | U23: Alphabet | V23: 1503 | W23: 406379.45 | X23: 270.37888
A24: Free RN | B24: 124 | D24: Pune | E24: 388 | G24: ZoomX Invincible | H24: 2 | I24: 5 | J24: 3 | K24: 3 | L24: 4 | M24: 2 | N24: 4 | O24: 27 | P24: 30 | Q24: 30 | R24: 30 | S24: 140 | U24: Missing | V24: 510 | W24: 157717.7 | X24: 309.25039
A25: Kyrie Flytrap | B25: 116 | D25: Grand Total | E25: 2500 | G25: Grand Total | H25: 76 | I25: 77 | J25: 61 | K25: 59 | L25: 86 | M25: 60 | N25: 68 | O25: 513 | P25: 478 | Q25: 510 | R25: 512 | S25: 2500 | U25: Number | V25: 487 | W25: 123087.14 | X25: 252.74567
A26: LeBron 20 | B26: 144 | U26: Grand Total | V26: 2500 | W26: 687184.29 | X26: 274.87372
A27: Mercurial Superfly | B27: 109 | D27: Row Labels | E27: Count of Units_Sold
A28: Metcon 7 | B28: 117 | D28: -1 | E28: 205
A29: Pegasus Turbo | B29: 109 | D29: 0 | E29: 224
A30: Phantom GT | B30: 130 | D30: 1 | E30: 203
A31: Premier III | B31: 121 | D31: 2 | E31: 234
A32: React Infinity | B32: 134 | D32: 3 | E32: 187
A33: SuperRep Go | B33: 148 | D33: 4 | E33: 212
A34: Tiempo Legend | B34: 112 | D34: (blank)
A35: Waffle One | B35: 137 | D35: Grand Total | E35: 1265
A36: Zoom Freak | B36: 114
A37: ZoomX Invincible | B37: 140
A38: Grand Total | B38: 2500

Sheet Nike_Sales_PreCleaned
A1: Order_ID | B1: Gender_Category | C1: Product_Line | D1: Product_Name | E1: Size | F1: Size_Type | G1: Size_Verification | H1: Valid_Size_Analysis | I1: Units_Sold | J1: Product_Status | K1: MRP | L1: Discount_Applied | M1: Discount_Verification | N1: Discount_Analysis | O1: Revenue | P1: Rev_Recalc | Q1: Rev_Verify | R1: Revenue_Analysis | S1: Order_Date | T1: OD_Status | U1: Valid_OD_Analysis | V1: Sales_Channel | W1: Region | X1: Region_Formatted | Y1: Profit | Z1: Profit_Status | AA1: Profit_Analysis | AC1: DATA QUALITY SUMMARY TABLE | AD1: Stats
A2: 2000 | B2: Kids | C2: Training | D2: SuperRep Go | E2: M | F2: =_xlfn.IFS(ISBLANK(Size),"Missing",ISNUMBER(Size),"Number",ISTEXT(Size),"Alphabet") -> Alphabet | G2: =IF(Size_Type ="Missing","Unknown",TRIM(Size)) -> M | H2: =IF(Size_Verification="Unknown","No","Yes") -> Yes | J2: =_xlfn.IFS(Units_Sold<0,"Check Return/Refund",Units_Sold=" ",Invalid,Units_Sold=0,"Available",Units_Sold>0,"Sold") -> Available | L2: 0.47 | M2: =IF(OR(Discount_Applied="",Discount_Applied>1,Discount_Applied<0),"Invalid","Valid") -> Valid | N2: =IF(PC_NikeSales[[#This Row],[Discount_Verification]]="Valid","Include","Exclude") -> Include | O2: 0 | P2: =IF(AND(Units_Sold<>"",MRP<>"",Discount_Applied<1),Units_Sold*MRP*(1-Discount_Applied),"Insufficient Data") -> Insufficient Data | Q2: =_xlfn.IFS(Rev_Recalc="Insufficient Data","Missing Information",Rev_Recalc<0,"Negative Revenue",Rev_Recalc=0,"No Recorded Revenue",Rev_Recalc>0,"Valid Revenue") -> Missing Information | R2: =IF(PC_NikeSales[[#This Row],[Rev_Verify]]="Valid Revenue","Include","Exclude") -> Exclude | S2: 45360 | T2: =IF(ISBLANK(Order_Date),"Missing Date",Order_Date) -> 45360 | U2: =IF(ISBLANK(Order_Date),"No","Yes") -> Yes | V2: Online | W2: bengaluru | X2: =PROPER(Region) -> Bengaluru | Y2: -770.45 | Z2: =IF(PC_NikeSales[[#This Row],[Profit]]<0,"Loss Making Sales",IF(PC_NikeSales[[#This Row],[Profit]]=0,"No Recorded Profit",IF(PC_NikeSales[[#This Row],[Profit]]>PC_NikeSales[Rev_Recalc],"Invalid Profit", "Valid Profit"))) -> Loss Making Sales | AA2: =IF(PC_NikeSales[[#This Row],[Profit_Status]]="Valid Profit","Include","Exclude") -> Exclude | AC2: % of Revenue Insufficent Data | AD2: =(COUNTIF(Rev_Recalc,"Insufficient Data")/2500)*100 -> 76.44
A3: 2001 | B3: Women | C3: Soccer | D3: Tiempo Legend | E3: M | F3: =_xlfn.IFS(ISBLANK(Size),"Missing",ISNUMBER(Size),"Number",ISTEXT(Size),"Alphabet") -> Alphabet | G3: =IF(Size_Type ="Missing","Unknown",TRIM(Size)) -> M | H3: =IF(Size_Verification="Unknown","No","Yes") -> Yes | I3: 3 | J3: =_xlfn.IFS(Units_Sold<0,"Check Return/Refund",Units_Sold=" ",Invalid,Units_Sold=0,"Available",Units_Sold>0,"Sold") -> Sold | K3: 4957.93 | M3: =IF(OR(Discount_Applied="",Discount_Applied>1,Discount_Applied<0),"Invalid","Valid") -> Invalid | N3: =IF(PC_NikeSales[[#This Row],[Discount_Verification]]="Valid","Include","Exclude") -> Exclude | O3: 0 | P3: =IF(AND(Units_Sold<>"",MRP<>"",Discount_Applied<1),Units_Sold*MRP*(1-Discount_Applied),"Insufficient Data") -> 14873.79 | Q3: =_xlfn.IFS(Rev_Recalc="Insufficient Data","Missing Information",Rev_Recalc<0,"Negative Revenue",Rev_Recalc=0,"No Recorded Revenue",Rev_Recalc>0,"Valid Revenue") -> Valid Revenue | R3: =IF(PC_NikeSales[[#This Row],[Rev_Verify]]="Valid Revenue","Include","Exclude") -> Include | S3: 45482 | T3: =IF(ISBLANK(Order_Date),"Missing Date",Order_Date) -> 45482 | U3: =IF(ISBLANK(Order_Date),"No","Yes") -> Yes | V3: Retail | W3: Hyderabad | X3: =PROPER(Region) -> Hyderabad | Y3: -112.53 | Z3: =IF(PC_NikeSales[[#This Row],[Profit]]<0,"Loss Making Sales",IF(PC_NikeSales[[#This Row],[Profit]]=0,"No Recorded Profit",IF(PC_NikeSales[[#This Row],[Profit]]>PC_NikeSales[Rev_Recalc],"Invalid Profit", "Valid Profit"))) -> Loss Making Sales | AA3: =IF(PC_NikeSales[[#This Row],[Profit_Status]]="Valid Profit","Include","Exclude") -> Exclude | AC3: % of Invalid Profit | AD3: =(COUNTIF(Z:Z, "Invalid Profit")/ROWS(Order_ID))*100 -> 12.2
A4: 2002 | B4: Women | C4: Soccer | D4: Premier III | E4: M | F4: =_xlfn.IFS(ISBLANK(Size),"Missing",ISNUMBER(Size),"Number",ISTEXT(Size),"Alphabet") -> Alphabet | G4: =IF(Size_Type ="Missing","Unknown",TRIM(Size)) -> M | H4: =IF(Size_Verification="Unknown","No","Yes") -> Yes | I4: 4 | J4: =_xlfn.IFS(Units_Sold<0,"Check Return/Refund",Units_Sold=" ",Invalid,Units_Sold=0,"Available",Units_Sold>0,"Sold") -> Sold | M4: =IF(OR(Discount_Applied="",Discount_Applied>1,Discount_Applied<0),"Invalid","Valid") -> Invalid | N4: =IF(PC_NikeSales[[#This Row],[Discount_Verification]]="Valid","Include","Exclude") -> Exclude | O4: 0 | P4: =IF(AND(Units_Sold<>"",MRP<>"",Discount_Applied<1),Units_Sold*MRP*(1-Discount_Applied),"Insufficient Data") -> Insufficient Data | Q4: =_xlfn.IFS(Rev_Recalc="Insufficient Data","Missing Information",Rev_Recalc<0,"Negative Revenue",Rev_Recalc=0,"No Recorded Revenue",Rev_Recalc>0,"Valid Revenue") -> Missing Information | R4: =IF(PC_NikeSales[[#This Row],[Rev_Verify]]="Valid Revenue","Include","Exclude") -> Exclude | T4: =IF(ISBLANK(Order_Date),"Missing Date",Order_Date) -> Missing Date | U4: =IF(ISBLANK(Order_Date),"No","Yes") -> No | V4: Retail | W4: Mumbai | X4: =PROPER(Region) -> Mumbai | Y4: 3337.34 | Z4: =IF(PC_NikeSales[[#This Row],[Profit]]<0,"Loss Making Sales",IF(PC_NikeSales[[#This Row],[Profit]]=0,"No Recorded Profit",IF($Y2>$P2,"Invalid Profit", "Valid Profit"))) -> Valid Profit | AA4: =IF(PC_NikeSales[[#This Row],[Profit_Status]]="Valid Profit","Include","Exclude") -> Include | AC4: % of Loss Making Sales | AD4: =(COUNTIF(Profit_Status,"Loss Making Sales")/2500)*100 -> 23.12
A5: 2003 | B5: Kids | C5: Lifestyle | D5: Blazer Mid | E5: L | F5: =_xlfn.IFS(ISBLANK(Size),"Missing",ISNUMBER(Size),"Number",ISTEXT(Size),"Alphabet") -> Alphabet | G5: =IF(Size_Type ="Missing","Unknown",TRIM(Size)) -> L | H5: =IF(Size_Verification="Unknown","No","Yes") -> Yes | J5: =_xlfn.IFS(Units_Sold<0,"Check Return/Refund",Units_Sold=" ",Invalid,Units_Sold=0,"Available",Units_Sold>0,"Sold") -> Available | K5: 9673.57 | M5: =IF(OR(Discount_Applied="",Discount_Applied>1,Discount_Applied<0),"Invalid","Valid") -> Invalid | N5: =IF(PC_NikeSales[[#This Row],[Discount_Verification]]="Valid","Include","Exclude") -> Exclude | O5: 0 | P5: =IF(AND(Units_Sold<>"",MRP<>"",Discount_Applied<1),Units_Sold*MRP*(1-Discount_Applied),"Insufficient Data") -> Insufficient Data | Q5: =_xlfn.IFS(Rev_Recalc="Insufficient Data","Missing Information",Rev_Recalc<0,"Negative Revenue",Rev_Recalc=0,"No Recorded Revenue",Rev_Recalc>0,"Valid Revenue") -> Missing Information | R5: =IF(PC_NikeSales[[#This Row],[Rev_Verify]]="Valid Revenue","Include","Exclude") -> Exclude | S5: 45569 | T5: =IF(ISBLANK(Order_Date),"Missing Date",Order_Date) -> 45569 | U5: =IF(ISBLANK(Order_Date),"No","Yes") -> Yes | V5: Online | W5: Pune | X5: =PROPER(Region) -> Pune | Y5: 3376.85 | Z5: =IF(PC_NikeSales[[#This Row],[Profit]]<0,"Loss Making Sales",IF(PC_NikeSales[[#This Row],[Profit]]=0,"No Recorded Profit",IF($Y3>$P3,"Invalid Profit", "Valid Profit"))) -> Valid Profit | AA5: =IF(PC_NikeSales[[#This Row],[Profit_Status]]="Valid Profit","Include","Exclude") -> Include | AC5: % of Missing Sizes | AD5: =(COUNTIF(Size_Type,"Missing")/2500)*100 -> 20.4
A6: 2004 | B6: Kids | C6: Running | D6: React Infinity | E6: XL | F6: =_xlfn.IFS(ISBLANK(Size),"Missing",ISNUMBER(Size),"Number",ISTEXT(Size),"Alphabet") -> Alphabet | G6: =IF(Size_Type ="Missing","Unknown",TRIM(Size)) -> XL | H6: =IF(Size_Verification="Unknown","No","Yes") -> Yes | J6: =_xlfn.IFS(Units_Sold<0,"Check Return/Refund",Units_Sold=" ",Invalid,Units_Sold=0,"Available",Units_Sold>0,"Sold") -> Available | M6: =IF(OR(Discount_Applied="",Discount_Applied>1,Discount_Applied<0),"Invalid","Valid") -> Invalid | N6: =IF(PC_NikeSales[[#This Row],[Discount_Verification]]="Valid","Include","Exclude") -> Exclude | O6: 0 | P6: =IF(AND(Units_Sold<>"",MRP<>"",Discount_Applied<1),Units_Sold*MRP*(1-Discount_Applied),"Insufficient Data") -> Insufficient Data | Q6: =_xlfn.IFS(Rev_Recalc="Insufficient Data","Missing Information",Rev_Recalc<0,"Negative Revenue",Rev_Recalc=0,"No Recorded Revenue",Rev_Recalc>0,"Valid Revenue") -> Missing Information | R6: =IF(PC_NikeSales[[#This Row],[Rev_Verify]]="Valid Revenue","Include","Exclude") -> Exclude | S6: 45547 | T6: =IF(ISBLANK(Order_Date),"Missing Date",Order_Date) -> 45547 | U6: =IF(ISBLANK(Order_Date),"No","Yes") -> Yes | V6: Retail | W6: Delhi | X6: =PROPER(Region) -> Delhi | Y6: 187.89 | Z6: =IF(PC_NikeSales[[#This Row],[Profit]]<0,"Loss Making Sales",IF(PC_NikeSales[[#This Row],[Profit]]=0,"No Recorded Profit",IF($Y4>$P4,"Invalid Profit", "Valid Profit"))) -> Valid Profit | AA6: =IF(PC_NikeSales[[#This Row],[Profit_Status]]="Valid Profit","Include","Exclude") -> Include | AC6: % of Missing Dates | AD6: =(COUNTIF(OD_Status,"Missing Date")/2500)*100 -> 24.64
A7: 2005 | B7: Women | C7: Training | D7: Flex Trainer | E7: M | F7: =_xlfn.IFS(ISBLANK(Size),"Missing",ISNUMBER(Size),"Number",ISTEXT(Size),"Alphabet") -> Alphabet | G7: =IF(Size_Type ="Missing","Unknown",TRIM(Size)) -> M | H7: =IF(Size_Verification="Unknown","No","Yes") -> Yes | I7: 1 | J7: =_xlfn.IFS(Units_Sold<0,"Check Return/Refund",Units_Sold=" ",Invalid,Units_Sold=0,"Available",Units_Sold>0,"Sold") -> Sold | K7: 7363.96 | M7: =IF(OR(Discount_Applied="",Discount_Applied>1,Discount_Applied<0),"Invalid","Valid") -> Invalid | N7: =IF(PC_NikeSales[[#This Row],[Discount_Verification]]="Valid","Include","Exclude") -> Exclude | O7: 0 | P7: =IF(AND(Units_Sold<>"",MRP<>"",Discount_Applied<1),Units_Sold*MRP*(1-Discount_Applied),"Insufficient Data") -> 7363.96 | Q7: =_xlfn.IFS(Rev_Recalc="Insufficient Data","Missing Information",Rev_Recalc<0,"Negative Revenue",Rev_Recalc=0,"No Recorded Revenue",Rev_Recalc>0,"Valid Revenue") -> Valid Revenue | R7: =IF(PC_NikeSales[[#This Row],[Rev_Verify]]="Valid Revenue","Include","Exclude") -> Include | T7: =IF(ISBLANK(Order_Date),"Missing Date",Order_Date) -> Missing Date | U7: =IF(ISBLANK(Order_Date),"No","Yes") -> No | V7: Retail | W7: Delhi | X7: =PROPER(Region) -> Delhi | Y7: 1415.98 | Z7: =IF(PC_NikeSales[[#This Row],[Profit]]<0,"Loss Making Sales",IF(PC_NikeSales[[#This Row],[Profit]]=0,"No Recorded Profit",IF($Y5>$P5,"Invalid Profit", "Valid Profit"))) -> Valid Profit | AA7: =IF(PC_NikeSales[[#This Row],[Profit_Status]]="Valid Profit","Include","Exclude") -> Include | AC7: % of Invalid Discounts | AD7: =(COUNTIF(M:M,"Invalid")/ROWS(Order_ID))*100 -> 73.92
A8: 2006 | B8: Men | C8: Training | D8: SuperRep Go | E8: M | F8: =_xlfn.IFS(ISBLANK(Size),"Missing",ISNUMBER(Size),"Number",ISTEXT(Size),"Alphabet") -> Alphabet | G8: =IF(Size_Type ="Missing","Unknown",TRIM(Size)) -> M | H8: =IF(Size_Verification="Unknown","No","Yes") -> Yes | J8: =_xlfn.IFS(Units_Sold<0,"Check Return/Refund",Units_Sold=" ",Invalid,Units_Sold=0,"Available",Units_Sold>0,"Sold") -> Available | K8: 6819.78 | M8: =IF(OR(Discount_Applied="",Discount_Applied>1,Discount_Applied<0),"Invalid","Valid") -> Invalid | N8: =IF(PC_NikeSales[[#This Row],[Discount_Verification]]="Valid","Include","Exclude") -> Exclude | O8: 0 | P8: =IF(AND(Units_Sold<>"",MRP<>"",Discount_Applied<1),Units_Sold*MRP*(1-Discount_Applied),"Insufficient Data") -> Insufficient Data | Q8: =_xlfn.IFS(Rev_Recalc="Insufficient Data","Missing Information",Rev_Recalc<0,"Negative Revenue",Rev_Recalc=0,"No Recorded Revenue",Rev_Recalc>0,"Valid Revenue") -> Missing Information | R8: =IF(PC_NikeSales[[#This Row],[Rev_Verify]]="Valid Revenue","Include","Exclude") -> Exclude | S8: 45812 | T8: =IF(ISBLANK(Order_Date),"Missing Date",Order_Date) -> 45812 | U8: =IF(ISBLANK(Order_Date),"No","Yes") -> Yes | V8: Online | W8: Bangalore | X8: =PROPER(Region) -> Bangalore | Y8: 1802.09 | Z8: =IF(PC_NikeSales[[#This Row],[Profit]]<0,"Loss Making Sales",IF(PC_NikeSales[[#This Row],[Profit]]=0,"No Recorded Profit",IF($Y6>$P6,"Invalid Profit", "Valid Profit"))) -> Valid Profit | AA8: =IF(PC_NikeSales[[#This Row],[Profit_Status]]="Valid Profit","Include","Exclude") -> Include | AC8: % of Included Rows | AD8: =(ROWS(CleanedSales)/2500)*100 -> 1.68
A9: 2007 | B9: Kids | C9: Training | D9: SuperRep Go | E9: M | F9: =_xlfn.IFS(ISBLANK(Size),"Missing",ISNUMBER(Size),"Number",ISTEXT(Size),"Alphabet") -> Alphabet | G9: =IF(Size_Type ="Missing","Unknown",TRIM(Size)) -> M | H9: =IF(Size_Verification="Unknown","No","Yes") -> Yes | I9: 1 | J9: =_xlfn.IFS(Units_Sold<0,"Check Return/Refund",Units_Sold=" ",Invalid,Units_Sold=0,"Available",Units_Sold>0,"Sold") -> Sold | L9: 0.32 | M9: =IF(OR(Discount_Applied="",Discount_Applied>1,Discount_Applied<0),"Invalid","Valid") -> Valid | N9: =IF(PC_NikeSales[[#This Row],[Discount_Verification]]="Valid","Include","Exclude") -> Include | O9: 0 | P9: =IF(AND(Units_Sold<>"",MRP<>"",Discount_Applied<1),Units_Sold*MRP*(1-Discount_Applied),"Insufficient Data") -> Insufficient Data | Q9: =_xlfn.IFS(Rev_Recalc="Insufficient Data","Missing Information",Rev_Recalc<0,"Negative Revenue",Rev_Recalc=0,"No Recorded Revenue",Rev_Recalc>0,"Valid Revenue") -> Missing Information | R9: =IF(PC_NikeSales[[#This Row],[Rev_Verify]]="Valid Revenue","Include","Exclude") -> Exclude | T9: =IF(ISBLANK(Order_Date),"Missing Date",Order_Date) -> Missing Date | U9: =IF(ISBLANK(Order_Date),"No","Yes") -> No | V9: Retail | W9: Bangalore | X9: =PROPER(Region) -> Bangalore | Y9: 2928.36 | Z9: =IF(PC_NikeSales[[#This Row],[Profit]]<0,"Loss Making Sales",IF(PC_NikeSales[[#This Row],[Profit]]=0,"No Recorded Profit",IF($Y7>$P7,"Invalid Profit", "Valid Profit"))) -> Valid Profit | AA9: =IF(PC_NikeSales[[#This Row],[Profit_Status]]="Valid Profit","Include","Exclude") -> Include | AC9: Total Original Rows | AD9: =ROWS(Order_ID) -> 2500
A10: 2008 | B10: Women | C10: Soccer | D10: Premier III | E10: 11 | F10: =_xlfn.IFS(ISBLANK(Size),"Missing",ISNUMBER(Size),"Number",ISTEXT(Size),"Alphabet") -> Number | G10: =IF(Size_Type ="Missing","Unknown",TRIM(Size)) -> 11 | H10: =IF(Size_Verification="Unknown","No","Yes") -> Yes | I10: -1 | J10: =_xlfn.IFS(Units_Sold<0,"Check Return/Refund",Units_Sold=" ",Invalid,Units_Sold=0,"Available",Units_Sold>0,"Sold") -> Check Return/Refund | M10: =IF(OR(Discount_Applied="",Discount_Applied>1,Discount_Applied<0),"Invalid","Valid") -> Invalid | N10: =IF(PC_NikeSales[[#This Row],[Discount_Verification]]="Valid","Include","Exclude") -> Exclude | O10: 0 | P10: =IF(AND(Units_Sold<>"",MRP<>"",Discount_Applied<1),Units_Sold*MRP*(1-Discount_Applied),"Insufficient Data") -> Insufficient Data | Q10: =_xlfn.IFS(Rev_Recalc="Insufficient Data","Missing Information",Rev_Recalc<0,"Negative Revenue",Rev_Recalc=0,"No Recorded Revenue",Rev_Recalc>0,"Valid Revenue") -> Missing Information | R10: =IF(PC_NikeSales[[#This Row],[Rev_Verify]]="Valid Revenue","Include","Exclude") -> Exclude | S10: 45576 | T10: =IF(ISBLANK(Order_Date),"Missing Date",Order_Date) -> 45576 | U10: =IF(ISBLANK(Order_Date),"No","Yes") -> Yes | V10: Online | W10: Hyderabad | X10: =PROPER(Region) -> Hyderabad | Y10: -731.18 | Z10: =IF(PC_NikeSales[[#This Row],[Profit]]<0,"Loss Making Sales",IF(PC_NikeSales[[#This Row],[Profit]]=0,"No Recorded Profit",IF(PC_NikeSales[[#This Row],[Profit]]>PC_NikeSales[Rev_Recalc],"Invalid Profit", "Valid Profit"))) -> Loss Making Sales | AA10: =IF(PC_NikeSales[[#This Row],[Profit_Status]]="Valid Profit","Include","Exclude") -> Exclude
A11: 2009 | B11: Men | C11: Soccer | D11: Mercurial Superfly | E11: M | F11: =_xlfn.IFS(ISBLANK(Size),"Missing",ISNUMBER(Size),"Number",ISTEXT(Size),"Alphabet") -> Alphabet | G11: =IF(Size_Type ="Missing","Unknown",TRIM(Size)) -> M | H11: =IF(Size_Verification="Unknown","No","Yes") -> Yes | I11: 4 | J11: =_xlfn.IFS(Units_Sold<0,"Check Return/Refund",Units_Sold=" ",Invalid,Units_Sold=0,"Available",Units_Sold>0,"Sold") -> Sold | M11: =IF(OR(Discount_Applied="",Discount_Applied>1,Discount_Applied<0),"Invalid","Valid") -> Invalid | N11: =IF(PC_NikeSales[[#This Row],[Discount_Verification]]="Valid","Include","Exclude") -> Exclude | O11: 0 | P11: =IF(AND(Units_Sold<>"",MRP<>"",Discount_Applied<1),Units_Sold*MRP*(1-Discount_Applied),"Insufficient Data") -> Insufficient Data | Q11: =_xlfn.IFS(Rev_Recalc="Insufficient Data","Missing Information",Rev_Recalc<0,"Negative Revenue",Rev_Recalc=0,"No Recorded Revenue",Rev_Recalc>0,"Valid Revenue") -> Missing Information | R11: =IF(PC_NikeSales[[#This Row],[Rev_Verify]]="Valid Revenue","Include","Exclude") -> Exclude | T11: =IF(ISBLANK(Order_Date),"Missing Date",Order_Date) -> Missing Date | U11: =IF(ISBLANK(Order_Date),"No","Yes") -> No | V11: Online | W11: Pune | X11: =PROPER(Region) -> Pune | Y11: 3929.61 | Z11: =IF(PC_NikeSales[[#This Row],[Profit]]<0,"Loss Making Sales",IF(PC_NikeSales[[#This Row],[Profit]]=0,"No Recorded Profit",IF($Y9>$P9,"Invalid Profit", "Valid Profit"))) -> Valid Profit | AA11: =IF(PC_NikeSales[[#This Row],[Profit_Status]]="Valid Profit","Include","Exclude") -> Include
A12: 2010 | B12: Kids | C12: Lifestyle | D12: Waffle One | E12: L | F12: =_xlfn.IFS(ISBLANK(Size),"Missing",ISNUMBER(Size),"Number",ISTEXT(Size),"Alphabet") -> Alphabet | G12: =IF(Size_Type ="Missing","Unknown",TRIM(Size)) -> L | H12: =IF(Size_Verification="Unknown","No","Yes") -> Yes | I12: 1 | J12: =_xlfn.IFS(Units_Sold<0,"Check Return/Refund",Units_Sold=" ",Invalid,Units_Sold=0,"Available",Units_Sold>0,"Sold") -> Sold | K12: 7949.83 | M12: =IF(OR(Discount_Applied="",Discount_Applied>1,Discount_Applied<0),"Invalid","Valid") -> Invalid | N12: =IF(PC_NikeSales[[#This Row],[Discount_Verification]]="Valid","Include","Exclude") -> Exclude | O12: 0 | P12: =IF(AND(Units_Sold<>"",MRP<>"",Discount_Applied<1),Units_Sold*MRP*(1-Discount_Applied),"Insufficient Data") -> 7949.83 | Q12: =_xlfn.IFS(Rev_Recalc="Insufficient Data","Missing Information",Rev_Recalc<0,"Negative Revenue",Rev_Recalc=0,"No Recorded Revenue",Rev_Recalc>0,"Valid Revenue") -> Valid Revenue | R12: =IF(PC_NikeSales[[#This Row],[Rev_Verify]]="Valid Revenue","Include","Exclude") -> Include | S12: 45673 | T12: =IF(ISBLANK(Order_Date),"Missing Date",Order_Date) -> 45673 | U12: =IF(ISBLANK(Order_Date),"No","Yes") -> Yes | V12: Online | W12: Pune | X12: =PROPER(Region) -> Pune | Y12: 1965.56 | Z12: =IF(PC_NikeSales[[#This Row],[Profit]]<0,"Loss Making Sales",IF(PC_NikeSales[[#This Row],[Profit]]=0,"No Recorded Profit",IF($Y10>$P10,"Invalid Profit", "Valid Profit"))) -> Valid Profit | AA12: =IF(PC_NikeSales[[#This Row],[Profit_Status]]="Valid Profit","Include","Exclude") -> Include
A13: 2011 | B13: Women | C13: Training | D13: Flex Trainer | E13: L | F13: =_xlfn.IFS(ISBLANK(Size),"Missing",ISNUMBER(Size),"Number",ISTEXT(Size),"Alphabet") -> Alphabet | G13: =IF(Size_Type ="Missing","Unknown",TRIM(Size)) -> L | H13: =IF(Size_Verification="Unknown","No","Yes") -> Yes | I13: -1 | J13: =_xlfn.IFS(Units_Sold<0,"Check Return/Refund",Units_Sold=" ",Invalid,Units_Sold=0,"Available",Units_Sold>0,"Sold") -> Check Return/Refund | K13: 9586.08 | M13: =IF(OR(Discount_Applied="",Discount_Applied>1,Discount_Applied<0),"Invalid","Valid") -> Invalid | N13: =IF(PC_NikeSales[[#This Row],[Discount_Verification]]="Valid","Include","Exclude") -> Exclude | O13: 0 | P13: =IF(AND(Units_Sold<>"",MRP<>"",Discount_Applied<1),Units_Sold*MRP*(1-Discount_Applied),"Insufficient Data") -> -9586.08 | Q13: =_xlfn.IFS(Rev_Recalc="Insufficient Data","Missing Information",Rev_Recalc<0,"Negative Revenue",Rev_Recalc=0,"No Recorded Revenue",Rev_Recalc>0,"Valid Revenue") -> Negative Revenue | R13: =IF(PC_NikeSales[[#This Row],[Rev_Verify]]="Valid Revenue","Include","Exclude") -> Exclude | T13: =IF(ISBLANK(Order_Date),"Missing Date",Order_Date) -> Missing Date | U13: =IF(ISBLANK(Order_Date),"No","Yes") -> No | V13: Retail | W13: Hyderabad | X13: =PROPER(Region) -> Hyderabad | Y13: 1667.08 | Z13: =IF(PC_NikeSales[[#This Row],[Profit]]<0,"Loss Making Sales",IF(PC_NikeSales[[#This Row],[Profit]]=0,"No Recorded Profit",IF(PC_NikeSales[[#This Row],[Profit]]>PC_NikeSales[Rev_Recalc],"Invalid Profit", "Valid Profit"))) -> Invalid Profit | AA13: =IF(PC_NikeSales[[#This Row],[Profit_Status]]="Valid Profit","Include","Exclude") -> Exclude
A14: 2018 | B14: Kids | C14: Lifestyle | D14: Blazer Mid | F14: =_xlfn.IFS(ISBLANK(Size),"Missing",ISNUMBER(Size),"Number",ISTEXT(Size),"Alphabet") -> Missing | G14: =IF(Size_Type ="Missing","Unknown",TRIM(Size)) -> Unknown | H14: =IF(Size_Verification="Unknown","No","Yes") -> No | I14: -1 | J14: =_xlfn.IFS(Units_Sold<0,"Check Return/Refund",Units_Sold=" ",Invalid,Units_Sold=0,"Available",Units_Sold>0,"Sold") -> Check Return/Refund | L14: 0.86 | M14: =IF(OR(Discount_Applied="",Discount_Applied>1,Discount_Applied<0),"Invalid","Valid") -> Valid | N14: =IF(PC_NikeSales[[#This Row],[Discount_Verification]]="Valid","Include","Exclude") -> Include | O14: 0 | P14: =IF(AND(Units_Sold<>"",MRP<>"",Discount_Applied<1),Units_Sold*MRP*(1-Discount_Applied),"Insufficient Data") -> Insufficient Data | Q14: =_xlfn.IFS(Rev_Recalc="Insufficient Data","Missing Information",Rev_Recalc<0,"Negative Revenue",Rev_Recalc=0,"No Recorded Revenue",Rev_Recalc>0,"Valid Revenue") -> Missing Information | R14: =IF(PC_NikeSales[[#This Row],[Rev_Verify]]="Valid Revenue","Include","Exclude") -> Exclude | S14: 45609 | T14: =IF(ISBLANK(Order_Date),"Missing Date",Order_Date) -> 45609 | U14: =IF(ISBLANK(Order_Date),"No","Yes") -> Yes | V14: Online | W14: Delhi | X14: =PROPER(Region) -> Delhi | Y14: 2109.48 | Z14: =IF(PC_NikeSales[[#This Row],[Profit]]<0,"Loss Making Sales",IF(PC_NikeSales[[#This Row],[Profit]]=0,"No Recorded Profit",IF($Y12>$P12,"Invalid Profit", "Valid Profit"))) -> Valid Profit | AA14: =IF(PC_NikeSales[[#This Row],[Profit_Status]]="Valid Profit","Include","Exclude") -> Include
A15: 2013 | B15: Kids | C15: Training | D15: SuperRep Go | F15: =_xlfn.IFS(ISBLANK(Size),"Missing",ISNUMBER(Size),"Number",ISTEXT(Size),"Alphabet") -> Missing | G15: =IF(Size_Type ="Missing","Unknown",TRIM(Size)) -> Unknown | H15: =IF(Size_Verification="Unknown","No","Yes") -> No | J15: =_xlfn.IFS(Units_Sold<0,"Check Return/Refund",Units_Sold=" ",Invalid,Units_Sold=0,"Available",Units_Sold>0,"Sold") -> Available | K15: 9671.05 | M15: =IF(OR(Discount_Applied="",Discount_Applied>1,Discount_Applied<0),"Invalid","Valid") -> Invalid | N15: =IF(PC_NikeSales[[#This Row],[Discount_Verification]]="Valid","Include","Exclude") -> Exclude | O15: 0 | P15: =IF(AND(Units_Sold<>"",MRP<>"",Discount_Applied<1),Units_Sold*MRP*(1-Discount_Applied),"Insufficient Data") -> Insufficient Data | Q15: =_xlfn.IFS(Rev_Recalc="Insufficient Data","Missing Information",Rev_Recalc<0,"Negative Revenue",Rev_Recalc=0,"No Recorded Revenue",Rev_Recalc>0,"Valid Revenue") -> Missing Information | R15: =IF(PC_NikeSales[[#This Row],[Rev_Verify]]="Valid Revenue","Include","Exclude") -> Exclude | S15: 45554 | T15: =IF(ISBLANK(Order_Date),"Missing Date",Order_Date) -> 45554 | U15: =IF(ISBLANK(Order_Date),"No","Yes") -> Yes | V15: Online | W15: Hyderabad | X15: =PROPER(Region) -> Hyderabad | Y15: 299.34 | Z15: =IF(PC_NikeSales[[#This Row],[Profit]]<0,"Loss Making Sales",IF(PC_NikeSales[[#This Row],[Profit]]=0,"No Recorded Profit",IF($Y13>$P13,"Invalid Profit", "Valid Profit"))) -> Invalid Profit | AA15: =IF(PC_NikeSales[[#This Row],[Profit_Status]]="Valid Profit","Include","Exclude") -> Exclude
A16: 2014 | B16: Women | C16: Running | D16: React Infinity | E16: 11 | F16: =_xlfn.IFS(ISBLANK(Size),"Missing",ISNUMBER(Size),"Number",ISTEXT(Size),"Alphabet") -> Number | G16: =IF(Size_Type ="Missing","Unknown",TRIM(Size)) -> 11 | H16: =IF(Size_Verification="Unknown","No","Yes") -> Yes | J16: =_xlfn.IFS(Units_Sold<0,"Check Return/Refund",Units_Sold=" ",Invalid,Units_Sold=0,"Available",Units_Sold>0,"Sold") -> Available | M16: =IF(OR(Discount_Applied="",Discount_Applied>1,Discount_Applied<0),"Invalid","Valid") -> Invalid | N16: =IF(PC_NikeSales[[#This Row],[Discount_Verification]]="Valid","Include","Exclude") -> Exclude | O16: 0 | P16: =IF(AND(Units_Sold<>"",MRP<>"",Discount_Applied<1),Units_Sold*MRP*(1-Discount_Applied),"Insufficient Data") -> Insufficient Data | Q16: =_xlfn.IFS(Rev_Recalc="Insufficient Data","Missing Information",Rev_Recalc<0,"Negative Revenue",Rev_Recalc=0,"No Recorded Revenue",Rev_Recalc>0,"Valid Revenue") -> Missing Information | R16: =IF(PC_NikeSales[[#This Row],[Rev_Verify]]="Valid Revenue","Include","Exclude") -> Exclude | S16: 45759 | T16: =IF(ISBLANK(Order_Date),"Missing Date",Order_Date) -> 45759 | U16: =IF(ISBLANK(Order_Date),"No","Yes") -> Yes | V16: Online | W16: Bangalore | X16: =PROPER(Region) -> Bangalore | Y16: -1044.4 | Z16: =IF(PC_NikeSales[[#This Row],[Profit]]<0,"Loss Making Sales",IF(PC_NikeSales[[#This Row],[Profit]]=0,"No Recorded Profit",IF(PC_NikeSales[[#This Row],[Profit]]>PC_NikeSales[Rev_Recalc],"Invalid Profit", "Valid Profit"))) -> Loss Making Sales | AA16: =IF(PC_NikeSales[[#This Row],[Profit_Status]]="Valid Profit","Include","Exclude") -> Exclude
A17: 2015 | B17: Kids | C17: Basketball | D17: Air Jordan | F17: =_xlfn.IFS(ISBLANK(Size),"Missing",ISNUMBER(Size),"Number",ISTEXT(Size),"Alphabet") -> Missing | G17: =IF(Size_Type ="Missing","Unknown",TRIM(Size)) -> Unknown | H17: =IF(Size_Verification="Unknown","No","Yes") -> No | J17: =_xlfn.IFS(Units_Sold<0,"Check Return/Refund",Units_Sold=" ",Invalid,Units_Sold=0,"Available",Units_Sold>0,"Sold") -> Available | K17: 3285.52 | M17: =IF(OR(Discount_Applied="",Discount_Applied>1,Discount_Applied<0),"Invalid","Valid") -> Invalid | N17: =IF(PC_NikeSales[[#This Row],[Discount_Verification]]="Valid","Include","Exclude") -> Exclude | O17: 0 | P17: =IF(AND(Units_Sold<>"",MRP<>"",Discount_Applied<1),Units_Sold*MRP*(1-Discount_Applied),"Insufficient Data") -> Insufficient Data | Q17: =_xlfn.IFS(Rev_Recalc="Insufficient Data","Missing Information",Rev_Recalc<0,"Negative Revenue",Rev_Recalc=0,"No Recorded Revenue",Rev_Recalc>0,"Valid Revenue") -> Missing Information | R17: =IF(PC_NikeSales[[#This Row],[Rev_Verify]]="Valid Revenue","Include","Exclude") -> Exclude | S17: 45808 | T17: =IF(ISBLANK(Order_Date),"Missing Date",Order_Date) -> 45808 | U17: =IF(ISBLANK(Order_Date),"No","Yes") -> Yes | V17: Retail | W17: Kolkata | X17: =PROPER(Region) -> Kolkata | Y17: 1193.21 | Z17: =IF(PC_NikeSales[[#This Row],[Profit]]<0,"Loss Making Sales",IF(PC_NikeSales[[#This Row],[Profit]]=0,"No Recorded Profit",IF($Y15>$P15,"Invalid Profit", "Valid Profit"))) -> Valid Profit | AA17: =IF(PC_NikeSales[[#This Row],[Profit_Status]]="Valid Profit","Include","Exclude") -> Include
A18: 2016 | B18: Women | C18: Basketball | D18: Air Jordan | E18: M | F18: =_xlfn.IFS(ISBLANK(Size),"Missing",ISNUMBER(Size),"Number",ISTEXT(Size),"Alphabet") -> Alphabet | G18: =IF(Size_Type ="Missing","Unknown",TRIM(Size)) -> M | H18: =IF(Size_Verification="Unknown","No","Yes") -> Yes | I18: 1 | J18: =_xlfn.IFS(Units_Sold<0,"Check Return/Refund",Units_Sold=" ",Invalid,Units_Sold=0,"Available",Units_Sold>0,"Sold") -> Sold | K18: 9871.75 | L18: 0.3 | M18: =IF(OR(Discount_Applied="",Discount_Applied>1,Discount_Applied<0),"Invalid","Valid") -> Valid | N18: =IF(PC_NikeSales[[#This Row],[Discount_Verification]]="Valid","Include","Exclude") -> Include | O18: 6910.22 | P18: =IF(AND(Units_Sold<>"",MRP<>"",Discount_Applied<1),Units_Sold*MRP*(1-Discount_Applied),"Insufficient Data") -> 6910.225 | Q18: =_xlfn.IFS(Rev_Recalc="Insufficient Data","Missing Information",Rev_Recalc<0,"Negative Revenue",Rev_Recalc=0,"No Recorded Revenue",Rev_Recalc>0,"Valid Revenue") -> Valid Revenue | R18: =IF(PC_NikeSales[[#This Row],[Rev_Verify]]="Valid Revenue","Include","Exclude") -> Include | T18: =IF(ISBLANK(Order_Date),"Missing Date",Order_Date) -> Missing Date | U18: =IF(ISBLANK(Order_Date),"No","Yes") -> No | V18: Retail | W18: Hyderabad | X18: =PROPER(Region) -> Hyderabad | Y18: 2452.69 | Z18: =IF(PC_NikeSales[[#This Row],[Profit]]<0,"Loss Making Sales",IF(PC_NikeSales[[#This Row],[Profit]]=0,"No Recorded Profit",IF($Y16>$P16,"Invalid Profit", "Valid Profit"))) -> Valid Profit | AA18: =IF(PC_NikeSales[[#This Row],[Profit_Status]]="Valid Profit","Include","Exclude") -> Include
A19: 2017 | B19: Women | C19: Basketball | D19: Air Jordan | E19: 9 | F19: =_xlfn.IFS(ISBLANK(Size),"Missing",ISNUMBER(Size),"Number",ISTEXT(Size),"Alphabet") -> Number | G19: =IF(Size_Type ="Missing","Unknown",TRIM(Size)) -> 9 | H19: =IF(Size_Verification="Unknown","No","Yes") -> Yes | I19: 4 | J19: =_xlfn.IFS(Units_Sold<0,"Check Return/Refund",Units_Sold=" ",Invalid,Units_Sold=0,"Available",Units_Sold>0,"Sold") -> Sold | M19: =IF(OR(Discount_Applied="",Discount_Applied>1,Discount_Applied<0),"Invalid","Valid") -> Invalid | N19: =IF(PC_NikeSales[[#This Row],[Discount_Verification]]="Valid","Include","Exclude") -> Exclude | O19: 0 | P19: =IF(AND(Units_Sold<>"",MRP<>"",Discount_Applied<1),Units_Sold*MRP*(1-Discount_Applied),"Insufficient Data") -> Insufficient Data | Q19: =_xlfn.IFS(Rev_Recalc="Insufficient Data","Missing Information",Rev_Recalc<0,"Negative Revenue",Rev_Recalc=0,"No Recorded Revenue",Rev_Recalc>0,"Valid Revenue") -> Missing Information | R19: =IF(PC_NikeSales[[#This Row],[Rev_Verify]]="Valid Revenue","Include","Exclude") -> Exclude | S19: 45733 | T19: =IF(ISBLANK(Order_Date),"Missing Date",Order_Date) -> 45733 | U19: =IF(ISBLANK(Order_Date),"No","Yes") -> Yes | V19: Retail | W19: Delhi | X19: =PROPER(Region) -> Delhi | Y19: 1946.24 | Z19: =IF(PC_NikeSales[[#This Row],[Profit]]<0,"Loss Making Sales",IF(PC_NikeSales[[#This Row],[Profit]]=0,"No Recorded Profit",IF($Y17>$P17,"Invalid Profit", "Valid Profit"))) -> Valid Profit | AA19: =IF(PC_NikeSales[[#This Row],[Profit_Status]]="Valid Profit","Include","Exclude") -> Include
A20: 2018 | B20: Men | C20: Training | D20: Metcon 7 | E20: XL | F20: =_xlfn.IFS(ISBLANK(Size),"Missing",ISNUMBER(Size),"Number",ISTEXT(Size),"Alphabet") -> Alphabet | G20: =IF(Size_Type ="Missing","Unknown",TRIM(Size)) -> XL | H20: =IF(Size_Verification="Unknown","No","Yes") -> Yes | I20: 0 | J20: =_xlfn.IFS(Units_Sold<0,"Check Return/Refund",Units_Sold=" ",Invalid,Units_Sold=0,"Available",Units_Sold>0,"Sold") -> Available | L20: 1.17 | M20: =IF(OR(Discount_Applied="",Discount_Applied>1,Discount_Applied<0),"Invalid","Valid") -> Invalid | N20: =IF(PC_NikeSales[[#This Row],[Discount_Verification]]="Valid","Include","Exclude") -> Exclude | O20: 0 | P20: =IF(AND(Units_Sold<>"",MRP<>"",Discount_Applied<1),Units_Sold*MRP*(1-Discount_Applied),"Insufficient Data") -> Insufficient Data | Q20: =_xlfn.IFS(Rev_Recalc="Insufficient Data","Missing Information",Rev_Recalc<0,"Negative Revenue",Rev_Recalc=0,"No Recorded Revenue",Rev_Recalc>0,"Valid Revenue") -> Missing Information | R20: =IF(PC_NikeSales[[#This Row],[Rev_Verify]]="Valid Revenue","Include","Exclude") -> Exclude | T20: =IF(ISBLANK(Order_Date),"Missing Date",Order_Date) -> Missing Date | U20: =IF(ISBLANK(Order_Date),"No","Yes") -> No | V20: Online | W20: bengaluru | X20: =PROPER(Region) -> Bengaluru | Y20: -966.89 | Z20: =IF(PC_NikeSales[[#This Row],[Profit]]<0,"Loss Making Sales",IF(PC_NikeSales[[#This Row],[Profit]]=0,"No Recorded Profit",IF(PC_NikeSales[[#This Row],[Profit]]>PC_NikeSales[Rev_Recalc],"Invalid Profit", "Valid Profit"))) -> Loss Making Sales | AA20: =IF(PC_NikeSales[[#This Row],[Profit_Status]]="Valid Profit","Include","Exclude") -> Exclude
A21: 2019 | B21: Kids | C21: Running | D21: Air Zoom | E21: 6 | F21: =_xlfn.IFS(ISBLANK(Size),"Missing",ISNUMBER(Size),"Number",ISTEXT(Size),"Alphabet") -> Number | G21: =IF(Size_Type ="Missing","Unknown",TRIM(Size)) -> 6 | H21: =IF(Size_Verification="Unknown","No","Yes") -> Yes | I21: 0 | J21: =_xlfn.IFS(Units_Sold<0,"Check Return/Refund",Units_Sold=" ",Invalid,Units_Sold=0,"Available",Units_Sold>0,"Sold") -> Available | K21: 3424.06 | L21: 0.32 | M21: =IF(OR(Discount_Applied="",Discount_Applied>1,Discount_Applied<0),"Invalid","Valid") -> Valid | N21: =IF(PC_NikeSales[[#This Row],[Discount_Verification]]="Valid","Include","Exclude") -> Include | O21: 0 | P21: =IF(AND(Units_Sold<>"",MRP<>"",Discount_Applied<1),Units_Sold*MRP*(1-Discount_Applied),"Insufficient Data") -> 0 | Q21: =_xlfn.IFS(Rev_Recalc="Insufficient Data","Missing Information",Rev_Recalc<0,"Negative Revenue",Rev_Recalc=0,"No Recorded Revenue",Rev_Recalc>0,"Valid Revenue") -> No Recorded Revenue | R21: =IF(PC_NikeSales[[#This Row],[Rev_Verify]]="Valid Revenue","Include","Exclude") -> Exclude | S21: 45674 | T21: =IF(ISBLANK(Order_Date),"Missing Date",Order_Date) -> 45674 | U21: =IF(ISBLANK(Order_Date),"No","Yes") -> Yes | V21: Online | W21: Hyderabad | X21: =PROPER(Region) -> Hyderabad | Y21: 1915.24 | Z21: =IF(PC_NikeSales[[#This Row],[Profit]]<0,"Loss Making Sales",IF(PC_NikeSales[[#This Row],[Profit]]=0,"No Recorded Profit",IF(PC_NikeSales[[#This Row],[Profit]]>PC_NikeSales[Rev_Recalc],"Invalid Profit", "Valid Profit"))) -> Invalid Profit | AA21: =IF(PC_NikeSales[[#This Row],[Profit_Status]]="Valid Profit","Include","Exclude") -> Exclude
A22: 2020 | B22: Kids | C22: Soccer | D22: Tiempo Legend | E22: L | F22: =_xlfn.IFS(ISBLANK(Size),"Missing",ISNUMBER(Size),"Number",ISTEXT(Size),"Alphabet") -> Alphabet | G22: =IF(Size_Type ="Missing","Unknown",TRIM(Size)) -> L | H22: =IF(Size_Verification="Unknown","No","Yes") -> Yes | I22: -1 | J22: =_xlfn.IFS(Units_Sold<0,"Check Return/Refund",Units_Sold=" ",Invalid,Units_Sold=0,"Available",Units_Sold>0,"Sold") -> Check Return/Refund | L22: 0.67 | M22: =IF(OR(Discount_Applied="",Discount_Applied>1,Discount_Applied<0),"Invalid","Valid") -> Valid | N22: =IF(PC_NikeSales[[#This Row],[Discount_Verification]]="Valid","Include","Exclude") -> Include | O22: 0 | P22: =IF(AND(Units_Sold<>"",MRP<>"",Discount_Applied<1),Units_Sold*MRP*(1-Discount_Applied),"Insufficient Data") -> Insufficient Data | Q22: =_xlfn.IFS(Rev_Recalc="Insufficient Data","Missing Information",Rev_Recalc<0,"Negative Revenue",Rev_Recalc=0,"No Recorded Revenue",Rev_Recalc>0,"Valid Revenue") -> Missing Information | R22: =IF(PC_NikeSales[[#This Row],[Rev_Verify]]="Valid Revenue","Include","Exclude") -> Exclude | S22: 45744 | T22: =IF(ISBLANK(Order_Date),"Missing Date",Order_Date) -> 45744 | U22: =IF(ISBLANK(Order_Date),"No","Yes") -> Yes | V22: Retail | W22: Mumbai | X22: =PROPER(Region) -> Mumbai | Y22: 439.96 | Z22: =IF(PC_NikeSales[[#This Row],[Profit]]<0,"Loss Making Sales",IF(PC_NikeSales[[#This Row],[Profit]]=0,"No Recorded Profit",IF($Y20>$P20,"Invalid Profit", "Valid Profit"))) -> Valid Profit | AA22: =IF(PC_NikeSales[[#This Row],[Profit_Status]]="Valid Profit","Include","Exclude") -> Include
A23: 2021 | B23: Men | C23: Running | D23: Free RN | E23: L | F23: =_xlfn.IFS(ISBLANK(Size),"Missing",ISNUMBER(Size),"Number",ISTEXT(Size),"Alphabet") -> Alphabet | G23: =IF(Size_Type ="Missing","Unknown",TRIM(Size)) -> L | H23: =IF(Size_Verification="Unknown","No","Yes") -> Yes | I23: -1 | J23: =_xlfn.IFS(Units_Sold<0,"Check Return/Refund",Units_Sold=" ",Invalid,Units_Sold=0,"Available",Units_Sold>0,"Sold") -> Check Return/Refund | K23: 7086.7 | L23: 0.66 | M23: =IF(OR(Discount_Applied="",Discount_Applied>1,Discount_Applied<0),"Invalid","Valid") -> Valid | N23: =IF(PC_NikeSales[[#This Row],[Discount_Verification]]="Valid","Include","Exclude") -> Include | O23: -2409.48 | P23: =IF(AND(Units_Sold<>"",MRP<>"",Discount_Applied<1),Units_Sold*MRP*(1-Discount_Applied),"Insufficient Data") -> -2409.478 | Q23: =_xlfn.IFS(Rev_Recalc="Insufficient Data","Missing Information",Rev_Recalc<0,"Negative Revenue",Rev_Recalc=0,"No Recorded Revenue",Rev_Recalc>0,"Valid Revenue") -> Negative Revenue | R23: =IF(PC_NikeSales[[#This Row],[Rev_Verify]]="Valid Revenue","Include","Exclude") -> Exclude | S23: 45615 | T23: =IF(ISBLANK(Order_Date),"Missing Date",Order_Date) -> 45615 | U23: =IF(ISBLANK(Order_Date),"No","Yes") -> Yes | V23: Retail | W23: Hyderabad | X23: =PROPER(Region) -> Hyderabad | Y23: -1120.49 | Z23: =IF(PC_NikeSales[[#This Row],[Profit]]<0,"Loss Making Sales",IF(PC_NikeSales[[#This Row],[Profit]]=0,"No Recorded Profit",IF(PC_NikeSales[[#This Row],[Profit]]>PC_NikeSales[Rev_Recalc],"Invalid Profit", "Valid Profit"))) -> Loss Making Sales | AA23: =IF(PC_NikeSales[[#This Row],[Profit_Status]]="Valid Profit","Include","Exclude") -> Exclude
A24: 2022 | B24: Women | C24: Soccer | D24: Premier III | E24: M | F24: =_xlfn.IFS(ISBLANK(Size),"Missing",ISNUMBER(Size),"Number",ISTEXT(Size),"Alphabet") -> Alphabet | G24: =IF(Size_Type ="Missing","Unknown",TRIM(Size)) -> M | H24: =IF(Size_Verification="Unknown","No","Yes") -> Yes | J24: =_xlfn.IFS(Units_Sold<0,"Check Return/Refund",Units_Sold=" ",Invalid,Units_Sold=0,"Available",Units_Sold>0,"Sold") -> Available | M24: =IF(OR(Discount_Applied="",Discount_Applied>1,Discount_Applied<0),"Invalid","Valid") -> Invalid | N24: =IF(PC_NikeSales[[#This Row],[Discount_Verification]]="Valid","Include","Exclude") -> Exclude | O24: 0 | P24: =IF(AND(Units_Sold<>"",MRP<>"",Discount_Applied<1),Units_Sold*MRP*(1-Discount_Applied),"Insufficient Data") -> Insufficient Data | Q24: =_xlfn.IFS(Rev_Recalc="Insufficient Data","Missing Information",Rev_Recalc<0,"Negative Revenue",Rev_Recalc=0,"No Recorded Revenue",Rev_Recalc>0,"Valid Revenue") -> Missing Information | R24: =IF(PC_NikeSales[[#This Row],[Rev_Verify]]="Valid Revenue","Include","Exclude") -> Exclude | S24: 45559 | T24: =IF(ISBLANK(Order_Date),"Missing Date",Order_Date) -> 45559 | U24: =IF(ISBLANK(Order_Date),"No","Yes") -> Yes | V24: Online | W24: Pune | X24: =PROPER(Region) -> Pune | Y24: 3427.16 | Z24: =IF(PC_NikeSales[[#This Row],[Profit]]<0,"Loss Making Sales",IF(PC_NikeSales[[#This Row],[Profit]]=0,"No Recorded Profit",IF($Y22>$P22,"Invalid Profit", "Valid Profit"))) -> Valid Profit | AA24: =IF(PC_NikeSales[[#This Row],[Profit_Status]]="Valid Profit","Include","Exclude") -> Include
A25: 2023 | B25: Men | C25: Lifestyle | D25: Waffle One | E25: M | F25: =_xlfn.IFS(ISBLANK(Size),"Missing",ISNUMBER(Size),"Number",ISTEXT(Size),"Alphabet") -> Alphabet | G25: =IF(Size_Type ="Missing","Unknown",TRIM(Size)) -> M | H25: =IF(Size_Verification="Unknown","No","Yes") -> Yes | J25: =_xlfn.IFS(Units_Sold<0,"Check Return/Refund",Units_Sold=" ",Invalid,Units_Sold=0,"Available",Units_Sold>0,"Sold") -> Available | K25: 5003.95 | M25: =IF(OR(Discount_Applied="",Discount_Applied>1,Discount_Applied<0),"Invalid","Valid") -> Invalid | N25: =IF(PC_NikeSales[[#This Row],[Discount_Verification]]="Valid","Include","Exclude") -> Exclude | O25: 0 | P25: =IF(AND(Units_Sold<>"",MRP<>"",Discount_Applied<1),Units_Sold*MRP*(1-Discount_Applied),"Insufficient Data") -> Insufficient Data | Q25: =_xlfn.IFS(Rev_Recalc="Insufficient Data","Missing Information",Rev_Recalc<0,"Negative Revenue",Rev_Recalc=0,"No Recorded Revenue",Rev_Recalc>0,"Valid Revenue") -> Missing Information | R25: =IF(PC_NikeSales[[#This Row],[Rev_Verify]]="Valid Revenue","Include","Exclude") -> Exclude | S25: 45667 | T25: =IF(ISBLANK(Order_Date),"Missing Date",Order_Date) -> 45667 | U25: =IF(ISBLANK(Order_Date),"No","Yes") -> Yes | V25: Online | W25: Mumbai | X25: =PROPER(Region) -> Mumbai | Y25: 1498.37 | Z25: =IF(PC_NikeSales[[#This Row],[Profit]]<0,"Loss Making Sales",IF(PC_NikeSales[[#This Row],[Profit]]=0,"No Recorded Profit",IF($Y23>$P23,"Invalid Profit", "Valid Profit"))) -> Invalid Profit | AA25: =IF(PC_NikeSales[[#This Row],[Profit_Status]]="Valid Profit","Include","Exclude") -> Exclude
A26: 2024 | B26: Kids | C26: Training | D26: SuperRep Go | E26: XL | F26: =_xlfn.IFS(ISBLANK(Size),"Missing",ISNUMBER(Size),"Number",ISTEXT(Size),"Alphabet") -> Alphabet | G26: =IF(Size_Type ="Missing","Unknown",TRIM(Size)) -> XL | H26: =IF(Size_Verification="Unknown","No","Yes") -> Yes | I26: 0 | J26: =_xlfn.IFS(Units_Sold<0,"Check Return/Refund",Units_Sold=" ",Invalid,Units_Sold=0,"Available",Units_Sold>0,"Sold") -> Available | L26: 0.5 | M26: =IF(OR(Discount_Applied="",Discount_Applied>1,Discount_Applied<0),"Invalid","Valid") -> Valid | N26: =IF(PC_NikeSales[[#This Row],[Discount_Verification]]="Valid","Include","Exclude") -> Include | O26: 0 | P26: =IF(AND(Units_Sold<>"",MRP<>"",Discount_Applied<1),Units_Sold*MRP*(1-Discount_Applied),"Insufficient Data") -> Insufficient Data | Q26: =_xlfn.IFS(Rev_Recalc="Insufficient Data","Missing Information",Rev_Recalc<0,"Negative Revenue",Rev_Recalc=0,"No Recorded Revenue",Rev_Recalc>0,"Valid Revenue") -> Missing Information | R26: =IF(PC_NikeSales[[#This Row],[Rev_Verify]]="Valid Revenue","Include","Exclude") -> Exclude | S26: 45654 | T26: =IF(ISBLANK(Order_Date),"Missing Date",Order_Date) -> 45654 | U26: =IF(ISBLANK(Order_Date),"No","Yes") -> Yes | V26: Retail | W26: Bangalore | X26: =PROPER(Region) -> Bangalore | Y26: 1842.35 | Z26: =IF(PC_NikeSales[[#This Row],[Profit]]<0,"Loss Making Sales",IF(PC_NikeSales[[#This Row],[Profit]]=0,"No Recorded Profit",IF($Y24>$P24,"Invalid Profit", "Valid Profit"))) -> Valid Profit | AA26: =IF(PC_NikeSales[[#This Row],[Profit_Status]]="Valid Profit","Include","Exclude") -> Include
A27: 2025 | B27: Women | C27: Basketball | D27: Kyrie Flytrap | E27: M | F27: =_xlfn.IFS(ISBLANK(Size),"Missing",ISNUMBER(Size),"Number",ISTEXT(Size),"Alphabet") -> Alphabet | G27: =IF(Size_Type ="Missing","Unknown",TRIM(Size)) -> M | H27: =IF(Size_Verification="Unknown","No","Yes") -> Yes | I27: 3 | J27: =_xlfn.IFS(Units_Sold<0,"Check Return/Refund",Units_Sold=" ",Invalid,Units_Sold=0,"Available",Units_Sold>0,"Sold") -> Sold | K27: 9820.5 | M27: =IF(OR(Discount_Applied="",Discount_Applied>1,Discount_Applied<0),"Invalid","Valid") -> Invalid | N27: =IF(PC_NikeSales[[#This Row],[Discount_Verification]]="Valid","Include","Exclude") -> Exclude | O27: 0 | P27: =IF(AND(Units_Sold<>"",MRP<>"",Discount_Applied<1),Units_Sold*MRP*(1-Discount_Applied),"Insufficient Data") -> 29461.5 | Q27: =_xlfn.IFS(Rev_Recalc="Insufficient Data","Missing Information",Rev_Recalc<0,"Negative Revenue",Rev_Recalc=0,"No Recorded Revenue",Rev_Recalc>0,"Valid Revenue") -> Valid Revenue | R27: =IF(PC_NikeSales[[#This Row],[Rev_Verify]]="Valid Revenue","Include","Exclude") -> Include | T27: =IF(ISBLANK(Order_Date),"Missing Date",Order_Date) -> Missing Date | U27: =IF(ISBLANK(Order_Date),"No","Yes") -> No | V27: Retail | W27: Mumbai | X27: =PROPER(Region) -> Mumbai | Y27: 1900.15 | Z27: =IF(PC_NikeSales[[#This Row],[Profit]]<0,"Loss Making Sales",IF(PC_NikeSales[[#This Row],[Profit]]=0,"No Recorded Profit",IF($Y25>$P25,"Invalid Profit", "Valid Profit"))) -> Valid Profit | AA27: =IF(PC_NikeSales[[#This Row],[Profit_Status]]="Valid Profit","Include","Exclude") -> Include
A28: 2026 | B28: Kids | C28: Lifestyle | D28: Blazer Mid | E28: XL | F28: =_xlfn.IFS(ISBLANK(Size),"Missing",ISNUMBER(Size),"Number",ISTEXT(Size),"Alphabet") -> Alphabet | G28: =IF(Size_Type ="Missing","Unknown",TRIM(Size)) -> XL | H28: =IF(Size_Verification="Unknown","No","Yes") -> Yes | I28: 1 | J28: =_xlfn.IFS(Units_Sold<0,"Check Return/Refund",Units_Sold=" ",Invalid,Units_Sold=0,"Available",Units_Sold>0,"Sold") -> Sold | L28: 0.16 | M28: =IF(OR(Discount_Applied="",Discount_Applied>1,Discount_Applied<0),"Invalid","Valid") -> Valid | N28: =IF(PC_NikeSales[[#This Row],[Discount_Verification]]="Valid","Include","Exclude") -> Include | O28: 0 | P28: =IF(AND(Units_Sold<>"",MRP<>"",Discount_Applied<1),Units_Sold*MRP*(1-Discount_Applied),"Insufficient Data") -> Insufficient Data | Q28: =_xlfn.IFS(Rev_Recalc="Insufficient Data","Missing Information",Rev_Recalc<0,"Negative Revenue",Rev_Recalc=0,"No Recorded Revenue",Rev_Recalc>0,"Valid Revenue") -> Missing Information | R28: =IF(PC_NikeSales[[#This Row],[Rev_Verify]]="Valid Revenue","Include","Exclude") -> Exclude | S28: 45514 | T28: =IF(ISBLANK(Order_Date),"Missing Date",Order_Date) -> 45514 | U28: =IF(ISBLANK(Order_Date),"No","Yes") -> Yes | V28: Retail | W28: Kolkata | X28: =PROPER(Region) -> Kolkata | Y28: 2301.64 | Z28: =IF(PC_NikeSales[[#This Row],[Profit]]<0,"Loss Making Sales",IF(PC_NikeSales[[#This Row],[Profit]]=0,"No Recorded Profit",IF($Y26>$P26,"Invalid Profit", "Valid Profit"))) -> Valid Profit | AA28: =IF(PC_NikeSales[[#This Row],[Profit_Status]]="Valid Profit","Include","Exclude") -> Include
A29: 2027 | B29: Men | C29: Basketball | D29: Zoom Freak | E29: XL | F29: =_xlfn.IFS(ISBLANK(Size),"Missing",ISNUMBER(Size),"Number",ISTEXT(Size),"Alphabet") -> Alphabet | G29: =IF(Size_Type ="Missing","Unknown",TRIM(Size)) -> XL | H29: =IF(Size_Verification="Unknown","No","Yes") -> Yes | J29: =_xlfn.IFS(Units_Sold<0,"Check Return/Refund",Units_Sold=" ",Invalid,Units_Sold=0,"Available",Units_Sold>0,"Sold") -> Available | L29: 0.22 | M29: =IF(OR(Discount_Applied="",Discount_Applied>1,Discount_Applied<0),"Invalid","Valid") -> Valid | N29: =IF(PC_NikeSales[[#This Row],[Discount_Verification]]="Valid","Include","Exclude") -> Include | O29: 0 | P29: =IF(AND(Units_Sold<>"",MRP<>"",Discount_Applied<1),Units_Sold*MRP*(1-Discount_Applied),"Insufficient Data") -> Insufficient Data | Q29: =_xlfn.IFS(Rev_Recalc="Insufficient Data","Missing Information",Rev_Recalc<0,"Negative Revenue",Rev_Recalc=0,"No Recorded Revenue",Rev_Recalc>0,"Valid Revenue") -> Missing Information | R29: =IF(PC_NikeSales[[#This Row],[Rev_Verify]]="Valid Revenue","Include","Exclude") -> Exclude | T29: =IF(ISBLANK(Order_Date),"Missing Date",Order_Date) -> Missing Date | U29: =IF(ISBLANK(Order_Date),"No","Yes") -> No | V29: Online | W29: Pune | X29: =PROPER(Region) -> Pune | Y29: -138.74 | Z29: =IF(PC_NikeSales[[#This Row],[Profit]]<0,"Loss Making Sales",IF(PC_NikeSales[[#This Row],[Profit]]=0,"No Recorded Profit",IF(PC_NikeSales[[#This Row],[Profit]]>PC_NikeSales[Rev_Recalc],"Invalid Profit", "Valid Profit"))) -> Loss Making Sales | AA29: =IF(PC_NikeSales[[#This Row],[Profit_Status]]="Valid Profit","Include","Exclude") -> Exclude
A30: 2028 | B30: Men | C30: Training | D30: Flex Trainer | E30: 12 | F30: =_xlfn.IFS(ISBLANK(Size),"Missing",ISNUMBER(Size),"Number",ISTEXT(Size),"Alphabet") -> Number | G30: =IF(Size_Type ="Missing","Unknown",TRIM(Size)) -> 12 | H30: =IF(Size_Verification="Unknown","No","Yes") -> Yes | J30: =_xlfn.IFS(Units_Sold<0,"Check Return/Refund",Units_Sold=" ",Invalid,Units_Sold=0,"Available",Units_Sold>0,"Sold") -> Available | K30: 3270.23 | M30: =IF(OR(Discount_Applied="",Discount_Applied>1,Discount_Applied<0),"Invalid","Valid") -> Invalid | N30: =IF(PC_NikeSales[[#This Row],[Discount_Verification]]="Valid","Include","Exclude") -> Exclude | O30: 0 | P30: =IF(AND(Units_Sold<>"",MRP<>"",Discount_Applied<1),Units_Sold*MRP*(1-Discount_Applied),"Insufficient Data") -> Insufficient Data | Q30: =_xlfn.IFS(Rev_Recalc="Insufficient Data","Missing Information",Rev_Recalc<0,"Negative Revenue",Rev_Recalc=0,"No Recorded Revenue",Rev_Recalc>0,"Valid Revenue") -> Missing Information | R30: =IF(PC_NikeSales[[#This Row],[Rev_Verify]]="Valid Revenue","Include","Exclude") -> Exclude | T30: =IF(ISBLANK(Order_Date),"Missing Date",Order_Date) -> Missing Date | U30: =IF(ISBLANK(Order_Date),"No","Yes") -> No | V30: Retail | W30: Delhi | X30: =PROPER(Region) -> Delhi | Y30: -946.86 | Z30: =IF(PC_NikeSales[[#This Row],[Profit]]<0,"Loss Making Sales",IF(PC_NikeSales[[#This Row],[Profit]]=0,"No Recorded Profit",IF(PC_NikeSales[[#This Row],[Profit]]>PC_NikeSales[Rev_Recalc],"Invalid Profit", "Valid Profit"))) -> Loss Making Sales | AA30: =IF(PC_NikeSales[[#This Row],[Profit_Status]]="Valid Profit","Include","Exclude") -> Exclude
A31: 2029 | B31: Men | C31: Training | D31: ZoomX Invincible | E31: 12 | F31: =_xlfn.IFS(ISBLANK(Size),"Missing",ISNUMBER(Size),"Number",ISTEXT(Size),"Alphabet") -> Number | G31: =IF(Size_Type ="Missing","Unknown",TRIM(Size)) -> 12 | H31: =IF(Size_Verification="Unknown","No","Yes") -> Yes | I31: 0 | J31: =_xlfn.IFS(Units_Sold<0,"Check Return/Refund",Units_Sold=" ",Invalid,Units_Sold=0,"Available",Units_Sold>0,"Sold") -> Available | M31: =IF(OR(Discount_Applied="",Discount_Applied>1,Discount_Applied<0),"Invalid","Valid") -> Invalid | N31: =IF(PC_NikeSales[[#This Row],[Discount_Verification]]="Valid","Include","Exclude") -> Exclude | O31: 0 | P31: =IF(AND(Units_Sold<>"",MRP<>"",Discount_Applied<1),Units_Sold*MRP*(1-Discount_Applied),"Insufficient Data") -> Insufficient Data | Q31: =_xlfn.IFS(Rev_Recalc="Insufficient Data","Missing Information",Rev_Recalc<0,"Negative Revenue",Rev_Recalc=0,"No Recorded Revenue",Rev_Recalc>0,"Valid Revenue") -> Missing Information | R31: =IF(PC_NikeSales[[#This Row],[Rev_Verify]]="Valid Revenue","Include","Exclude") -> Exclude | S31: 45227 | T31: =IF(ISBLANK(Order_Date),"Missing Date",Order_Date) -> 45227 | U31: =IF(ISBLANK(Order_Date),"No","Yes") -> Yes | V31: Online | W31: Bangalore | X31: =PROPER(Region) -> Bangalore | Y31: -185.67 | Z31: =IF(PC_NikeSales[[#This Row],[Profit]]<0,"Loss Making Sales",IF(PC_NikeSales[[#This Row],[Profit]]=0,"No Recorded Profit",IF(PC_NikeSales[[#This Row],[Profit]]>PC_NikeSales[Rev_Recalc],"Invalid Profit", "Valid Profit"))) -> Loss Making Sales | AA31: =IF(PC_NikeSales[[#This Row],[Profit_Status]]="Valid Profit","Include","Exclude") -> Exclude
A32: 2030 | B32: Men | C32: Soccer | D32: Phantom GT | E32: XL | F32: =_xlfn.IFS(ISBLANK(Size),"Missing",ISNUMBER(Size),"Number",ISTEXT(Size),"Alphabet") -> Alphabet | G32: =IF(Size_Type ="Missing","Unknown",TRIM(Size)) -> XL | H32: =IF(Size_Verification="Unknown","No","Yes") -> Yes | J32: =_xlfn.IFS(Units_Sold<0,"Check Return/Refund",Units_Sold=" ",Invalid,Units_Sold=0,"Available",Units_Sold>0,"Sold") -> Available | L32: 1.05 | M32: =IF(OR(Discount_Applied="",Discount_Applied>1,Discount_Applied<0),"Invalid","Valid") -> Invalid | N32: =IF(PC_NikeSales[[#This Row],[Discount_Verification]]="Valid","Include","Exclude") -> Exclude | O32: 0 | P32: =IF(AND(Units_Sold<>"",MRP<>"",Discount_Applied<1),Units_Sold*MRP*(1-Discount_Applied),"Insufficient Data") -> Insufficient Data | Q32: =_xlfn.IFS(Rev_Recalc="Insufficient Data","Missing Information",Rev_Recalc<0,"Negative Revenue",Rev_Recalc=0,"No Recorded Revenue",Rev_Recalc>0,"Valid Revenue") -> Missing Information | R32: =IF(PC_NikeSales[[#This Row],[Rev_Verify]]="Valid Revenue","Include","Exclude") -> Exclude | S32: 45852 | T32: =IF(ISBLANK(Order_Date),"Missing Date",Order_Date) -> 45852 | U32: =IF(ISBLANK(Order_Date),"No","Yes") -> Yes | V32: Retail | W32: Hyderabad | X32: =PROPER(Region) -> Hyderabad | Y32: -122.93 | Z32: =IF(PC_NikeSales[[#This Row],[Profit]]<0,"Loss Making Sales",IF(PC_NikeSales[[#This Row],[Profit]]=0,"No Recorded Profit",IF(PC_NikeSales[[#This Row],[Profit]]>PC_NikeSales[Rev_Recalc],"Invalid Profit", "Valid Profit"))) -> Loss Making Sales | AA32: =IF(PC_NikeSales[[#This Row],[Profit_Status]]="Valid Profit","Include","Exclude") -> Exclude
A33: 2031 | B33: Men | C33: Soccer | D33: Premier III | F33: =_xlfn.IFS(ISBLANK(Size),"Missing",ISNUMBER(Size),"Number",ISTEXT(Size),"Alphabet") -> Missing | G33: =IF(Size_Type ="Missing","Unknown",TRIM(Size)) -> Unknown | H33: =IF(Size_Verification="Unknown","No","Yes") -> No | I33: 4 | J33: =_xlfn.IFS(Units_Sold<0,"Check Return/Refund",Units_Sold=" ",Invalid,Units_Sold=0,"Available",Units_Sold>0,"Sold") -> Sold | K33: 3493.04 | L33: 0.82 | M33: =IF(OR(Discount_Applied="",Discount_Applied>1,Discount_Applied<0),"Invalid","Valid") -> Valid | N33: =IF(PC_NikeSales[[#This Row],[Discount_Verification]]="Valid","Include","Exclude") -> Include | O33: 2514.99 | P33: =IF(AND(Units_Sold<>"",MRP<>"",Discount_Applied<1),Units_Sold*MRP*(1-Discount_Applied),"Insufficient Data") -> 2514.9888 | Q33: =_xlfn.IFS(Rev_Recalc="Insufficient Data","Missing Information",Rev_Recalc<0,"Negative Revenue",Rev_Recalc=0,"No Recorded Revenue",Rev_Recalc>0,"Valid Revenue") -> Valid Revenue | R33: =IF(PC_NikeSales[[#This Row],[Rev_Verify]]="Valid Revenue","Include","Exclude") -> Include | S33: 45421 | T33: =IF(ISBLANK(Order_Date),"Missing Date",Order_Date) -> 45421 | U33: =IF(ISBLANK(Order_Date),"No","Yes") -> Yes | V33: Online | W33: Delhi | X33: =PROPER(Region) -> Delhi | Y33: 350.7 | Z33: =IF(PC_NikeSales[[#This Row],[Profit]]<0,"Loss Making Sales",IF(PC_NikeSales[[#This Row],[Profit]]=0,"No Recorded Profit",IF($Y31>$P31,"Invalid Profit", "Valid Profit"))) -> Valid Profit | AA33: =IF(PC_NikeSales[[#This Row],[Profit_Status]]="Valid Profit","Include","Exclude") -> Include
A34: 2032 | B34: Women | C34: Lifestyle | D34: Blazer Mid | E34: XL | F34: =_xlfn.IFS(ISBLANK(Size),"Missing",ISNUMBER(Size),"Number",ISTEXT(Size),"Alphabet") -> Alphabet | G34: =IF(Size_Type ="Missing","Unknown",TRIM(Size)) -> XL | H34: =IF(Size_Verification="Unknown","No","Yes") -> Yes | I34: 1 | J34: =_xlfn.IFS(Units_Sold<0,"Check Return/Refund",Units_Sold=" ",Invalid,Units_Sold=0,"Available",Units_Sold>0,"Sold") -> Sold | L34: 1.07 | M34: =IF(OR(Discount_Applied="",Discount_Applied>1,Discount_Applied<0),"Invalid","Valid") -> Invalid | N34: =IF(PC_NikeSales[[#This Row],[Discount_Verification]]="Valid","Include","Exclude") -> Exclude | O34: 0 | P34: =IF(AND(Units_Sold<>"",MRP<>"",Discount_Applied<1),Units_Sold*MRP*(1-Discount_Applied),"Insufficient Data") -> Insufficient Data | Q34: =_xlfn.IFS(Rev_Recalc="Insufficient Data","Missing Information",Rev_Recalc<0,"Negative Revenue",Rev_Recalc=0,"No Recorded Revenue",Rev_Recalc>0,"Valid Revenue") -> Missing Information | R34: =IF(PC_NikeSales[[#This Row],[Rev_Verify]]="Valid Revenue","Include","Exclude") -> Exclude | S34: 45758 | T34: =IF(ISBLANK(Order_Date),"Missing Date",Order_Date) -> 45758 | U34: =IF(ISBLANK(Order_Date),"No","Yes") -> Yes | V34: Retail | W34: Mumbai | X34: =PROPER(Region) -> Mumbai | Y34: -555.16 | Z34: =IF(PC_NikeSales[[#This Row],[Profit]]<0,"Loss Making Sales",IF(PC_NikeSales[[#This Row],[Profit]]=0,"No Recorded Profit",IF(PC_NikeSales[[#This Row],[Profit]]>PC_NikeSales[Rev_Recalc],"Invalid Profit", "Valid Profit"))) -> Loss Making Sales | AA34: =IF(PC_NikeSales[[#This Row],[Profit_Status]]="Valid Profit","Include","Exclude") -> Exclude
A35: 2033 | B35: Men | C35: Soccer | D35: Mercurial Superfly | E35: XL | F35: =_xlfn.IFS(ISBLANK(Size),"Missing",ISNUMBER(Size),"Number",ISTEXT(Size),"Alphabet") -> Alphabet | G35: =IF(Size_Type ="Missing","Unknown",TRIM(Size)) -> XL | H35: =IF(Size_Verification="Unknown","No","Yes") -> Yes | I35: -1 | J35: =_xlfn.IFS(Units_Sold<0,"Check Return/Refund",Units_Sold=" ",Invalid,Units_Sold=0,"Available",Units_Sold>0,"Sold") -> Check Return/Refund | M35: =IF(OR(Discount_Applied="",Discount_Applied>1,Discount_Applied<0),"Invalid","Valid") -> Invalid | N35: =IF(PC_NikeSales[[#This Row],[Discount_Verification]]="Valid","Include","Exclude") -> Exclude | O35: 0 | P35: =IF(AND(Units_Sold<>"",MRP<>"",Discount_Applied<1),Units_Sold*MRP*(1-Discount_Applied),"Insufficient Data") -> Insufficient Data | Q35: =_xlfn.IFS(Rev_Recalc="Insufficient Data","Missing Information",Rev_Recalc<0,"Negative Revenue",Rev_Recalc=0,"No Recorded Revenue",Rev_Recalc>0,"Valid Revenue") -> Missing Information | R35: =IF(PC_NikeSales[[#This Row],[Rev_Verify]]="Valid Revenue","Include","Exclude") -> Exclude | T35: =IF(ISBLANK(Order_Date),"Missing Date",Order_Date) -> Missing Date | U35: =IF(ISBLANK(Order_Date),"No","Yes") -> No | V35: Retail | W35: Kolkata | X35: =PROPER(Region) -> Kolkata | Y35: -1005.71 | Z35: =IF(PC_NikeSales[[#This Row],[Profit]]<0,"Loss Making Sales",IF(PC_NikeSales[[#This Row],[Profit]]=0,"No Recorded Profit",IF(PC_NikeSales[[#This Row],[Profit]]>PC_NikeSales[Rev_Recalc],"Invalid Profit", "Valid Profit"))) -> Loss Making Sales | AA35: =IF(PC_NikeSales[[#This Row],[Profit_Status]]="Valid Profit","Include","Exclude") -> Exclude
A36: 2034 | B36: Men | C36: Basketball | D36: Air Jordan | E36: 6 | F36: =_xlfn.IFS(ISBLANK(Size),"Missing",ISNUMBER(Size),"Number",ISTEXT(Size),"Alphabet") -> Number | G36: =IF(Size_Type ="Missing","Unknown",TRIM(Size)) -> 6 | H36: =IF(Size_Verification="Unknown","No","Yes") -> Yes | J36: =_xlfn.IFS(Units_Sold<0,"Check Return/Refund",Units_Sold=" ",Invalid,Units_Sold=0,"Available",Units_Sold>0,"Sold") -> Available | K36: 6235.71 | M36: =IF(OR(Discount_Applied="",Discount_Applied>1,Discount_Applied<0),"Invalid","Valid") -> Invalid | N36: =IF(PC_NikeSales[[#This Row],[Discount_Verification]]="Valid","Include","Exclude") -> Exclude | O36: 0 | P36: =IF(AND(Units_Sold<>"",MRP<>"",Discount_Applied<1),Units_Sold*MRP*(1-Discount_Applied),"Insufficient Data") -> Insufficient Data | Q36: =_xlfn.IFS(Rev_Recalc="Insufficient Data","Missing Information",Rev_Recalc<0,"Negative Revenue",Rev_Recalc=0,"No Recorded Revenue",Rev_Recalc>0,"Valid Revenue") -> Missing Information | R36: =IF(PC_NikeSales[[#This Row],[Rev_Verify]]="Valid Revenue","Include","Exclude") -> Exclude | S36: 45777 | T36: =IF(ISBLANK(Order_Date),"Missing Date",Order_Date) -> 45777 | U36: =IF(ISBLANK(Order_Date),"No","Yes") -> Yes | V36: Retail | W36: Delhi | X36: =PROPER(Region) -> Delhi | Y36: -267.37 | Z36: =IF(PC_NikeSales[[#This Row],[Profit]]<0,"Loss Making Sales",IF(PC_NikeSales[[#This Row],[Profit]]=0,"No Recorded Profit",IF(PC_NikeSales[[#This Row],[Profit]]>PC_NikeSales[Rev_Recalc],"Invalid Profit", "Valid Profit"))) -> Loss Making Sales | AA36: =IF(PC_NikeSales[[#This Row],[Profit_Status]]="Valid Profit","Include","Exclude") -> Exclude
A37: 2035 | B37: Kids | C37: Basketball | D37: Zoom Freak | F37: =_xlfn.IFS(ISBLANK(Size),"Missing",ISNUMBER(Size),"Number",ISTEXT(Size),"Alphabet") -> Missing | G37: =IF(Size_Type ="Missing","Unknown",TRIM(Size)) -> Unknown | H37: =IF(Size_Verification="Unknown","No","Yes") -> No | I37: 4 | J37: =_xlfn.IFS(Units_Sold<0,"Check Return/Refund",Units_Sold=" ",Invalid,Units_Sold=0,"Available",Units_Sold>0,"Sold") -> Sold | L37: 0.38 | M37: =IF(OR(Discount_Applied="",Discount_Applied>1,Discount_Applied<0),"Invalid","Valid") -> Valid | N37: =IF(PC_NikeSales[[#This Row],[Discount_Verification]]="Valid","Include","Exclude") -> Include | O37: 0 | P37: =IF(AND(Units_Sold<>"",MRP<>"",Discount_Applied<1),Units_Sold*MRP*(1-Discount_Applied),"Insufficient Data") -> Insufficient Data | Q37: =_xlfn.IFS(Rev_Recalc="Insufficient Data","Missing Information",Rev_Recalc<0,"Negative Revenue",Rev_Recalc=0,"No Recorded Revenue",Rev_Recalc>0,"Valid Revenue") -> Missing Information | R37: =IF(PC_NikeSales[[#This Row],[Rev_Verify]]="Valid Revenue","Include","Exclude") -> Exclude | S37: 45613 | T37: =IF(ISBLANK(Order_Date),"Missing Date",Order_Date) -> 45613 | U37: =IF(ISBLANK(Order_Date),"No","Yes") -> Yes | V37: Online | W37: Bangalore | X37: =PROPER(Region) -> Bangalore | Y37: 2914.83 | Z37: =IF(PC_NikeSales[[#This Row],[Profit]]<0,"Loss Making Sales",IF(PC_NikeSales[[#This Row],[Profit]]=0,"No Recorded Profit",IF($Y35>$P35,"Invalid Profit", "Valid Profit"))) -> Valid Profit | AA37: =IF(PC_NikeSales[[#This Row],[Profit_Status]]="Valid Profit","Include","Exclude") -> Include
A38: 2036 | B38: Men | C38: Training | D38: Metcon 7 | F38: =_xlfn.IFS(ISBLANK(Size),"Missing",ISNUMBER(Size),"Number",ISTEXT(Size),"Alphabet") -> Missing | G38: =IF(Size_Type ="Missing","Unknown",TRIM(Size)) -> Unknown | H38: =IF(Size_Verification="Unknown","No","Yes") -> No | I38: 3 | J38: =_xlfn.IFS(Units_Sold<0,"Check Return/Refund",Units_Sold=" ",Invalid,Units_Sold=0,"Available",Units_Sold>0,"Sold") -> Sold | M38: =IF(OR(Discount_Applied="",Discount_Applied>1,Discount_Applied<0),"Invalid","Valid") -> Invalid | N38: =IF(PC_NikeSales[[#This Row],[Discount_Verification]]="Valid","Include","Exclude") -> Exclude | O38: 0 | P38: =IF(AND(Units_Sold<>"",MRP<>"",Discount_Applied<1),Units_Sold*MRP*(1-Discount_Applied),"Insufficient Data") -> Insufficient Data | Q38: =_xlfn.IFS(Rev_Recalc="Insufficient Data","Missing Information",Rev_Recalc<0,"Negative Revenue",Rev_Recalc=0,"No Recorded Revenue",Rev_Recalc>0,"Valid Revenue") -> Missing Information | R38: =IF(PC_NikeSales[[#This Row],[Rev_Verify]]="Valid Revenue","Include","Exclude") -> Exclude | S38: 45703 | T38: =IF(ISBLANK(Order_Date),"Missing Date",Order_Date) -> 45703 | U38: =IF(ISBLANK(Order_Date),"No","Yes") -> Yes | V38: Retail | W38: Bangalore | X38: =PROPER(Region) -> Bangalore | Y38: -143.8 | Z38: =IF(PC_NikeSales[[#This Row],[Profit]]<0,"Loss Making Sales",IF(PC_NikeSales[[#This Row],[Profit]]=0,"No Recorded Profit",IF(PC_NikeSales[[#This Row],[Profit]]>PC_NikeSales[Rev_Recalc],"Invalid Profit", "Valid Profit"))) -> Loss Making Sales | AA38: =IF(PC_NikeSales[[#This Row],[Profit_Status]]="Valid Profit","Include","Exclude") -> Exclude
A39: 2037 | B39: Kids | C39: Running | D39: Pegasus Turbo | E39: 7 | F39: =_xlfn.IFS(ISBLANK(Size),"Missing",ISNUMBER(Size),"Number",ISTEXT(Size),"Alphabet") -> Number | G39: =IF(Size_Type ="Missing","Unknown",TRIM(Size)) -> 7 | H39: =IF(Size_Verification="Unknown","No","Yes") -> Yes | I39: 3 | J39: =_xlfn.IFS(Units_Sold<0,"Check Return/Refund",Units_Sold=" ",Invalid,Units_Sold=0,"Available",Units_Sold>0,"Sold") -> Sold | K39: 5653.14 | L39: 1.01 | M39: =IF(OR(Discount_Applied="",Discount_Applied>1,Discount_Applied<0),"Invalid","Valid") -> Invalid | N39: =IF(PC_NikeSales[[#This Row],[Discount_Verification]]="Valid","Include","Exclude") -> Exclude | O39: -169.59 | P39: =IF(AND(Units_Sold<>"",MRP<>"",Discount_Applied<1),Units_Sold*MRP*(1-Discount_Applied),"Insufficient Data") -> Insufficient Data | Q39: =_xlfn.IFS(Rev_Recalc="Insufficient Data","Missing Information",Rev_Recalc<0,"Negative Revenue",Rev_Recalc=0,"No Recorded Revenue",Rev_Recalc>0,"Valid Revenue") -> Missing Information | R39: =IF(PC_NikeSales[[#This Row],[Rev_Verify]]="Valid Revenue","Include","Exclude") -> Exclude | T39: =IF(ISBLANK(Order_Date),"Missing Date",Order_Date) -> Missing Date | U39: =IF(ISBLANK(Order_Date),"No","Yes") -> No | V39: Retail | W39: Pune | X39: =PROPER(Region) -> Pune | Y39: 2776.96 | Z39: =IF(PC_NikeSales[[#This Row],[Profit]]<0,"Loss Making Sales",IF(PC_NikeSales[[#This Row],[Profit]]=0,"No Recorded Profit",IF($Y37>$P37,"Invalid Profit", "Valid Profit"))) -> Valid Profit | AA39: =IF(PC_NikeSales[[#This Row],[Profit_Status]]="Valid Profit","Include","Exclude") -> Include
A40: 2038 | B40: Kids | C40: Running | D40: Free RN | F40: =_xlfn.IFS(ISBLANK(Size),"Missing",ISNUMBER(Size),"Number",ISTEXT(Size),"Alphabet") -> Missing | G40: =IF(Size_Type ="Missing","Unknown",TRIM(Size)) -> Unknown | H40: =IF(Size_Verification="Unknown","No","Yes") -> No | I40: 0 | J40: =_xlfn.IFS(Units_Sold<0,"Check Return/Refund",Units_Sold=" ",Invalid,Units_Sold=0,"Available",Units_Sold>0,"Sold") -> Available | L40: 0.83 | M40: =IF(OR(Discount_Applied="",Discount_Applied>1,Discount_Applied<0),"Invalid","Valid") -> Valid | N40: =IF(PC_NikeSales[[#This Row],[Discount_Verification]]="Valid","Include","Exclude") -> Include | O40: 0 | P40: =IF(AND(Units_Sold<>"",MRP<>"",Discount_Applied<1),Units_Sold*MRP*(1-Discount_Applied),"Insufficient Data") -> Insufficient Data | Q40: =_xlfn.IFS(Rev_Recalc="Insufficient Data","Missing Information",Rev_Recalc<0,"Negative Revenue",Rev_Recalc=0,"No Recorded Revenue",Rev_Recalc>0,"Valid Revenue") -> Missing Information | R40: =IF(PC_NikeSales[[#This Row],[Rev_Verify]]="Valid Revenue","Include","Exclude") -> Exclude | T40: =IF(ISBLANK(Order_Date),"Missing Date",Order_Date) -> Missing Date | U40: =IF(ISBLANK(Order_Date),"No","Yes") -> No | V40: Online | W40: Delhi | X40: =PROPER(Region) -> Delhi | Y40: 1163.21 | Z40: =IF(PC_NikeSales[[#This Row],[Profit]]<0,"Loss Making Sales",IF(PC_NikeSales[[#This Row],[Profit]]=0,"No Recorded Profit",IF($Y38>$P38,"Invalid Profit", "Valid Profit"))) -> Valid Profit | AA40: =IF(PC_NikeSales[[#This Row],[Profit_Status]]="Valid Profit","Include","Exclude") -> Include
A41: 2039 | B41: Women | C41: Training | D41: Flex Trainer | E41: M | F41: =_xlfn.IFS(ISBLANK(Size),"Missing",ISNUMBER(Size),"Number",ISTEXT(Size),"Alphabet") -> Alphabet | G41: =IF(Size_Type ="Missing","Unknown",TRIM(Size)) -> M | H41: =IF(Size_Verification="Unknown","No","Yes") -> Yes | J41: =_xlfn.IFS(Units_Sold<0,"Check Return/Refund",Units_Sold=" ",Invalid,Units_Sold=0,"Available",Units_Sold>0,"Sold") -> Available | K41: 2767.7 | L41: 0.63 | M41: =IF(OR(Discount_Applied="",Discount_Applied>1,Discount_Applied<0),"Invalid","Valid") -> Valid | N41: =IF(PC_NikeSales[[#This Row],[Discount_Verification]]="Valid","Include","Exclude") -> Include | O41: 0 | P41: =IF(AND(Units_Sold<>"",MRP<>"",Discount_Applied<1),Units_Sold*MRP*(1-Discount_Applied),"Insufficient Data") -> Insufficient Data | Q41: =_xlfn.IFS(Rev_Recalc="Insufficient Data","Missing Information",Rev_Recalc<0,"Negative Revenue",Rev_Recalc=0,"No Recorded Revenue",Rev_Recalc>0,"Valid Revenue") -> Missing Information | R41: =IF(PC_NikeSales[[#This Row],[Rev_Verify]]="Valid Revenue","Include","Exclude") -> Exclude | S41: 45769 | T41: =IF(ISBLANK(Order_Date),"Missing Date",Order_Date) -> 45769 | U41: =IF(ISBLANK(Order_Date),"No","Yes") -> Yes | V41: Retail | W41: Hyderabad | X41: =PROPER(Region) -> Hyderabad | Y41: -336.3 | Z41: =IF(PC_NikeSales[[#This Row],[Profit]]<0,"Loss Making Sales",IF(PC_NikeSales[[#This Row],[Profit]]=0,"No Recorded Profit",IF(PC_NikeSales[[#This Row],[Profit]]>PC_NikeSales[Rev_Recalc],"Invalid Profit", "Valid Profit"))) -> Loss Making Sales | AA41: =IF(PC_NikeSales[[#This Row],[Profit_Status]]="Valid Profit","Include","Exclude") -> Exclude
A42: 2002 | B42: Women | C42: Basketball | D42: Zoom Freak | E42: XL | F42: =_xlfn.IFS(ISBLANK(Size),"Missing",ISNUMBER(Size),"Number",ISTEXT(Size),"Alphabet") -> Alphabet | G42: =IF(Size_Type ="Missing","Unknown",TRIM(Size)) -> XL | H42: =IF(Size_Verification="Unknown","No","Yes") -> Yes | I42: 3 | J42: =_xlfn.IFS(Units_Sold<0,"Check Return/Refund",Units_Sold=" ",Invalid,Units_Sold=0,"Available",Units_Sold>0,"Sold") -> Sold | K42: 5075.22 | M42: =IF(OR(Discount_Applied="",Discount_Applied>1,Discount_Applied<0),"Invalid","Valid") -> Invalid | N42: =IF(PC_NikeSales[[#This Row],[Discount_Verification]]="Valid","Include","Exclude") -> Exclude | O42: 0 | P42: =IF(AND(Units_Sold<>"",MRP<>"",Discount_Applied<1),Units_Sold*MRP*(1-Discount_Applied),"Insufficient Data") -> 15225.66 | Q42: =_xlfn.IFS(Rev_Recalc="Insufficient Data","Missing Information",Rev_Recalc<0,"Negative Revenue",Rev_Recalc=0,"No Recorded Revenue",Rev_Recalc>0,"Valid Revenue") -> Valid Revenue | R42: =IF(PC_NikeSales[[#This Row],[Rev_Verify]]="Valid Revenue","Include","Exclude") -> Include | S42: 45723 | T42: =IF(ISBLANK(Order_Date),"Missing Date",Order_Date) -> 45723 | U42: =IF(ISBLANK(Order_Date),"No","Yes") -> Yes | V42: Retail | W42: Delhi | X42: =PROPER(Region) -> Delhi | Y42: 145.08 | Z42: =IF(PC_NikeSales[[#This Row],[Profit]]<0,"Loss Making Sales",IF(PC_NikeSales[[#This Row],[Profit]]=0,"No Recorded Profit",IF($Y40>$P40,"Invalid Profit", "Valid Profit"))) -> Valid Profit | AA42: =IF(PC_NikeSales[[#This Row],[Profit_Status]]="Valid Profit","Include","Exclude") -> Include
A43: 2041 | B43: Kids | C43: Soccer | D43: Tiempo Legend | E43: 12 | F43: =_xlfn.IFS(ISBLANK(Size),"Missing",ISNUMBER(Size),"Number",ISTEXT(Size),"Alphabet") -> Number | G43: =IF(Size_Type ="Missing","Unknown",TRIM(Size)) -> 12 | H43: =IF(Size_Verification="Unknown","No","Yes") -> Yes | J43: =_xlfn.IFS(Units_Sold<0,"Check Return/Refund",Units_Sold=" ",Invalid,Units_Sold=0,"Available",Units_Sold>0,"Sold") -> Available | K43: 5553.88 | M43: =IF(OR(Discount_Applied="",Discount_Applied>1,Discount_Applied<0),"Invalid","Valid") -> Invalid | N43: =IF(PC_NikeSales[[#This Row],[Discount_Verification]]="Valid","Include","Exclude") -> Exclude | O43: 0 | P43: =IF(AND(Units_Sold<>"",MRP<>"",Discount_Applied<1),Units_Sold*MRP*(1-Discount_Applied),"Insufficient Data") -> Insufficient Data | Q43: =_xlfn.IFS(Rev_Recalc="Insufficient Data","Missing Information",Rev_Recalc<0,"Negative Revenue",Rev_Recalc=0,"No Recorded Revenue",Rev_Recalc>0,"Valid Revenue") -> Missing Information | R43: =IF(PC_NikeSales[[#This Row],[Rev_Verify]]="Valid Revenue","Include","Exclude") -> Exclude | S43: 45721 | T43: =IF(ISBLANK(Order_Date),"Missing Date",Order_Date) -> 45721 | U43: =IF(ISBLANK(Order_Date),"No","Yes") -> Yes | V43: Online | W43: Hyderabad | X43: =PROPER(Region) -> Hyderabad | Y43: 2371.66 | Z43: =IF(PC_NikeSales[[#This Row],[Profit]]<0,"Loss Making Sales",IF(PC_NikeSales[[#This Row],[Profit]]=0,"No Recorded Profit",IF($Y41>$P41,"Invalid Profit", "Valid Profit"))) -> Valid Profit | AA43: =IF(PC_NikeSales[[#This Row],[Profit_Status]]="Valid Profit","Include","Exclude") -> Include
A44: 2042 | B44: Women | C44: Basketball | D44: Kyrie Flytrap | E44: L | F44: =_xlfn.IFS(ISBLANK(Size),"Missing",ISNUMBER(Size),"Number",ISTEXT(Size),"Alphabet") -> Alphabet | G44: =IF(Size_Type ="Missing","Unknown",TRIM(Size)) -> L | H44: =IF(Size_Verification="Unknown","No","Yes") -> Yes | J44: =_xlfn.IFS(Units_Sold<0,"Check Return/Refund",Units_Sold=" ",Invalid,Units_Sold=0,"Available",Units_Sold>0,"Sold") -> Available | M44: =IF(OR(Discount_Applied="",Discount_Applied>1,Discount_Applied<0),"Invalid","Valid") -> Invalid | N44: =IF(PC_NikeSales[[#This Row],[Discount_Verification]]="Valid","Include","Exclude") -> Exclude | O44: 0 | P44: =IF(AND(Units_Sold<>"",MRP<>"",Discount_Applied<1),Units_Sold*MRP*(1-Discount_Applied),"Insufficient Data") -> Insufficient Data | Q44: =_xlfn.IFS(Rev_Recalc="Insufficient Data","Missing Information",Rev_Recalc<0,"Negative Revenue",Rev_Recalc=0,"No Recorded Revenue",Rev_Recalc>0,"Valid Revenue") -> Missing Information | R44: =IF(PC_NikeSales[[#This Row],[Rev_Verify]]="Valid Revenue","Include","Exclude") -> Exclude | S44: 45766 | T44: =IF(ISBLANK(Order_Date),"Missing Date",Order_Date) -> 45766 | U44: =IF(ISBLANK(Order_Date),"No","Yes") -> Yes | V44: Online | W44: Hyderabad | X44: =PROPER(Region) -> Hyderabad | Y44: -862.16 | Z44: =IF(PC_NikeSales[[#This Row],[Profit]]<0,"Loss Making Sales",IF(PC_NikeSales[[#This Row],[Profit]]=0,"No Recorded Profit",IF(PC_NikeSales[[#This Row],[Profit]]>PC_NikeSales[Rev_Recalc],"Invalid Profit", "Valid Profit"))) -> Loss Making Sales | AA44: =IF(PC_NikeSales[[#This Row],[Profit_Status]]="Valid Profit","Include","Exclude") -> Exclude
A45: 2043 | B45: Men | C45: Soccer | D45: Premier III | E45: XL | F45: =_xlfn.IFS(ISBLANK(Size),"Missing",ISNUMBER(Size),"Number",ISTEXT(Size),"Alphabet") -> Alphabet | G45: =IF(Size_Type ="Missing","Unknown",TRIM(Size)) -> XL | H45: =IF(Size_Verification="Unknown","No","Yes") -> Yes | J45: =_xlfn.IFS(Units_Sold<0,"Check Return/Refund",Units_Sold=" ",Invalid,Units_Sold=0,"Available",Units_Sold>0,"Sold") -> Available | K45: 3492.89 | L45: 0.77 | M45: =IF(OR(Discount_Applied="",Discount_Applied>1,Discount_Applied<0),"Invalid","Valid") -> Valid | N45: =IF(PC_NikeSales[[#This Row],[Discount_Verification]]="Valid","Include","Exclude") -> Include | O45: 0 | P45: =IF(AND(Units_Sold<>"",MRP<>"",Discount_Applied<1),Units_Sold*MRP*(1-Discount_Applied),"Insufficient Data") -> Insufficient Data | Q45: =_xlfn.IFS(Rev_Recalc="Insufficient Data","Missing Information",Rev_Recalc<0,"Negative Revenue",Rev_Recalc=0,"No Recorded Revenue",Rev_Recalc>0,"Valid Revenue") -> Missing Information | R45: =IF(PC_NikeSales[[#This Row],[Rev_Verify]]="Valid Revenue","Include","Exclude") -> Exclude | S45: 45414 | T45: =IF(ISBLANK(Order_Date),"Missing Date",Order_Date) -> 45414 | U45: =IF(ISBLANK(Order_Date),"No","Yes") -> Yes | V45: Retail | W45: Delhi | X45: =PROPER(Region) -> Delhi | Y45: 3770.75 | Z45: =IF(PC_NikeSales[[#This Row],[Profit]]<0,"Loss Making Sales",IF(PC_NikeSales[[#This Row],[Profit]]=0,"No Recorded Profit",IF($Y43>$P43,"Invalid Profit", "Valid Profit"))) -> Valid Profit | AA45: =IF(PC_NikeSales[[#This Row],[Profit_Status]]="Valid Profit","Include","Exclude") -> Include
A46: 2044 | B46: Kids | C46: Training | D46: SuperRep Go | F46: =_xlfn.IFS(ISBLANK(Size),"Missing",ISNUMBER(Size),"Number",ISTEXT(Size),"Alphabet") -> Missing | G46: =IF(Size_Type ="Missing","Unknown",TRIM(Size)) -> Unknown | H46: =IF(Size_Verification="Unknown","No","Yes") -> No | J46: =_xlfn.IFS(Units_Sold<0,"Check Return/Refund",Units_Sold=" ",Invalid,Units_Sold=0,"Available",Units_Sold>0,"Sold") -> Available | M46: =IF(OR(Discount_Applied="",Discount_Applied>1,Discount_Applied<0),"Invalid","Valid") -> Invalid | N46: =IF(PC_NikeSales[[#This Row],[Discount_Verification]]="Valid","Include","Exclude") -> Exclude | O46: 0 | P46: =IF(AND(Units_Sold<>"",MRP<>"",Discount_Applied<1),Units_Sold*MRP*(1-Discount_Applied),"Insufficient Data") -> Insufficient Data | Q46: =_xlfn.IFS(Rev_Recalc="Insufficient Data","Missing Information",Rev_Recalc<0,"Negative Revenue",Rev_Recalc=0,"No Recorded Revenue",Rev_Recalc>0,"Valid Revenue") -> Missing Information | R46: =IF(PC_NikeSales[[#This Row],[Rev_Verify]]="Valid Revenue","Include","Exclude") -> Exclude | S46: 45175 | T46: =IF(ISBLANK(Order_Date),"Missing Date",Order_Date) -> 45175 | U46: =IF(ISBLANK(Order_Date),"No","Yes") -> Yes | V46: Online | W46: Delhi | X46: =PROPER(Region) -> Delhi | Y46: 2174.71 | Z46: =IF(PC_NikeSales[[#This Row],[Profit]]<0,"Loss Making Sales",IF(PC_NikeSales[[#This Row],[Profit]]=0,"No Recorded Profit",IF($Y44>$P44,"Invalid Profit", "Valid Profit"))) -> Valid Profit | AA46: =IF(PC_NikeSales[[#This Row],[Profit_Status]]="Valid Profit","Include","Exclude") -> Include
A47: 2045 | B47: Kids | C47: Lifestyle | D47: Dunk Low | E47: XL | F47: =_xlfn.IFS(ISBLANK(Size),"Missing",ISNUMBER(Size),"Number",ISTEXT(Size),"Alphabet") -> Alphabet | G47: =IF(Size_Type ="Missing","Unknown",TRIM(Size)) -> XL | H47: =IF(Size_Verification="Unknown","No","Yes") -> Yes | I47: 4 | J47: =_xlfn.IFS(Units_Sold<0,"Check Return/Refund",Units_Sold=" ",Invalid,Units_Sold=0,"Available",Units_Sold>0,"Sold") -> Sold | M47: =IF(OR(Discount_Applied="",Discount_Applied>1,Discount_Applied<0),"Invalid","Valid") -> Invalid | N47: =IF(PC_NikeSales[[#This Row],[Discount_Verification]]="Valid","Include","Exclude") -> Exclude | O47: 0 | P47: =IF(AND(Units_Sold<>"",MRP<>"",Discount_Applied<1),Units_Sold*MRP*(1-Discount_Applied),"Insufficient Data") -> Insufficient Data | Q47: =_xlfn.IFS(Rev_Recalc="Insufficient Data","Missing Information",Rev_Recalc<0,"Negative Revenue",Rev_Recalc=0,"No Recorded Revenue",Rev_Recalc>0,"Valid Revenue") -> Missing Information | R47: =IF(PC_NikeSales[[#This Row],[Rev_Verify]]="Valid Revenue","Include","Exclude") -> Exclude | S47: 45753 | T47: =IF(ISBLANK(Order_Date),"Missing Date",Order_Date) -> 45753 | U47: =IF(ISBLANK(Order_Date),"No","Yes") -> Yes | V47: Retail | W47: Delhi | X47: =PROPER(Region) -> Delhi | Y47: 1833.94 | Z47: =IF(PC_NikeSales[[#This Row],[Profit]]<0,"Loss Making Sales",IF(PC_NikeSales[[#This Row],[Profit]]=0,"No Recorded Profit",IF($Y45>$P45,"Invalid Profit", "Valid Profit"))) -> Valid Profit | AA47: =IF(PC_NikeSales[[#This Row],[Profit_Status]]="Valid Profit","Include","Exclude") -> Include
A48: 2046 | B48: Kids | C48: Running | D48: Air Zoom | E48: 12 | F48: =_xlfn.IFS(ISBLANK(Size),"Missing",ISNUMBER(Size),"Number",ISTEXT(Size),"Alphabet") -> Number | G48: =IF(Size_Type ="Missing","Unknown",TRIM(Size)) -> 12 | H48: =IF(Size_Verification="Unknown","No","Yes") -> Yes | J48: =_xlfn.IFS(Units_Sold<0,"Check Return/Refund",Units_Sold=" ",Invalid,Units_Sold=0,"Available",Units_Sold>0,"Sold") -> Available | L48: 1.04 | M48: =IF(OR(Discount_Applied="",Discount_Applied>1,Discount_Applied<0),"Invalid","Valid") -> Invalid | N48: =IF(PC_NikeSales[[#This Row],[Discount_Verification]]="Valid","Include","Exclude") -> Exclude | O48: 0 | P48: =IF(AND(Units_Sold<>"",MRP<>"",Discount_Applied<1),Units_Sold*MRP*(1-Discount_Applied),"Insufficient Data") -> Insufficient Data | Q48: =_xlfn.IFS(Rev_Recalc="Insufficient Data","Missing Information",Rev_Recalc<0,"Negative Revenue",Rev_Recalc=0,"No Recorded Revenue",Rev_Recalc>0,"Valid Revenue") -> Missing Information | R48: =IF(PC_NikeSales[[#This Row],[Rev_Verify]]="Valid Revenue","Include","Exclude") -> Exclude | T48: =IF(ISBLANK(Order_Date),"Missing Date",Order_Date) -> Missing Date | U48: =IF(ISBLANK(Order_Date),"No","Yes") -> No | V48: Online | W48: Kolkata | X48: =PROPER(Region) -> Kolkata | Y48: 1284.33 | Z48: =IF(PC_NikeSales[[#This Row],[Profit]]<0,"Loss Making Sales",IF(PC_NikeSales[[#This Row],[Profit]]=0,"No Recorded Profit",IF($Y46>$P46,"Invalid Profit", "Valid Profit"))) -> Valid Profit | AA48: =IF(PC_NikeSales[[#This Row],[Profit_Status]]="Valid Profit","Include","Exclude") -> Include
A49: 2047 | B49: Women | C49: Training | D49: SuperRep Go | E49: 10 | F49: =_xlfn.IFS(ISBLANK(Size),"Missing",ISNUMBER(Size),"Number",ISTEXT(Size),"Alphabet") -> Number | G49: =IF(Size_Type ="Missing","Unknown",TRIM(Size)) -> 10 | H49: =IF(Size_Verification="Unknown","No","Yes") -> Yes | I49: 1 | J49: =_xlfn.IFS(Units_Sold<0,"Check Return/Refund",Units_Sold=" ",Invalid,Units_Sold=0,"Available",Units_Sold>0,"Sold") -> Sold | K49: 8577.75 | M49: =IF(OR(Discount_Applied="",Discount_Applied>1,Discount_Applied<0),"Invalid","Valid") -> Invalid | N49: =IF(PC_NikeSales[[#This Row],[Discount_Verification]]="Valid","Include","Exclude") -> Exclude | O49: 0 | P49: =IF(AND(Units_Sold<>"",MRP<>"",Discount_Applied<1),Units_Sold*MRP*(1-Discount_Applied),"Insufficient Data") -> 8577.75 | Q49: =_xlfn.IFS(Rev_Recalc="Insufficient Data","Missing Information",Rev_Recalc<0,"Negative Revenue",Rev_Recalc=0,"No Recorded Revenue",Rev_Recalc>0,"Valid Revenue") -> Valid Revenue | R49: =IF(PC_NikeSales[[#This Row],[Rev_Verify]]="Valid Revenue","Include","Exclude") -> Include | S49: 45456 | T49: =IF(ISBLANK(Order_Date),"Missing Date",Order_Date) -> 45456 | U49: =IF(ISBLANK(Order_Date),"No","Yes") -> Yes | V49: Retail | W49: Bangalore | X49: =PROPER(Region) -> Bangalore | Y49: 2888.68 | Z49: =IF(PC_NikeSales[[#This Row],[Profit]]<0,"Loss Making Sales",IF(PC_NikeSales[[#This Row],[Profit]]=0,"No Recorded Profit",IF($Y47>$P47,"Invalid Profit", "Valid Profit"))) -> Valid Profit | AA49: =IF(PC_NikeSales[[#This Row],[Profit_Status]]="Valid Profit","Include","Exclude") -> Include
A50: 2048 | B50: Women | C50: Basketball | D50: Air Jordan | E50: XL | F50: =_xlfn.IFS(ISBLANK(Size),"Missing",ISNUMBER(Size),"Number",ISTEXT(Size),"Alphabet") -> Alphabet | G50: =IF(Size_Type ="Missing","Unknown",TRIM(Size)) -> XL | H50: =IF(Size_Verification="Unknown","No","Yes") -> Yes | J50: =_xlfn.IFS(Units_Sold<0,"Check Return/Refund",Units_Sold=" ",Invalid,Units_Sold=0,"Available",Units_Sold>0,"Sold") -> Available | M50: =IF(OR(Discount_Applied="",Discount_Applied>1,Discount_Applied<0),"Invalid","Valid") -> Invalid | N50: =IF(PC_NikeSales[[#This Row],[Discount_Verification]]="Valid","Include","Exclude") -> Exclude | O50: 0 | P50: =IF(AND(Units_Sold<>"",MRP<>"",Discount_Applied<1),Units_Sold*MRP*(1-Discount_Applied),"Insufficient Data") -> Insufficient Data | Q50: =_xlfn.IFS(Rev_Recalc="Insufficient Data","Missing Information",Rev_Recalc<0,"Negative Revenue",Rev_Recalc=0,"No Recorded Revenue",Rev_Recalc>0,"Valid Revenue") -> Missing Information | R50: =IF(PC_NikeSales[[#This Row],[Rev_Verify]]="Valid Revenue","Include","Exclude") -> Exclude | S50: 45592 | T50: =IF(ISBLANK(Order_Date),"Missing Date",Order_Date) -> 45592 | U50: =IF(ISBLANK(Order_Date),"No","Yes") -> Yes | V50: Online | W50: Bangalore | X50: =PROPER(Region) -> Bangalore | Y50: 2875.86 | Z50: =IF(PC_NikeSales[[#This Row],[Profit]]<0,"Loss Making Sales",IF(PC_NikeSales[[#This Row],[Profit]]=0,"No Recorded Profit",IF($Y48>$P48,"Invalid Profit", "Valid Profit"))) -> Valid Profit | AA50: =IF(PC_NikeSales[[#This Row],[Profit_Status]]="Valid Profit","Include","Exclude") -> Include
A51: 2049 | B51: Kids | C51: Soccer | D51: Tiempo Legend | E51: L | F51: =_xlfn.IFS(ISBLANK(Size),"Missing",ISNUMBER(Size),"Number",ISTEXT(Size),"Alphabet") -> Alphabet | G51: =IF(Size_Type ="Missing","Unknown",TRIM(Size)) -> L | H51: =IF(Size_Verification="Unknown","No","Yes") -> Yes | I51: 1 | J51: =_xlfn.IFS(Units_Sold<0,"Check Return/Refund",Units_Sold=" ",Invalid,Units_Sold=0,"Available",Units_Sold>0,"Sold") -> Sold | K51: 7767.2 | M51: =IF(OR(Discount_Applied="",Discount_Applied>1,Discount_Applied<0),"Invalid","Valid") -> Invalid | N51: =IF(PC_NikeSales[[#This Row],[Discount_Verification]]="Valid","Include","Exclude") -> Exclude | O51: 0 | P51: =IF(AND(Units_Sold<>"",MRP<>"",Discount_Applied<1),Units_Sold*MRP*(1-Discount_Applied),"Insufficient Data") -> 7767.2 | Q51: =_xlfn.IFS(Rev_Recalc="Insufficient Data","Missing Information",Rev_Recalc<0,"Negative Revenue",Rev_Recalc=0,"No Recorded Revenue",Rev_Recalc>0,"Valid Revenue") -> Valid Revenue | R51: =IF(PC_NikeSales[[#This Row],[Rev_Verify]]="Valid Revenue","Include","Exclude") -> Include | T51: =IF(ISBLANK(Order_Date),"Missing Date",Order_Date) -> Missing Date | U51: =IF(ISBLANK(Order_Date),"No","Yes") -> No | V51: Retail | W51: Pune | X51: =PROPER(Region) -> Pune | Y51: 311.48 | Z51: =IF(PC_NikeSales[[#This Row],[Profit]]<0,"Loss Making Sales",IF(PC_NikeSales[[#This Row],[Profit]]=0,"No Recorded Profit",IF($Y49>$P49,"Invalid Profit", "Valid Profit"))) -> Valid Profit | AA51: =IF(PC_NikeSales[[#This Row],[Profit_Status]]="Valid Profit","Include","Exclude") -> Include
A52: 2050 | B52: Men | C52: Running | D52: Air Zoom | E52: L | F52: =_xlfn.IFS(ISBLANK(Size),"Missing",ISNUMBER(Size),"Number",ISTEXT(Size),"Alphabet") -> Alphabet | G52: =IF(Size_Type ="Missing","Unknown",TRIM(Size)) -> L | H52: =IF(Size_Verification="Unknown","No","Yes") -> Yes | I52: 1 | J52: =_xlfn.IFS(Units_Sold<0,"Check Return/Refund",Units_Sold=" ",Invalid,Units_Sold=0,"Available",Units_Sold>0,"Sold") -> Sold | L52: 0.57 | M52: =IF(OR(Discount_Applied="",Discount_Applied>1,Discount_Applied<0),"Invalid","Valid") -> Valid | N52: =IF(PC_NikeSales[[#This Row],[Discount_Verification]]="Valid","Include","Exclude") -> Include | O52: 0 | P52: =IF(AND(Units_Sold<>"",MRP<>"",Discount_Applied<1),Units_Sold*MRP*(1-Discount_Applied),"Insufficient Data") -> Insufficient Data | Q52: =_xlfn.IFS(Rev_Recalc="Insufficient Data","Missing Information",Rev_Recalc<0,"Negative Revenue",Rev_Recalc=0,"No Recorded Revenue",Rev_Recalc>0,"Valid Revenue") -> Missing Information | R52: =IF(PC_NikeSales[[#This Row],[Rev_Verify]]="Valid Revenue","Include","Exclude") -> Exclude | T52: =IF(ISBLANK(Order_Date),"Missing Date",Order_Date) -> Missing Date | U52: =IF(ISBLANK(Order_Date),"No","Yes") -> No | V52: Retail | W52: Kolkata | X52: =PROPER(Region) -> Kolkata | Y52: 682.12 | Z52: =IF(PC_NikeSales[[#This Row],[Profit]]<0,"Loss Making Sales",IF(PC_NikeSales[[#This Row],[Profit]]=0,"No Recorded Profit",IF($Y50>$P50,"Invalid Profit", "Valid Profit"))) -> Valid Profit | AA52: =IF(PC_NikeSales[[#This Row],[Profit_Status]]="Valid Profit","Include","Exclude") -> Include
A53: 2051 | B53: Women | C53: Basketball | D53: Air Jordan | E53: XL | F53: =_xlfn.IFS(ISBLANK(Size),"Missing",ISNUMBER(Size),"Number",ISTEXT(Size),"Alphabet") -> Alphabet | G53: =IF(Size_Type ="Missing","Unknown",TRIM(Size)) -> XL | H53: =IF(Size_Verification="Unknown","No","Yes") -> Yes | J53: =_xlfn.IFS(Units_Sold<0,"Check Return/Refund",Units_Sold=" ",Invalid,Units_Sold=0,"Available",Units_Sold>0,"Sold") -> Available | L53: 0.37 | M53: =IF(OR(Discount_Applied="",Discount_Applied>1,Discount_Applied<0),"Invalid","Valid") -> Valid | N53: =IF(PC_NikeSales[[#This Row],[Discount_Verification]]="Valid","Include","Exclude") -> Include | O53: 0 | P53: =IF(AND(Units_Sold<>"",MRP<>"",Discount_Applied<1),Units_Sold*MRP*(1-Discount_Applied),"Insufficient Data") -> Insufficient Data | Q53: =_xlfn.IFS(Rev_Recalc="Insufficient Data","Missing Information",Rev_Recalc<0,"Negative Revenue",Rev_Recalc=0,"No Recorded Revenue",Rev_Recalc>0,"Valid Revenue") -> Missing Information | R53: =IF(PC_NikeSales[[#This Row],[Rev_Verify]]="Valid Revenue","Include","Exclude") -> Exclude | S53: 45296 | T53: =IF(ISBLANK(Order_Date),"Missing Date",Order_Date) -> 45296 | U53: =IF(ISBLANK(Order_Date),"No","Yes") -> Yes | V53: Retail | W53: Delhi | X53: =PROPER(Region) -> Delhi | Y53: 3135.98 | Z53: =IF(PC_NikeSales[[#This Row],[Profit]]<0,"Loss Making Sales",IF(PC_NikeSales[[#This Row],[Profit]]=0,"No Recorded Profit",IF($Y51>$P51,"Invalid Profit", "Valid Profit"))) -> Valid Profit | AA53: =IF(PC_NikeSales[[#This Row],[Profit_Status]]="Valid Profit","Include","Exclude") -> Include
A54: 2052 | B54: Men | C54: Training | D54: Flex Trainer | E54: 10 | F54: =_xlfn.IFS(ISBLANK(Size),"Missing",ISNUMBER(Size),"Number",ISTEXT(Size),"Alphabet") -> Number | G54: =IF(Size_Type ="Missing","Unknown",TRIM(Size)) -> 10 | H54: =IF(Size_Verification="Unknown","No","Yes") -> Yes | I54: 3 | J54: =_xlfn.IFS(Units_Sold<0,"Check Return/Refund",Units_Sold=" ",Invalid,Units_Sold=0,"Available",Units_Sold>0,"Sold") -> Sold | K54: 9155.96 | M54: =IF(OR(Discount_Applied="",Discount_Applied>1,Discount_Applied<0),"Invalid","Valid") -> Invalid | N54: =IF(PC_NikeSales[[#This Row],[Discount_Verification]]="Valid","Include","Exclude") -> Exclude | O54: 0 | P54: =IF(AND(Units_Sold<>"",MRP<>"",Discount_Applied<1),Units_Sold*MRP*(1-Discount_Applied),"Insufficient Data") -> 27467.88 | Q54: =_xlfn.IFS(Rev_Recalc="Insufficient Data","Missing Information",Rev_Recalc<0,"Negative Revenue",Rev_Recalc=0,"No Recorded Revenue",Rev_Recalc>0,"Valid Revenue") -> Valid Revenue | R54: =IF(PC_NikeSales[[#This Row],[Rev_Verify]]="Valid Revenue","Include","Exclude") -> Include | S54: 45573 | T54: =IF(ISBLANK(Order_Date),"Missing Date",Order_Date) -> 45573 | U54: =IF(ISBLANK(Order_Date),"No","Yes") -> Yes | V54: Retail | W54: Pune | X54: =PROPER(Region) -> Pune | Y54: 2184.8 | Z54: =IF(PC_NikeSales[[#This Row],[Profit]]<0,"Loss Making Sales",IF(PC_NikeSales[[#This Row],[Profit]]=0,"No Recorded Profit",IF($Y52>$P52,"Invalid Profit", "Valid Profit"))) -> Valid Profit | AA54: =IF(PC_NikeSales[[#This Row],[Profit_Status]]="Valid Profit","Include","Exclude") -> Include
A55: 2053 | B55: Men | C55: Lifestyle | D55: Air Force 1 | E55: XL | F55: =_xlfn.IFS(ISBLANK(Size),"Missing",ISNUMBER(Size),"Number",ISTEXT(Size),"Alphabet") -> Alphabet | G55: =IF(Size_Type ="Missing","Unknown",TRIM(Size)) -> XL | H55: =IF(Size_Verification="Unknown","No","Yes") -> Yes | I55: 3 | J55: =_xlfn.IFS(Units_Sold<0,"Check Return/Refund",Units_Sold=" ",Invalid,Units_Sold=0,"Available",Units_Sold>0,"Sold") -> Sold | K55: 6009.58 | M55: =IF(OR(Discount_Applied="",Discount_Applied>1,Discount_Applied<0),"Invalid","Valid") -> Invalid | N55: =IF(PC_NikeSales[[#This Row],[Discount_Verification]]="Valid","Include","Exclude") -> Exclude | O55: 0 | P55: =IF(AND(Units_Sold<>"",MRP<>"",Discount_Applied<1),Units_Sold*MRP*(1-Discount_Applied),"Insufficient Data") -> 18028.74 | Q55: =_xlfn.IFS(Rev_Recalc="Insufficient Data","Missing Information",Rev_Recalc<0,"Negative Revenue",Rev_Recalc=0,"No Recorded Revenue",Rev_Recalc>0,"Valid Revenue") -> Valid Revenue | R55: =IF(PC_NikeSales[[#This Row],[Rev_Verify]]="Valid Revenue","Include","Exclude") -> Include | S55: 45567 | T55: =IF(ISBLANK(Order_Date),"Missing Date",Order_Date) -> 45567 | U55: =IF(ISBLANK(Order_Date),"No","Yes") -> Yes | V55: Online | W55: Delhi | X55: =PROPER(Region) -> Delhi | Y55: 3384.92 | Z55: =IF(PC_NikeSales[[#This Row],[Profit]]<0,"Loss Making Sales",IF(PC_NikeSales[[#This Row],[Profit]]=0,"No Recorded Profit",IF($Y53>$P53,"Invalid Profit", "Valid Profit"))) -> Valid Profit | AA55: =IF(PC_NikeSales[[#This Row],[Profit_Status]]="Valid Profit","Include","Exclude") -> Include
A56: 2054 | B56: Women | C56: Training | D56: Flex Trainer | E56: 11 | F56: =_xlfn.IFS(ISBLANK(Size),"Missing",ISNUMBER(Size),"Number",ISTEXT(Size),"Alphabet") -> Number | G56: =IF(Size_Type ="Missing","Unknown",TRIM(Size)) -> 11 | H56: =IF(Size_Verification="Unknown","No","Yes") -> Yes | I56: -1 | J56: =_xlfn.IFS(Units_Sold<0,"Check Return/Refund",Units_Sold=" ",Invalid,Units_Sold=0,"Available",Units_Sold>0,"Sold") -> Check Return/Refund | M56: =IF(OR(Discount_Applied="",Discount_Applied>1,Discount_Applied<0),"Invalid","Valid") -> Invalid | N56: =IF(PC_NikeSales[[#This Row],[Discount_Verification]]="Valid","Include","Exclude") -> Exclude | O56: 0 | P56: =IF(AND(Units_Sold<>"",MRP<>"",Discount_Applied<1),Units_Sold*MRP*(1-Discount_Applied),"Insufficient Data") -> Insufficient Data | Q56: =_xlfn.IFS(Rev_Recalc="Insufficient Data","Missing Information",Rev_Recalc<0,"Negative Revenue",Rev_Recalc=0,"No Recorded Revenue",Rev_Recalc>0,"Valid Revenue") -> Missing Information | R56: =IF(PC_NikeSales[[#This Row],[Rev_Verify]]="Valid Revenue","Include","Exclude") -> Exclude | S56: 45831 | T56: =IF(ISBLANK(Order_Date),"Missing Date",Order_Date) -> 45831 | U56: =IF(ISBLANK(Order_Date),"No","Yes") -> Yes | V56: Online | W56: Mumbai | X56: =PROPER(Region) -> Mumbai | Y56: -549.76 | Z56: =IF(PC_NikeSales[[#This Row],[Profit]]<0,"Loss Making Sales",IF(PC_NikeSales[[#This Row],[Profit]]=0,"No Recorded Profit",IF(PC_NikeSales[[#This Row],[Profit]]>PC_NikeSales[Rev_Recalc],"Invalid Profit", "Valid Profit"))) -> Loss Making Sales | AA56: =IF(PC_NikeSales[[#This Row],[Profit_Status]]="Valid Profit","Include","Exclude") -> Exclude
A57: 2055 | B57: Men | C57: Basketball | D57: Kyrie Flytrap | E57: L | F57: =_xlfn.IFS(ISBLANK(Size),"Missing",ISNUMBER(Size),"Number",ISTEXT(Size),"Alphabet") -> Alphabet | G57: =IF(Size_Type ="Missing","Unknown",TRIM(Size)) -> L | H57: =IF(Size_Verification="Unknown","No","Yes") -> Yes | J57: =_xlfn.IFS(Units_Sold<0,"Check Return/Refund",Units_Sold=" ",Invalid,Units_Sold=0,"Available",Units_Sold>0,"Sold") -> Available | M57: =IF(OR(Discount_Applied="",Discount_Applied>1,Discount_Applied<0),"Invalid","Valid") -> Invalid | N57: =IF(PC_NikeSales[[#This Row],[Discount_Verification]]="Valid","Include","Exclude") -> Exclude | O57: 0 | P57: =IF(AND(Units_Sold<>"",MRP<>"",Discount_Applied<1),Units_Sold*MRP*(1-Discount_Applied),"Insufficient Data") -> Insufficient Data | Q57: =_xlfn.IFS(Rev_Recalc="Insufficient Data","Missing Information",Rev_Recalc<0,"Negative Revenue",Rev_Recalc=0,"No Recorded Revenue",Rev_Recalc>0,"Valid Revenue") -> Missing Information | R57: =IF(PC_NikeSales[[#This Row],[Rev_Verify]]="Valid Revenue","Include","Exclude") -> Exclude | S57: 45591 | T57: =IF(ISBLANK(Order_Date),"Missing Date",Order_Date) -> 45591 | U57: =IF(ISBLANK(Order_Date),"No","Yes") -> Yes | V57: Online | W57: Hyderabad | X57: =PROPER(Region) -> Hyderabad | Y57: -1078.76 | Z57: =IF(PC_NikeSales[[#This Row],[Profit]]<0,"Loss Making Sales",IF(PC_NikeSales[[#This Row],[Profit]]=0,"No Recorded Profit",IF(PC_NikeSales[[#This Row],[Profit]]>PC_NikeSales[Rev_Recalc],"Invalid Profit", "Valid Profit"))) -> Loss Making Sales | AA57: =IF(PC_NikeSales[[#This Row],[Profit_Status]]="Valid Profit","Include","Exclude") -> Exclude
A58: 2056 | B58: Men | C58: Running | D58: React Infinity | E58: L | F58: =_xlfn.IFS(ISBLANK(Size),"Missing",ISNUMBER(Size),"Number",ISTEXT(Size),"Alphabet") -> Alphabet | G58: =IF(Size_Type ="Missing","Unknown",TRIM(Size)) -> L | H58: =IF(Size_Verification="Unknown","No","Yes") -> Yes | I58: 3 | J58: =_xlfn.IFS(Units_Sold<0,"Check Return/Refund",Units_Sold=" ",Invalid,Units_Sold=0,"Available",Units_Sold>0,"Sold") -> Sold | M58: =IF(OR(Discount_Applied="",Discount_Applied>1,Discount_Applied<0),"Invalid","Valid") -> Invalid | N58: =IF(PC_NikeSales[[#This Row],[Discount_Verification]]="Valid","Include","Exclude") -> Exclude | O58: 0 | P58: =IF(AND(Units_Sold<>"",MRP<>"",Discount_Applied<1),Units_Sold*MRP*(1-Discount_Applied),"Insufficient Data") -> Insufficient Data | Q58: =_xlfn.IFS(Rev_Recalc="Insufficient Data","Missing Information",Rev_Recalc<0,"Negative Revenue",Rev_Recalc=0,"No Recorded Revenue",Rev_Recalc>0,"Valid Revenue") -> Missing Information | R58: =IF(PC_NikeSales[[#This Row],[Rev_Verify]]="Valid Revenue","Include","Exclude") -> Exclude | S58: 45443 | T58: =IF(ISBLANK(Order_Date),"Missing Date",Order_Date) -> 45443 | U58: =IF(ISBLANK(Order_Date),"No","Yes") -> Yes | V58: Retail | W58: Bangalore | X58: =PROPER(Region) -> Bangalore | Y58: -244.44 | Z58: =IF(PC_NikeSales[[#This Row],[Profit]]<0,"Loss Making Sales",IF(PC_NikeSales[[#This Row],[Profit]]=0,"No Recorded Profit",IF(PC_NikeSales[[#This Row],[Profit]]>PC_NikeSales[Rev_Recalc],"Invalid Profit", "Valid Profit"))) -> Loss Making Sales | AA58: =IF(PC_NikeSales[[#This Row],[Profit_Status]]="Valid Profit","Include","Exclude") -> Exclude
A59: 2048 | B59: Men | C59: Lifestyle | D59: Waffle One | E59: M | F59: =_xlfn.IFS(ISBLANK(Size),"Missing",ISNUMBER(Size),"Number",ISTEXT(Size),"Alphabet") -> Alphabet | G59: =IF(Size_Type ="Missing","Unknown",TRIM(Size)) -> M | H59: =IF(Size_Verification="Unknown","No","Yes") -> Yes | I59: 3 | J59: =_xlfn.IFS(Units_Sold<0,"Check Return/Refund",Units_Sold=" ",Invalid,Units_Sold=0,"Available",Units_Sold>0,"Sold") -> Sold | K59: 6216.29 | L59: 0.94 | M59: =IF(OR(Discount_Applied="",Discount_Applied>1,Discount_Applied<0),"Invalid","Valid") -> Valid | N59: =IF(PC_NikeSales[[#This Row],[Discount_Verification]]="Valid","Include","Exclude") -> Include | O59: 1118.93 | P59: =IF(AND(Units_Sold<>"",MRP<>"",Discount_Applied<1),Units_Sold*MRP*(1-Discount_Applied),"Insufficient Data") -> 1118.9322 | Q59: =_xlfn.IFS(Rev_Recalc="Insufficient Data","Missing Information",Rev_Recalc<0,"Negative Revenue",Rev_Recalc=0,"No Recorded Revenue",Rev_Recalc>0,"Valid Revenue") -> Valid Revenue | R59: =IF(PC_NikeSales[[#This Row],[Rev_Verify]]="Valid Revenue","Include","Exclude") -> Include | S59: 45549 | T59: =IF(ISBLANK(Order_Date),"Missing Date",Order_Date) -> 45549 | U59: =IF(ISBLANK(Order_Date),"No","Yes") -> Yes | V59: Online | W59: Mumbai | X59: =PROPER(Region) -> Mumbai | Y59: -642.02 | Z59: =IF(PC_NikeSales[[#This Row],[Profit]]<0,"Loss Making Sales",IF(PC_NikeSales[[#This Row],[Profit]]=0,"No Recorded Profit",IF(PC_NikeSales[[#This Row],[Profit]]>PC_NikeSales[Rev_Recalc],"Invalid Profit", "Valid Profit"))) -> Loss Making Sales | AA59: =IF(PC_NikeSales[[#This Row],[Profit_Status]]="Valid Profit","Include","Exclude") -> Exclude
A60: 2058 | B60: Women | C60: Training | D60: Flex Trainer | E60: 11 | F60: =_xlfn.IFS(ISBLANK(Size),"Missing",ISNUMBER(Size),"Number",ISTEXT(Size),"Alphabet") -> Number | G60: =IF(Size_Type ="Missing","Unknown",TRIM(Size)) -> 11 | H60: =IF(Size_Verification="Unknown","No","Yes") -> Yes | J60: =_xlfn.IFS(Units_Sold<0,"Check Return/Refund",Units_Sold=" ",Invalid,Units_Sold=0,"Available",Units_Sold>0,"Sold") -> Available | K60: 4985.92 | M60: =IF(OR(Discount_Applied="",Discount_Applied>1,Discount_Applied<0),"Invalid","Valid") -> Invalid | N60: =IF(PC_NikeSales[[#This Row],[Discount_Verification]]="Valid","Include","Exclude") -> Exclude | O60: 0 | P60: =IF(AND(Units_Sold<>"",MRP<>"",Discount_Applied<1),Units_Sold*MRP*(1-Discount_Applied),"Insufficient Data") -> Insufficient Data | Q60: =_xlfn.IFS(Rev_Recalc="Insufficient Data","Missing Information",Rev_Recalc<0,"Negative Revenue",Rev_Recalc=0,"No Recorded Revenue",Rev_Recalc>0,"Valid Revenue") -> Missing Information | R60: =IF(PC_NikeSales[[#This Row],[Rev_Verify]]="Valid Revenue","Include","Exclude") -> Exclude | T60: =IF(ISBLANK(Order_Date),"Missing Date",Order_Date) -> Missing Date | U60: =IF(ISBLANK(Order_Date),"No","Yes") -> No | V60: Online | W60: Kolkata | X60: =PROPER(Region) -> Kolkata | Y60: 361.54 | Z60: =IF(PC_NikeSales[[#This Row],[Profit]]<0,"Loss Making Sales",IF(PC_NikeSales[[#This Row],[Profit]]=0,"No Recorded Profit",IF($Y58>$P58,"Invalid Profit", "Valid Profit"))) -> Valid Profit | AA60: =IF(PC_NikeSales[[#This Row],[Profit_Status]]="Valid Profit","Include","Exclude") -> Include
A61: 2059 | B61: Kids | C61: Soccer | D61: Phantom GT | F61: =_xlfn.IFS(ISBLANK(Size),"Missing",ISNUMBER(Size),"Number",ISTEXT(Size),"Alphabet") -> Missing | G61: =IF(Size_Type ="Missing","Unknown",TRIM(Size)) -> Unknown | H61: =IF(Size_Verification="Unknown","No","Yes") -> No | I61: -1 | J61: =_xlfn.IFS(Units_Sold<0,"Check Return/Refund",Units_Sold=" ",Invalid,Units_Sold=0,"Available",Units_Sold>0,"Sold") -> Check Return/Refund | K61: 9507.54 | M61: =IF(OR(Discount_Applied="",Discount_Applied>1,Discount_Applied<0),"Invalid","Valid") -> Invalid | N61: =IF(PC_NikeSales[[#This Row],[Discount_Verification]]="Valid","Include","Exclude") -> Exclude | O61: 0 | P61: =IF(AND(Units_Sold<>"",MRP<>"",Discount_Applied<1),Units_Sold*MRP*(1-Discount_Applied),"Insufficient Data") -> -9507.54 | Q61: =_xlfn.IFS(Rev_Recalc="Insufficient Data","Missing Information",Rev_Recalc<0,"Negative Revenue",Rev_Recalc=0,"No Recorded Revenue",Rev_Recalc>0,"Valid Revenue") -> Negative Revenue | R61: =IF(PC_NikeSales[[#This Row],[Rev_Verify]]="Valid Revenue","Include","Exclude") -> Exclude | S61: 45287 | T61: =IF(ISBLANK(Order_Date),"Missing Date",Order_Date) -> 45287 | U61: =IF(ISBLANK(Order_Date),"No","Yes") -> Yes | V61: Retail | W61: Delhi | X61: =PROPER(Region) -> Delhi | Y61: 291.28 | Z61: =IF(PC_NikeSales[[#This Row],[Profit]]<0,"Loss Making Sales",IF(PC_NikeSales[[#This Row],[Profit]]=0,"No Recorded Profit",IF(PC_NikeSales[[#This Row],[Profit]]>PC_NikeSales[Rev_Recalc],"Invalid Profit", "Valid Profit"))) -> Invalid Profit | AA61: =IF(PC_NikeSales[[#This Row],[Profit_Status]]="Valid Profit","Include","Exclude") -> Exclude
A62: 2060 | B62: Men | C62: Lifestyle | D62: Waffle One | E62: L | F62: =_xlfn.IFS(ISBLANK(Size),"Missing",ISNUMBER(Size),"Number",ISTEXT(Size),"Alphabet") -> Alphabet | G62: =IF(Size_Type ="Missing","Unknown",TRIM(Size)) -> L | H62: =IF(Size_Verification="Unknown","No","Yes") -> Yes | I62: 2 | J62: =_xlfn.IFS(Units_Sold<0,"Check Return/Refund",Units_Sold=" ",Invalid,Units_Sold=0,"Available",Units_Sold>0,"Sold") -> Sold | K62: 7979.26 | M62: =IF(OR(Discount_Applied="",Discount_Applied>1,Discount_Applied<0),"Invalid","Valid") -> Invalid | N62: =IF(PC_NikeSales[[#This Row],[Discount_Verification]]="Valid","Include","Exclude") -> Exclude | O62: 0 | P62: =IF(AND(Units_Sold<>"",MRP<>"",Discount_Applied<1),Units_Sold*MRP*(1-Discount_Applied),"Insufficient Data") -> 15958.52 | Q62: =_xlfn.IFS(Rev_Recalc="Insufficient Data","Missing Information",Rev_Recalc<0,"Negative Revenue",Rev_Recalc=0,"No Recorded Revenue",Rev_Recalc>0,"Valid Revenue") -> Valid Revenue | R62: =IF(PC_NikeSales[[#This Row],[Rev_Verify]]="Valid Revenue","Include","Exclude") -> Include | S62: 45484 | T62: =IF(ISBLANK(Order_Date),"Missing Date",Order_Date) -> 45484 | U62: =IF(ISBLANK(Order_Date),"No","Yes") -> Yes | V62: Online | W62: bengaluru | X62: =PROPER(Region) -> Bengaluru | Y62: 2821.59 | Z62: =IF(PC_NikeSales[[#This Row],[Profit]]<0,"Loss Making Sales",IF(PC_NikeSales[[#This Row],[Profit]]=0,"No Recorded Profit",IF($Y60>$P60,"Invalid Profit", "Valid Profit"))) -> Valid Profit | AA62: =IF(PC_NikeSales[[#This Row],[Profit_Status]]="Valid Profit","Include","Exclude") -> Include
A63: 2061 | B63: Women | C63: Basketball | D63: LeBron 20 | E63: L | F63: =_xlfn.IFS(ISBLANK(Size),"Missing",ISNUMBER(Size),"Number",ISTEXT(Size),"Alphabet") -> Alphabet | G63: =IF(Size_Type ="Missing","Unknown",TRIM(Size)) -> L | H63: =IF(Size_Verification="Unknown","No","Yes") -> Yes | J63: =_xlfn.IFS(Units_Sold<0,"Check Return/Refund",Units_Sold=" ",Invalid,Units_Sold=0,"Available",Units_Sold>0,"Sold") -> Available | M63: =IF(OR(Discount_Applied="",Discount_Applied>1,Discount_Applied<0),"Invalid","Valid") -> Invalid | N63: =IF(PC_NikeSales[[#This Row],[Discount_Verification]]="Valid","Include","Exclude") -> Exclude | O63: 0 | P63: =IF(AND(Units_Sold<>"",MRP<>"",Discount_Applied<1),Units_Sold*MRP*(1-Discount_Applied),"Insufficient Data") -> Insufficient Data | Q63: =_xlfn.IFS(Rev_Recalc="Insufficient Data","Missing Information",Rev_Recalc<0,"Negative Revenue",Rev_Recalc=0,"No Recorded Revenue",Rev_Recalc>0,"Valid Revenue") -> Missing Information | R63: =IF(PC_NikeSales[[#This Row],[Rev_Verify]]="Valid Revenue","Include","Exclude") -> Exclude | S63: 45545 | T63: =IF(ISBLANK(Order_Date),"Missing Date",Order_Date) -> 45545 | U63: =IF(ISBLANK(Order_Date),"No","Yes") -> Yes | V63: Online | W63: Mumbai | X63: =PROPER(Region) -> Mumbai | Y63: -501.68 | Z63: =IF(PC_NikeSales[[#This Row],[Profit]]<0,"Loss Making Sales",IF(PC_NikeSales[[#This Row],[Profit]]=0,"No Recorded Profit",IF(PC_NikeSales[[#This Row],[Profit]]>PC_NikeSales[Rev_Recalc],"Invalid Profit", "Valid Profit"))) -> Loss Making Sales | AA63: =IF(PC_NikeSales[[#This Row],[Profit_Status]]="Valid Profit","Include","Exclude") -> Exclude
A64: 2062 | B64: Men | C64: Basketball | D64: Air Jordan | F64: =_xlfn.IFS(ISBLANK(Size),"Missing",ISNUMBER(Size),"Number",ISTEXT(Size),"Alphabet") -> Missing | G64: =IF(Size_Type ="Missing","Unknown",TRIM(Size)) -> Unknown | H64: =IF(Size_Verification="Unknown","No","Yes") -> No | I64: 2 | J64: =_xlfn.IFS(Units_Sold<0,"Check Return/Refund",Units_Sold=" ",Invalid,Units_Sold=0,"Available",Units_Sold>0,"Sold") -> Sold | M64: =IF(OR(Discount_Applied="",Discount_Applied>1,Discount_Applied<0),"Invalid","Valid") -> Invalid | N64: =IF(PC_NikeSales[[#This Row],[Discount_Verification]]="Valid","Include","Exclude") -> Exclude | O64: 0 | P64: =IF(AND(Units_Sold<>"",MRP<>"",Discount_Applied<1),Units_Sold*MRP*(1-Discount_Applied),"Insufficient Data") -> Insufficient Data | Q64: =_xlfn.IFS(Rev_Recalc="Insufficient Data","Missing Information",Rev_Recalc<0,"Negative Revenue",Rev_Recalc=0,"No Recorded Revenue",Rev_Recalc>0,"Valid Revenue") -> Missing Information | R64: =IF(PC_NikeSales[[#This Row],[Rev_Verify]]="Valid Revenue","Include","Exclude") -> Exclude | S64: 45814 | T64: =IF(ISBLANK(Order_Date),"Missing Date",Order_Date) -> 45814 | U64: =IF(ISBLANK(Order_Date),"No","Yes") -> Yes | V64: Online | W64: Bangalore | X64: =PROPER(Region) -> Bangalore | Y64: 1823.91 | Z64: =IF(PC_NikeSales[[#This Row],[Profit]]<0,"Loss Making Sales",IF(PC_NikeSales[[#This Row],[Profit]]=0,"No Recorded Profit",IF($Y62>$P62,"Invalid Profit", "Valid Profit"))) -> Valid Profit | AA64: =IF(PC_NikeSales[[#This Row],[Profit_Status]]="Valid Profit","Include","Exclude") -> Include
A65: 2063 | B65: Women | C65: Basketball | D65: Air Jordan | E65: M | F65: =_xlfn.IFS(ISBLANK(Size),"Missing",ISNUMBER(Size),"Number",ISTEXT(Size),"Alphabet") -> Alphabet | G65: =IF(Size_Type ="Missing","Unknown",TRIM(Size)) -> M | H65: =IF(Size_Verification="Unknown","No","Yes") -> Yes | I65: 1 | J65: =_xlfn.IFS(Units_Sold<0,"Check Return/Refund",Units_Sold=" ",Invalid,Units_Sold=0,"Available",Units_Sold>0,"Sold") -> Sold | K65: 9751 | L65: 0.16 | M65: =IF(OR(Discount_Applied="",Discount_Applied>1,Discount_Applied<0),"Invalid","Valid") -> Valid | N65: =IF(PC_NikeSales[[#This Row],[Discount_Verification]]="Valid","Include","Exclude") -> Include | O65: 8190.84 | P65: =IF(AND(Units_Sold<>"",MRP<>"",Discount_Applied<1),Units_Sold*MRP*(1-Discount_Applied),"Insufficient Data") -> 8190.84 | Q65: =_xlfn.IFS(Rev_Recalc="Insufficient Data","Missing Information",Rev_Recalc<0,"Negative Revenue",Rev_Recalc=0,"No Recorded Revenue",Rev_Recalc>0,"Valid Revenue") -> Valid Revenue | R65: =IF(PC_NikeSales[[#This Row],[Rev_Verify]]="Valid Revenue","Include","Exclude") -> Include | S65: 45541 | T65: =IF(ISBLANK(Order_Date),"Missing Date",Order_Date) -> 45541 | U65: =IF(ISBLANK(Order_Date),"No","Yes") -> Yes | V65: Retail | W65: Pune | X65: =PROPER(Region) -> Pune | Y65: 1130.31 | Z65: =IF(PC_NikeSales[[#This Row],[Profit]]<0,"Loss Making Sales",IF(PC_NikeSales[[#This Row],[Profit]]=0,"No Recorded Profit",IF($Y63>$P63,"Invalid Profit", "Valid Profit"))) -> Valid Profit | AA65: =IF(PC_NikeSales[[#This Row],[Profit_Status]]="Valid Profit","Include","Exclude") -> Include
A66: 2064 | B66: Kids | C66: Running | D66: React Infinity | E66: L | F66: =_xlfn.IFS(ISBLANK(Size),"Missing",ISNUMBER(Size),"Number",ISTEXT(Size),"Alphabet") -> Alphabet | G66: =IF(Size_Type ="Missing","Unknown",TRIM(Size)) -> L | H66: =IF(Size_Verification="Unknown","No","Yes") -> Yes | I66: 2 | J66: =_xlfn.IFS(Units_Sold<0,"Check Return/Refund",Units_Sold=" ",Invalid,Units_Sold=0,"Available",Units_Sold>0,"Sold") -> Sold | K66: 7557.71 | M66: =IF(OR(Discount_Applied="",Discount_Applied>1,Discount_Applied<0),"Invalid","Valid") -> Invalid | N66: =IF(PC_NikeSales[[#This Row],[Discount_Verification]]="Valid","Include","Exclude") -> Exclude | O66: 0 | P66: =IF(AND(Units_Sold<>"",MRP<>"",Discount_Applied<1),Units_Sold*MRP*(1-Discount_Applied),"Insufficient Data") -> 15115.42 | Q66: =_xlfn.IFS(Rev_Recalc="Insufficient Data","Missing Information",Rev_Recalc<0,"Negative Revenue",Rev_Recalc=0,"No Recorded Revenue",Rev_Recalc>0,"Valid Revenue") -> Valid Revenue | R66: =IF(PC_NikeSales[[#This Row],[Rev_Verify]]="Valid Revenue","Include","Exclude") -> Include | S66: 45718 | T66: =IF(ISBLANK(Order_Date),"Missing Date",Order_Date) -> 45718 | U66: =IF(ISBLANK(Order_Date),"No","Yes") -> Yes | V66: Online | W66: Bangalore | X66: =PROPER(Region) -> Bangalore | Y66: 3277.44 | Z66: =IF(PC_NikeSales[[#This Row],[Profit]]<0,"Loss Making Sales",IF(PC_NikeSales[[#This Row],[Profit]]=0,"No Recorded Profit",IF($Y64>$P64,"Invalid Profit", "Valid Profit"))) -> Valid Profit | AA66: =IF(PC_NikeSales[[#This Row],[Profit_Status]]="Valid Profit","Include","Exclude") -> Include
A67: 2065 | B67: Women | C67: Lifestyle | D67: Waffle One | E67: 10 | F67: =_xlfn.IFS(ISBLANK(Size),"Missing",ISNUMBER(Size),"Number",ISTEXT(Size),"Alphabet") -> Number | G67: =IF(Size_Type ="Missing","Unknown",TRIM(Size)) -> 10 | H67: =IF(Size_Verification="Unknown","No","Yes") -> Yes | J67: =_xlfn.IFS(Units_Sold<0,"Check Return/Refund",Units_Sold=" ",Invalid,Units_Sold=0,"Available",Units_Sold>0,"Sold") -> Available | L67: 0.78 | M67: =IF(OR(Discount_Applied="",Discount_Applied>1,Discount_Applied<0),"Invalid","Valid") -> Valid | N67: =IF(PC_NikeSales[[#This Row],[Discount_Verification]]="Valid","Include","Exclude") -> Include | O67: 0 | P67: =IF(AND(Units_Sold<>"",MRP<>"",Discount_Applied<1),Units_Sold*MRP*(1-Discount_Applied),"Insufficient Data") -> Insufficient Data | Q67: =_xlfn.IFS(Rev_Recalc="Insufficient Data","Missing Information",Rev_Recalc<0,"Negative Revenue",Rev_Recalc=0,"No Recorded Revenue",Rev_Recalc>0,"Valid Revenue") -> Missing Information | R67: =IF(PC_NikeSales[[#This Row],[Rev_Verify]]="Valid Revenue","Include","Exclude") -> Exclude | S67: 45333 | T67: =IF(ISBLANK(Order_Date),"Missing Date",Order_Date) -> 45333 | U67: =IF(ISBLANK(Order_Date),"No","Yes") -> Yes | V67: Retail | W67: Hyderabad | X67: =PROPER(Region) -> Hyderabad | Y67: 21.58 | Z67: =IF(PC_NikeSales[[#This Row],[Profit]]<0,"Loss Making Sales",IF(PC_NikeSales[[#This Row],[Profit]]=0,"No Recorded Profit",IF($Y65>$P65,"Invalid Profit", "Valid Profit"))) -> Valid Profit | AA67: =IF(PC_NikeSales[[#This Row],[Profit_Status]]="Valid Profit","Include","Exclude") -> Include
A68: 2066 | B68: Men | C68: Soccer | D68: Phantom GT | E68: XL | F68: =_xlfn.IFS(ISBLANK(Size),"Missing",ISNUMBER(Size),"Number",ISTEXT(Size),"Alphabet") -> Alphabet | G68: =IF(Size_Type ="Missing","Unknown",TRIM(Size)) -> XL | H68: =IF(Size_Verification="Unknown","No","Yes") -> Yes | I68: -1 | J68: =_xlfn.IFS(Units_Sold<0,"Check Return/Refund",Units_Sold=" ",Invalid,Units_Sold=0,"Available",Units_Sold>0,"Sold") -> Check Return/Refund | K68: 5259.05 | M68: =IF(OR(Discount_Applied="",Discount_Applied>1,Discount_Applied<0),"Invalid","Valid") -> Invalid | N68: =IF(PC_NikeSales[[#This Row],[Discount_Verification]]="Valid","Include","Exclude") -> Exclude | O68: 0 | P68: =IF(AND(Units_Sold<>"",MRP<>"",Discount_Applied<1),Units_Sold*MRP*(1-Discount_Applied),"Insufficient Data") -> -5259.05 | Q68: =_xlfn.IFS(Rev_Recalc="Insufficient Data","Missing Information",Rev_Recalc<0,"Negative Revenue",Rev_Recalc=0,"No Recorded Revenue",Rev_Recalc>0,"Valid Revenue") -> Negative Revenue | R68: =IF(PC_NikeSales[[#This Row],[Rev_Verify]]="Valid Revenue","Include","Exclude") -> Exclude | S68: 45636 | T68: =IF(ISBLANK(Order_Date),"Missing Date",Order_Date) -> 45636 | U68: =IF(ISBLANK(Order_Date),"No","Yes") -> Yes | V68: Online | W68: Mumbai | X68: =PROPER(Region) -> Mumbai | Y68: 1022.82 | Z68: =IF(PC_NikeSales[[#This Row],[Profit]]<0,"Loss Making Sales",IF(PC_NikeSales[[#This Row],[Profit]]=0,"No Recorded Profit",IF(PC_NikeSales[[#This Row],[Profit]]>PC_NikeSales[Rev_Recalc],"Invalid Profit", "Valid Profit"))) -> Invalid Profit | AA68: =IF(PC_NikeSales[[#This Row],[Profit_Status]]="Valid Profit","Include","Exclude") -> Exclude
A69: 2067 | B69: Kids | C69: Basketball | D69: LeBron 20 | E69: L | F69: =_xlfn.IFS(ISBLANK(Size),"Missing",ISNUMBER(Size),"Number",ISTEXT(Size),"Alphabet") -> Alphabet | G69: =IF(Size_Type ="Missing","Unknown",TRIM(Size)) -> L | H69: =IF(Size_Verification="Unknown","No","Yes") -> Yes | I69: 4 | J69: =_xlfn.IFS(Units_Sold<0,"Check Return/Refund",Units_Sold=" ",Invalid,Units_Sold=0,"Available",Units_Sold>0,"Sold") -> Sold | K69: 3588.38 | M69: =IF(OR(Discount_Applied="",Discount_Applied>1,Discount_Applied<0),"Invalid","Valid") -> Invalid | N69: =IF(PC_NikeSales[[#This Row],[Discount_Verification]]="Valid","Include","Exclude") -> Exclude | O69: 0 | P69: =IF(AND(Units_Sold<>"",MRP<>"",Discount_Applied<1),Units_Sold*MRP*(1-Discount_Applied),"Insufficient Data") -> 14353.52 | Q69: =_xlfn.IFS(Rev_Recalc="Insufficient Data","Missing Information",Rev_Recalc<0,"Negative Revenue",Rev_Recalc=0,"No Recorded Revenue",Rev_Recalc>0,"Valid Revenue") -> Valid Revenue | R69: =IF(PC_NikeSales[[#This Row],[Rev_Verify]]="Valid Revenue","Include","Exclude") -> Include | S69: 45783 | T69: =IF(ISBLANK(Order_Date),"Missing Date",Order_Date) -> 45783 | U69: =IF(ISBLANK(Order_Date),"No","Yes") -> Yes | V69: Online | W69: Kolkata | X69: =PROPER(Region) -> Kolkata | Y69: 161.5 | Z69: =IF(PC_NikeSales[[#This Row],[Profit]]<0,"Loss Making Sales",IF(PC_NikeSales[[#This Row],[Profit]]=0,"No Recorded Profit",IF($Y67>$P67,"Invalid Profit", "Valid Profit"))) -> Valid Profit | AA69: =IF(PC_NikeSales[[#This Row],[Profit_Status]]="Valid Profit","Include","Exclude") -> Include
A70: 2068 | B70: Men | C70: Running | D70: Free RN | F70: =_xlfn.IFS(ISBLANK(Size),"Missing",ISNUMBER(Size),"Number",ISTEXT(Size),"Alphabet") -> Missing | G70: =IF(Size_Type ="Missing","Unknown",TRIM(Size)) -> Unknown | H70: =IF(Size_Verification="Unknown","No","Yes") -> No | I70: 4 | J70: =_xlfn.IFS(Units_Sold<0,"Check Return/Refund",Units_Sold=" ",Invalid,Units_Sold=0,"Available",Units_Sold>0,"Sold") -> Sold | K70: 2553.29 | M70: =IF(OR(Discount_Applied="",Discount_Applied>1,Discount_Applied<0),"Invalid","Valid") -> Invalid | N70: =IF(PC_NikeSales[[#This Row],[Discount_Verification]]="Valid","Include","Exclude") -> Exclude | O70: 0 | P70: =IF(AND(Units_Sold<>"",MRP<>"",Discount_Applied<1),Units_Sold*MRP*(1-Discount_Applied),"Insufficient Data") -> 10213.16 | Q70: =_xlfn.IFS(Rev_Recalc="Insufficient Data","Missing Information",Rev_Recalc<0,"Negative Revenue",Rev_Recalc=0,"No Recorded Revenue",Rev_Recalc>0,"Valid Revenue") -> Valid Revenue | R70: =IF(PC_NikeSales[[#This Row],[Rev_Verify]]="Valid Revenue","Include","Exclude") -> Include | S70: 45631 | T70: =IF(ISBLANK(Order_Date),"Missing Date",Order_Date) -> 45631 | U70: =IF(ISBLANK(Order_Date),"No","Yes") -> Yes | V70: Retail | W70: Mumbai | X70: =PROPER(Region) -> Mumbai | Y70: 984.9 | Z70: =IF(PC_NikeSales[[#This Row],[Profit]]<0,"Loss Making Sales",IF(PC_NikeSales[[#This Row],[Profit]]=0,"No Recorded Profit",IF($Y68>$P68,"Invalid Profit", "Valid Profit"))) -> Invalid Profit | AA70: =IF(PC_NikeSales[[#This Row],[Profit_Status]]="Valid Profit","Include","Exclude") -> Exclude
A71: 2069 | B71: Women | C71: Training | D71: SuperRep Go | F71: =_xlfn.IFS(ISBLANK(Size),"Missing",ISNUMBER(Size),"Number",ISTEXT(Size),"Alphabet") -> Missing | G71: =IF(Size_Type ="Missing","Unknown",TRIM(Size)) -> Unknown | H71: =IF(Size_Verification="Unknown","No","Yes") -> No | J71: =_xlfn.IFS(Units_Sold<0,"Check Return/Refund",Units_Sold=" ",Invalid,Units_Sold=0,"Available",Units_Sold>0,"Sold") -> Available | K71: 7502.24 | M71: =IF(OR(Discount_Applied="",Discount_Applied>1,Discount_Applied<0),"Invalid","Valid") -> Invalid | N71: =IF(PC_NikeSales[[#This Row],[Discount_Verification]]="Valid","Include","Exclude") -> Exclude | O71: 0 | P71: =IF(AND(Units_Sold<>"",MRP<>"",Discount_Applied<1),Units_Sold*MRP*(1-Discount_Applied),"Insufficient Data") -> Insufficient Data | Q71: =_xlfn.IFS(Rev_Recalc="Insufficient Data","Missing Information",Rev_Recalc<0,"Negative Revenue",Rev_Recalc=0,"No Recorded Revenue",Rev_Recalc>0,"Valid Revenue") -> Missing Information | R71: =IF(PC_NikeSales[[#This Row],[Rev_Verify]]="Valid Revenue","Include","Exclude") -> Exclude | S71: 45852 | T71: =IF(ISBLANK(Order_Date),"Missing Date",Order_Date) -> 45852 | U71: =IF(ISBLANK(Order_Date),"No","Yes") -> Yes | V71: Online | W71: Pune | X71: =PROPER(Region) -> Pune | Y71: 3554.58 | Z71: =IF(PC_NikeSales[[#This Row],[Profit]]<0,"Loss Making Sales",IF(PC_NikeSales[[#This Row],[Profit]]=0,"No Recorded Profit",IF($Y69>$P69,"Invalid Profit", "Valid Profit"))) -> Valid Profit | AA71: =IF(PC_NikeSales[[#This Row],[Profit_Status]]="Valid Profit","Include","Exclude") -> Include
A72: 2070 | B72: Kids | C72: Running | D72: React Infinity | E72: L | F72: =_xlfn.IFS(ISBLANK(Size),"Missing",ISNUMBER(Size),"Number",ISTEXT(Size),"Alphabet") -> Alphabet | G72: =IF(Size_Type ="Missing","Unknown",TRIM(Size)) -> L | H72: =IF(Size_Verification="Unknown","No","Yes") -> Yes | J72: =_xlfn.IFS(Units_Sold<0,"Check Return/Refund",Units_Sold=" ",Invalid,Units_Sold=0,"Available",Units_Sold>0,"Sold") -> Available | M72: =IF(OR(Discount_Applied="",Discount_Applied>1,Discount_Applied<0),"Invalid","Valid") -> Invalid | N72: =IF(PC_NikeSales[[#This Row],[Discount_Verification]]="Valid","Include","Exclude") -> Exclude | O72: 0 | P72: =IF(AND(Units_Sold<>"",MRP<>"",Discount_Applied<1),Units_Sold*MRP*(1-Discount_Applied),"Insufficient Data") -> Insufficient Data | Q72: =_xlfn.IFS(Rev_Recalc="Insufficient Data","Missing Information",Rev_Recalc<0,"Negative Revenue",Rev_Recalc=0,"No Recorded Revenue",Rev_Recalc>0,"Valid Revenue") -> Missing Information | R72: =IF(PC_NikeSales[[#This Row],[Rev_Verify]]="Valid Revenue","Include","Exclude") -> Exclude | T72: =IF(ISBLANK(Order_Date),"Missing Date",Order_Date) -> Missing Date | U72: =IF(ISBLANK(Order_Date),"No","Yes") -> No | V72: Retail | W72: Mumbai | X72: =PROPER(Region) -> Mumbai | Y72: 1112.43 | Z72: =IF(PC_NikeSales[[#This Row],[Profit]]<0,"Loss Making Sales",IF(PC_NikeSales[[#This Row],[Profit]]=0,"No Recorded Profit",IF($Y70>$P70,"Invalid Profit", "Valid Profit"))) -> Valid Profit | AA72: =IF(PC_NikeSales[[#This Row],[Profit_Status]]="Valid Profit","Include","Exclude") -> Include
A73: 2071 | B73: Kids | C73: Lifestyle | D73: Blazer Mid | E73: M | F73: =_xlfn.IFS(ISBLANK(Size),"Missing",ISNUMBER(Size),"Number",ISTEXT(Size),"Alphabet") -> Alphabet | G73: =IF(Size_Type ="Missing","Unknown",TRIM(Size)) -> M | H73: =IF(Size_Verification="Unknown","No","Yes") -> Yes | I73: 3 | J73: =_xlfn.IFS(Units_Sold<0,"Check Return/Refund",Units_Sold=" ",Invalid,Units_Sold=0,"Available",Units_Sold>0,"Sold") -> Sold | K73: 7849.81 | L73: 0.49 | M73: =IF(OR(Discount_Applied="",Discount_Applied>1,Discount_Applied<0),"Invalid","Valid") -> Valid | N73: =IF(PC_NikeSales[[#This Row],[Discount_Verification]]="Valid","Include","Exclude") -> Include | O73: 12010.21 | P73: =IF(AND(Units_Sold<>"",MRP<>"",Discount_Applied<1),Units_Sold*MRP*(1-Discount_Applied),"Insufficient Data") -> 12010.209 | Q73: =_xlfn.IFS(Rev_Recalc="Insufficient Data","Missing Information",Rev_Recalc<0,"Negative Revenue",Rev_Recalc=0,"No Recorded Revenue",Rev_Recalc>0,"Valid Revenue") -> Valid Revenue | R73: =IF(PC_NikeSales[[#This Row],[Rev_Verify]]="Valid Revenue","Include","Exclude") -> Include | S73: 45669 | T73: =IF(ISBLANK(Order_Date),"Missing Date",Order_Date) -> 45669 | U73: =IF(ISBLANK(Order_Date),"No","Yes") -> Yes | V73: Retail | W73: Pune | X73: =PROPER(Region) -> Pune | Y73: -882.96 | Z73: =IF(PC_NikeSales[[#This Row],[Profit]]<0,"Loss Making Sales",IF(PC_NikeSales[[#This Row],[Profit]]=0,"No Recorded Profit",IF(PC_NikeSales[[#This Row],[Profit]]>PC_NikeSales[Rev_Recalc],"Invalid Profit", "Valid Profit"))) -> Loss Making Sales | AA73: =IF(PC_NikeSales[[#This Row],[Profit_Status]]="Valid Profit","Include","Exclude") -> Exclude
A74: 2072 | B74: Men | C74: Training | D74: Flex Trainer | F74: =_xlfn.IFS(ISBLANK(Size),"Missing",ISNUMBER(Size),"Number",ISTEXT(Size),"Alphabet") -> Missing | G74: =IF(Size_Type ="Missing","Unknown",TRIM(Size)) -> Unknown | H74: =IF(Size_Verification="Unknown","No","Yes") -> No | I74: 3 | J74: =_xlfn.IFS(Units_Sold<0,"Check Return/Refund",Units_Sold=" ",Invalid,Units_Sold=0,"Available",Units_Sold>0,"Sold") -> Sold | M74: =IF(OR(Discount_Applied="",Discount_Applied>1,Discount_Applied<0),"Invalid","Valid") -> Invalid | N74: =IF(PC_NikeSales[[#This Row],[Discount_Verification]]="Valid","Include","Exclude") -> Exclude | O74: 0 | P74: =IF(AND(Units_Sold<>"",MRP<>"",Discount_Applied<1),Units_Sold*MRP*(1-Discount_Applied),"Insufficient Data") -> Insufficient Data | Q74: =_xlfn.IFS(Rev_Recalc="Insufficient Data","Missing Information",Rev_Recalc<0,"Negative Revenue",Rev_Recalc=0,"No Recorded Revenue",Rev_Recalc>0,"Valid Revenue") -> Missing Information | R74: =IF(PC_NikeSales[[#This Row],[Rev_Verify]]="Valid Revenue","Include","Exclude") -> Exclude | T74: =IF(ISBLANK(Order_Date),"Missing Date",Order_Date) -> Missing Date | U74: =IF(ISBLANK(Order_Date),"No","Yes") -> No | V74: Retail | W74: Pune | X74: =PROPER(Region) -> Pune | Y74: 3639.2 | Z74: =IF(PC_NikeSales[[#This Row],[Profit]]<0,"Loss Making Sales",IF(PC_NikeSales[[#This Row],[Profit]]=0,"No Recorded Profit",IF($Y72>$P72,"Invalid Profit", "Valid Profit"))) -> Valid Profit | AA74: =IF(PC_NikeSales[[#This Row],[Profit_Status]]="Valid Profit","Include","Exclude") -> Include
A75: 2073 | B75: Women | C75: Lifestyle | D75: Blazer Mid | E75: 12 | F75: =_xlfn.IFS(ISBLANK(Size),"Missing",ISNUMBER(Size),"Number",ISTEXT(Size),"Alphabet") -> Number | G75: =IF(Size_Type ="Missing","Unknown",TRIM(Size)) -> 12 | H75: =IF(Size_Verification="Unknown","No","Yes") -> Yes | I75: 4 | J75: =_xlfn.IFS(Units_Sold<0,"Check Return/Refund",Units_Sold=" ",Invalid,Units_Sold=0,"Available",Units_Sold>0,"Sold") -> Sold | L75: 0.85 | M75: =IF(OR(Discount_Applied="",Discount_Applied>1,Discount_Applied<0),"Invalid","Valid") -> Valid | N75: =IF(PC_NikeSales[[#This Row],[Discount_Verification]]="Valid","Include","Exclude") -> Include | O75: 0 | P75: =IF(AND(Units_Sold<>"",MRP<>"",Discount_Applied<1),Units_Sold*MRP*(1-Discount_Applied),"Insufficient Data") -> Insufficient Data | Q75: =_xlfn.IFS(Rev_Recalc="Insufficient Data","Missing Information",Rev_Recalc<0,"Negative Revenue",Rev_Recalc=0,"No Recorded Revenue",Rev_Recalc>0,"Valid Revenue") -> Missing Information | R75: =IF(PC_NikeSales[[#This Row],[Rev_Verify]]="Valid Revenue","Include","Exclude") -> Exclude | S75: 45599 | T75: =IF(ISBLANK(Order_Date),"Missing Date",Order_Date) -> 45599 | U75: =IF(ISBLANK(Order_Date),"No","Yes") -> Yes | V75: Online | W75: Hyderabad | X75: =PROPER(Region) -> Hyderabad | Y75: 443.86 | Z75: =IF(PC_NikeSales[[#This Row],[Profit]]<0,"Loss Making Sales",IF(PC_NikeSales[[#This Row],[Profit]]=0,"No Recorded Profit",IF($Y73>$P73,"Invalid Profit", "Valid Profit"))) -> Valid Profit | AA75: =IF(PC_NikeSales[[#This Row],[Profit_Status]]="Valid Profit","Include","Exclude") -> Include
A76: 2074 | B76: Men | C76: Training | D76: Flex Trainer | E76: L | F76: =_xlfn.IFS(ISBLANK(Size),"Missing",ISNUMBER(Size),"Number",ISTEXT(Size),"Alphabet") -> Alphabet | G76: =IF(Size_Type ="Missing","Unknown",TRIM(Size)) -> L | H76: =IF(Size_Verification="Unknown","No","Yes") -> Yes | I76: -1 | J76: =_xlfn.IFS(Units_Sold<0,"Check Return/Refund",Units_Sold=" ",Invalid,Units_Sold=0,"Available",Units_Sold>0,"Sold") -> Check Return/Refund | L76: 0.57 | M76: =IF(OR(Discount_Applied="",Discount_Applied>1,Discount_Applied<0),"Invalid","Valid") -> Valid | N76: =IF(PC_NikeSales[[#This Row],[Discount_Verification]]="Valid","Include","Exclude") -> Include | O76: 0 | P76: =IF(AND(Units_Sold<>"",MRP<>"",Discount_Applied<1),Units_Sold*MRP*(1-Discount_Applied),"Insufficient Data") -> Insufficient Data | Q76: =_xlfn.IFS(Rev_Recalc="Insufficient Data","Missing Information",Rev_Recalc<0,"Negative Revenue",Rev_Recalc=0,"No Recorded Revenue",Rev_Recalc>0,"Valid Revenue") -> Missing Information | R76: =IF(PC_NikeSales[[#This Row],[Rev_Verify]]="Valid Revenue","Include","Exclude") -> Exclude | T76: =IF(ISBLANK(Order_Date),"Missing Date",Order_Date) -> Missing Date | U76: =IF(ISBLANK(Order_Date),"No","Yes") -> No | V76: Online | W76: Kolkata | X76: =PROPER(Region) -> Kolkata | Y76: 1958.47 | Z76: =IF(PC_NikeSales[[#This Row],[Profit]]<0,"Loss Making Sales",IF(PC_NikeSales[[#This Row],[Profit]]=0,"No Recorded Profit",IF($Y74>$P74,"Invalid Profit", "Valid Profit"))) -> Valid Profit | AA76: =IF(PC_NikeSales[[#This Row],[Profit_Status]]="Valid Profit","Include","Exclude") -> Include
A77: 2075 | B77: Kids | C77: Basketball | D77: Air Jordan | E77: L | F77: =_xlfn.IFS(ISBLANK(Size),"Missing",ISNUMBER(Size),"Number",ISTEXT(Size),"Alphabet") -> Alphabet | G77: =IF(Size_Type ="Missing","Unknown",TRIM(Size)) -> L | H77: =IF(Size_Verification="Unknown","No","Yes") -> Yes | I77: 4 | J77: =_xlfn.IFS(Units_Sold<0,"Check Return/Refund",Units_Sold=" ",Invalid,Units_Sold=0,"Available",Units_Sold>0,"Sold") -> Sold | K77: 4251.74 | M77: =IF(OR(Discount_Applied="",Discount_Applied>1,Discount_Applied<0),"Invalid","Valid") -> Invalid | N77: =IF(PC_NikeSales[[#This Row],[Discount_Verification]]="Valid","Include","Exclude") -> Exclude | O77: 0 | P77: =IF(AND(Units_Sold<>"",MRP<>"",Discount_Applied<1),Units_Sold*MRP*(1-Discount_Applied),"Insufficient Data") -> 17006.96 | Q77: =_xlfn.IFS(Rev_Recalc="Insufficient Data","Missing Information",Rev_Recalc<0,"Negative Revenue",Rev_Recalc=0,"No Recorded Revenue",Rev_Recalc>0,"Valid Revenue") -> Valid Revenue | R77: =IF(PC_NikeSales[[#This Row],[Rev_Verify]]="Valid Revenue","Include","Exclude") -> Include | S77: 45852 | T77: =IF(ISBLANK(Order_Date),"Missing Date",Order_Date) -> 45852 | U77: =IF(ISBLANK(Order_Date),"No","Yes") -> Yes | V77: Online | W77: Pune | X77: =PROPER(Region) -> Pune | Y77: 2345.35 | Z77: =IF(PC_NikeSales[[#This Row],[Profit]]<0,"Loss Making Sales",IF(PC_NikeSales[[#This Row],[Profit]]=0,"No Recorded Profit",IF($Y75>$P75,"Invalid Profit", "Valid Profit"))) -> Valid Profit | AA77: =IF(PC_NikeSales[[#This Row],[Profit_Status]]="Valid Profit","Include","Exclude") -> Include
A78: 2076 | B78: Women | C78: Training | D78: ZoomX Invincible | E78: 11 | F78: =_xlfn.IFS(ISBLANK(Size),"Missing",ISNUMBER(Size),"Number",ISTEXT(Size),"Alphabet") -> Number | G78: =IF(Size_Type ="Missing","Unknown",TRIM(Size)) -> 11 | H78: =IF(Size_Verification="Unknown","No","Yes") -> Yes | J78: =_xlfn.IFS(Units_Sold<0,"Check Return/Refund",Units_Sold=" ",Invalid,Units_Sold=0,"Available",Units_Sold>0,"Sold") -> Available | M78: =IF(OR(Discount_Applied="",Discount_Applied>1,Discount_Applied<0),"Invalid","Valid") -> Invalid | N78: =IF(PC_NikeSales[[#This Row],[Discount_Verification]]="Valid","Include","Exclude") -> Exclude | O78: 0 | P78: =IF(AND(Units_Sold<>"",MRP<>"",Discount_Applied<1),Units_Sold*MRP*(1-Discount_Applied),"Insufficient Data") -> Insufficient Data | Q78: =_xlfn.IFS(Rev_Recalc="Insufficient Data","Missing Information",Rev_Recalc<0,"Negative Revenue",Rev_Recalc=0,"No Recorded Revenue",Rev_Recalc>0,"Valid Revenue") -> Missing Information | R78: =IF(PC_NikeSales[[#This Row],[Rev_Verify]]="Valid Revenue","Include","Exclude") -> Exclude | S78: 45578 | T78: =IF(ISBLANK(Order_Date),"Missing Date",Order_Date) -> 45578 | U78: =IF(ISBLANK(Order_Date),"No","Yes") -> Yes | V78: Retail | W78: bengaluru | X78: =PROPER(Region) -> Bengaluru | Y78: 2011.25 | Z78: =IF(PC_NikeSales[[#This Row],[Profit]]<0,"Loss Making Sales",IF(PC_NikeSales[[#This Row],[Profit]]=0,"No Recorded Profit",IF($Y76>$P76,"Invalid Profit", "Valid Profit"))) -> Valid Profit | AA78: =IF(PC_NikeSales[[#This Row],[Profit_Status]]="Valid Profit","Include","Exclude") -> Include
A79: 2077 | B79: Men | C79: Training | D79: ZoomX Invincible | E79: L | F79: =_xlfn.IFS(ISBLANK(Size),"Missing",ISNUMBER(Size),"Number",ISTEXT(Size),"Alphabet") -> Alphabet | G79: =IF(Size_Type ="Missing","Unknown",TRIM(Size)) -> L | H79: =IF(Size_Verification="Unknown","No","Yes") -> Yes | J79: =_xlfn.IFS(Units_Sold<0,"Check Return/Refund",Units_Sold=" ",Invalid,Units_Sold=0,"Available",Units_Sold>0,"Sold") -> Available | M79: =IF(OR(Discount_Applied="",Discount_Applied>1,Discount_Applied<0),"Invalid","Valid") -> Invalid | N79: =IF(PC_NikeSales[[#This Row],[Discount_Verification]]="Valid","Include","Exclude") -> Exclude | O79: 0 | P79: =IF(AND(Units_Sold<>"",MRP<>"",Discount_Applied<1),Units_Sold*MRP*(1-Discount_Applied),"Insufficient Data") -> Insufficient Data | Q79: =_xlfn.IFS(Rev_Recalc="Insufficient Data","Missing Information",Rev_Recalc<0,"Negative Revenue",Rev_Recalc=0,"No Recorded Revenue",Rev_Recalc>0,"Valid Revenue") -> Missing Information | R79: =IF(PC_NikeSales[[#This Row],[Rev_Verify]]="Valid Revenue","Include","Exclude") -> Exclude | S79: 45251 | T79: =IF(ISBLANK(Order_Date),"Missing Date",Order_Date) -> 45251 | U79: =IF(ISBLANK(Order_Date),"No","Yes") -> Yes | V79: Online | W79: Pune | X79: =PROPER(Region) -> Pune | Y79: 3332.66 | Z79: =IF(PC_NikeSales[[#This Row],[Profit]]<0,"Loss Making Sales",IF(PC_NikeSales[[#This Row],[Profit]]=0,"No Recorded Profit",IF($Y77>$P77,"Invalid Profit", "Valid Profit"))) -> Valid Profit | AA79: =IF(PC_NikeSales[[#This Row],[Profit_Status]]="Valid Profit","Include","Exclude") -> Include
A80: 2078 | B80: Women | C80: Basketball | D80: LeBron 20 | F80: =_xlfn.IFS(ISBLANK(Size),"Missing",ISNUMBER(Size),"Number",ISTEXT(Size),"Alphabet") -> Missing | G80: =IF(Size_Type ="Missing","Unknown",TRIM(Size)) -> Unknown | H80: =IF(Size_Verification="Unknown","No","Yes") -> No | I80: 0 | J80: =_xlfn.IFS(Units_Sold<0,"Check Return/Refund",Units_Sold=" ",Invalid,Units_Sold=0,"Available",Units_Sold>0,"Sold") -> Available | K80: 6970.47 | M80: =IF(OR(Discount_Applied="",Discount_Applied>1,Discount_Applied<0),"Invalid","Valid") -> Invalid | N80: =IF(PC_NikeSales[[#This Row],[Discount_Verification]]="Valid","Include","Exclude") -> Exclude | O80: 0 | P80: =IF(AND(Units_Sold<>"",MRP<>"",Discount_Applied<1),Units_Sold*MRP*(1-Discount_Applied),"Insufficient Data") -> 0 | Q80: =_xlfn.IFS(Rev_Recalc="Insufficient Data","Missing Information",Rev_Recalc<0,"Negative Revenue",Rev_Recalc=0,"No Recorded Revenue",Rev_Recalc>0,"Valid Revenue") -> No Recorded Revenue | R80: =IF(PC_NikeSales[[#This Row],[Rev_Verify]]="Valid Revenue","Include","Exclude") -> Exclude | T80: =IF(ISBLANK(Order_Date),"Missing Date",Order_Date) -> Missing Date | U80: =IF(ISBLANK(Order_Date),"No","Yes") -> No | V80: Online | W80: Mumbai | X80: =PROPER(Region) -> Mumbai | Y80: 262.79 | Z80: =IF(PC_NikeSales[[#This Row],[Profit]]<0,"Loss Making Sales",IF(PC_NikeSales[[#This Row],[Profit]]=0,"No Recorded Profit",IF(PC_NikeSales[[#This Row],[Profit]]>PC_NikeSales[Rev_Recalc],"Invalid Profit", "Valid Profit"))) -> Invalid Profit | AA80: =IF(PC_NikeSales[[#This Row],[Profit_Status]]="Valid Profit","Include","Exclude") -> Exclude
A81: 2079 | B81: Men | C81: Running | D81: Pegasus Turbo | E81: XL | F81: =_xlfn.IFS(ISBLANK(Size),"Missing",ISNUMBER(Size),"Number",ISTEXT(Size),"Alphabet") -> Alphabet | G81: =IF(Size_Type ="Missing","Unknown",TRIM(Size)) -> XL | H81: =IF(Size_Verification="Unknown","No","Yes") -> Yes | I81: -1 | J81: =_xlfn.IFS(Units_Sold<0,"Check Return/Refund",Units_Sold=" ",Invalid,Units_Sold=0,"Available",Units_Sold>0,"Sold") -> Check Return/Refund | K81: 4322.06 | M81: =IF(OR(Discount_Applied="",Discount_Applied>1,Discount_Applied<0),"Invalid","Valid") -> Invalid | N81: =IF(PC_NikeSales[[#This Row],[Discount_Verification]]="Valid","Include","Exclude") -> Exclude | O81: 0 | P81: =IF(AND(Units_Sold<>"",MRP<>"",Discount_Applied<1),Units_Sold*MRP*(1-Discount_Applied),"Insufficient Data") -> -4322.06 | Q81: =_xlfn.IFS(Rev_Recalc="Insufficient Data","Missing Information",Rev_Recalc<0,"Negative Revenue",Rev_Recalc=0,"No Recorded Revenue",Rev_Recalc>0,"Valid Revenue") -> Negative Revenue | R81: =IF(PC_NikeSales[[#This Row],[Rev_Verify]]="Valid Revenue","Include","Exclude") -> Exclude | S81: 45676 | T81: =IF(ISBLANK(Order_Date),"Missing Date",Order_Date) -> 45676 | U81: =IF(ISBLANK(Order_Date),"No","Yes") -> Yes | V81: Online | W81: bengaluru | X81: =PROPER(Region) -> Bengaluru | Y81: 279.78 | Z81: =IF(PC_NikeSales[[#This Row],[Profit]]<0,"Loss Making Sales",IF(PC_NikeSales[[#This Row],[Profit]]=0,"No Recorded Profit",IF(PC_NikeSales[[#This Row],[Profit]]>PC_NikeSales[Rev_Recalc],"Invalid Profit", "Valid Profit"))) -> Invalid Profit | AA81: =IF(PC_NikeSales[[#This Row],[Profit_Status]]="Valid Profit","Include","Exclude") -> Exclude
A82: 2080 | B82: Men | C82: Lifestyle | D82: Blazer Mid | E82: L | F82: =_xlfn.IFS(ISBLANK(Size),"Missing",ISNUMBER(Size),"Number",ISTEXT(Size),"Alphabet") -> Alphabet | G82: =IF(Size_Type ="Missing","Unknown",TRIM(Size)) -> L | H82: =IF(Size_Verification="Unknown","No","Yes") -> Yes | J82: =_xlfn.IFS(Units_Sold<0,"Check Return/Refund",Units_Sold=" ",Invalid,Units_Sold=0,"Available",Units_Sold>0,"Sold") -> Available | M82: =IF(OR(Discount_Applied="",Discount_Applied>1,Discount_Applied<0),"Invalid","Valid") -> Invalid | N82: =IF(PC_NikeSales[[#This Row],[Discount_Verification]]="Valid","Include","Exclude") -> Exclude | O82: 0 | P82: =IF(AND(Units_Sold<>"",MRP<>"",Discount_Applied<1),Units_Sold*MRP*(1-Discount_Applied),"Insufficient Data") -> Insufficient Data | Q82: =_xlfn.IFS(Rev_Recalc="Insufficient Data","Missing Information",Rev_Recalc<0,"Negative Revenue",Rev_Recalc=0,"No Recorded Revenue",Rev_Recalc>0,"Valid Revenue") -> Missing Information | R82: =IF(PC_NikeSales[[#This Row],[Rev_Verify]]="Valid Revenue","Include","Exclude") -> Exclude | S82: 45747 | T82: =IF(ISBLANK(Order_Date),"Missing Date",Order_Date) -> 45747 | U82: =IF(ISBLANK(Order_Date),"No","Yes") -> Yes | V82: Online | W82: Bangalore | X82: =PROPER(Region) -> Bangalore | Y82: -1005.89 | Z82: =IF(PC_NikeSales[[#This Row],[Profit]]<0,"Loss Making Sales",IF(PC_NikeSales[[#This Row],[Profit]]=0,"No Recorded Profit",IF(PC_NikeSales[[#This Row],[Profit]]>PC_NikeSales[Rev_Recalc],"Invalid Profit", "Valid Profit"))) -> Loss Making Sales | AA82: =IF(PC_NikeSales[[#This Row],[Profit_Status]]="Valid Profit","Include","Exclude") -> Exclude
A83: 2081 | B83: Men | C83: Training | D83: ZoomX Invincible | E83: L | F83: =_xlfn.IFS(ISBLANK(Size),"Missing",ISNUMBER(Size),"Number",ISTEXT(Size),"Alphabet") -> Alphabet | G83: =IF(Size_Type ="Missing","Unknown",TRIM(Size)) -> L | H83: =IF(Size_Verification="Unknown","No","Yes") -> Yes | J83: =_xlfn.IFS(Units_Sold<0,"Check Return/Refund",Units_Sold=" ",Invalid,Units_Sold=0,"Available",Units_Sold>0,"Sold") -> Available | M83: =IF(OR(Discount_Applied="",Discount_Applied>1,Discount_Applied<0),"Invalid","Valid") -> Invalid | N83: =IF(PC_NikeSales[[#This Row],[Discount_Verification]]="Valid","Include","Exclude") -> Exclude | O83: 0 | P83: =IF(AND(Units_Sold<>"",MRP<>"",Discount_Applied<1),Units_Sold*MRP*(1-Discount_Applied),"Insufficient Data") -> Insufficient Data | Q83: =_xlfn.IFS(Rev_Recalc="Insufficient Data","Missing Information",Rev_Recalc<0,"Negative Revenue",Rev_Recalc=0,"No Recorded Revenue",Rev_Recalc>0,"Valid Revenue") -> Missing Information | R83: =IF(PC_NikeSales[[#This Row],[Rev_Verify]]="Valid Revenue","Include","Exclude") -> Exclude | T83: =IF(ISBLANK(Order_Date),"Missing Date",Order_Date) -> Missing Date | U83: =IF(ISBLANK(Order_Date),"No","Yes") -> No | V83: Online | W83: Mumbai | X83: =PROPER(Region) -> Mumbai | Y83: 2810.49 | Z83: =IF(PC_NikeSales[[#This Row],[Profit]]<0,"Loss Making Sales",IF(PC_NikeSales[[#This Row],[Profit]]=0,"No Recorded Profit",IF($Y81>$P81,"Invalid Profit", "Valid Profit"))) -> Invalid Profit | AA83: =IF(PC_NikeSales[[#This Row],[Profit_Status]]="Valid Profit","Include","Exclude") -> Exclude
A84: 2028 | B84: Men | C84: Running | D84: Free RN | F84: =_xlfn.IFS(ISBLANK(Size),"Missing",ISNUMBER(Size),"Number",ISTEXT(Size),"Alphabet") -> Missing | G84: =IF(Size_Type ="Missing","Unknown",TRIM(Size)) -> Unknown | H84: =IF(Size_Verification="Unknown","No","Yes") -> No | I84: -1 | J84: =_xlfn.IFS(Units_Sold<0,"Check Return/Refund",Units_Sold=" ",Invalid,Units_Sold=0,"Available",Units_Sold>0,"Sold") -> Check Return/Refund | L84: 0.21 | M84: =IF(OR(Discount_Applied="",Discount_Applied>1,Discount_Applied<0),"Invalid","Valid") -> Valid | N84: =IF(PC_NikeSales[[#This Row],[Discount_Verification]]="Valid","Include","Exclude") -> Include | O84: 0 | P84: =IF(AND(Units_Sold<>"",MRP<>"",Discount_Applied<1),Units_Sold*MRP*(1-Discount_Applied),"Insufficient Data") -> Insufficient Data | Q84: =_xlfn.IFS(Rev_Recalc="Insufficient Data","Missing Information",Rev_Recalc<0,"Negative Revenue",Rev_Recalc=0,"No Recorded Revenue",Rev_Recalc>0,"Valid Revenue") -> Missing Information | R84: =IF(PC_NikeSales[[#This Row],[Rev_Verify]]="Valid Revenue","Include","Exclude") -> Exclude | S84: 45336 | T84: =IF(ISBLANK(Order_Date),"Missing Date",Order_Date) -> 45336 | U84: =IF(ISBLANK(Order_Date),"No","Yes") -> Yes | V84: Online | W84: Hyderabad | X84: =PROPER(Region) -> Hyderabad | Y84: 3303.01 | Z84: =IF(PC_NikeSales[[#This Row],[Profit]]<0,"Loss Making Sales",IF(PC_NikeSales[[#This Row],[Profit]]=0,"No Recorded Profit",IF($Y82>$P82,"Invalid Profit", "Valid Profit"))) -> Valid Profit | AA84: =IF(PC_NikeSales[[#This Row],[Profit_Status]]="Valid Profit","Include","Exclude") -> Include
A85: 2083 | B85: Men | C85: Running | D85: Free RN | F85: =_xlfn.IFS(ISBLANK(Size),"Missing",ISNUMBER(Size),"Number",ISTEXT(Size),"Alphabet") -> Missing | G85: =IF(Size_Type ="Missing","Unknown",TRIM(Size)) -> Unknown | H85: =IF(Size_Verification="Unknown","No","Yes") -> No | J85: =_xlfn.IFS(Units_Sold<0,"Check Return/Refund",Units_Sold=" ",Invalid,Units_Sold=0,"Available",Units_Sold>0,"Sold") -> Available | K85: 9291.74 | M85: =IF(OR(Discount_Applied="",Discount_Applied>1,Discount_Applied<0),"Invalid","Valid") -> Invalid | N85: =IF(PC_NikeSales[[#This Row],[Discount_Verification]]="Valid","Include","Exclude") -> Exclude | O85: 0 | P85: =IF(AND(Units_Sold<>"",MRP<>"",Discount_Applied<1),Units_Sold*MRP*(1-Discount_Applied),"Insufficient Data") -> Insufficient Data | Q85: =_xlfn.IFS(Rev_Recalc="Insufficient Data","Missing Information",Rev_Recalc<0,"Negative Revenue",Rev_Recalc=0,"No Recorded Revenue",Rev_Recalc>0,"Valid Revenue") -> Missing Information | R85: =IF(PC_NikeSales[[#This Row],[Rev_Verify]]="Valid Revenue","Include","Exclude") -> Exclude | S85: 45579 | T85: =IF(ISBLANK(Order_Date),"Missing Date",Order_Date) -> 45579 | U85: =IF(ISBLANK(Order_Date),"No","Yes") -> Yes | V85: Retail | W85: Delhi | X85: =PROPER(Region) -> Delhi | Y85: -981.21 | Z85: =IF(PC_NikeSales[[#This Row],[Profit]]<0,"Loss Making Sales",IF(PC_NikeSales[[#This Row],[Profit]]=0,"No Recorded Profit",IF(PC_NikeSales[[#This Row],[Profit]]>PC_NikeSales[Rev_Recalc],"Invalid Profit", "Valid Profit"))) -> Loss Making Sales | AA85: =IF(PC_NikeSales[[#This Row],[Profit_Status]]="Valid Profit","Include","Exclude") -> Exclude
A86: 2084 | B86: Men | C86: Training | D86: Metcon 7 | E86: M | F86: =_xlfn.IFS(ISBLANK(Size),"Missing",ISNUMBER(Size),"Number",ISTEXT(Size),"Alphabet") -> Alphabet | G86: =IF(Size_Type ="Missing","Unknown",TRIM(Size)) -> M | H86: =IF(Size_Verification="Unknown","No","Yes") -> Yes | I86: 2 | J86: =_xlfn.IFS(Units_Sold<0,"Check Return/Refund",Units_Sold=" ",Invalid,Units_Sold=0,"Available",Units_Sold>0,"Sold") -> Sold | M86: =IF(OR(Discount_Applied="",Discount_Applied>1,Discount_Applied<0),"Invalid","Valid") -> Invalid | N86: =IF(PC_NikeSales[[#This Row],[Discount_Verification]]="Valid","Include","Exclude") -> Exclude | O86: 0 | P86: =IF(AND(Units_Sold<>"",MRP<>"",Discount_Applied<1),Units_Sold*MRP*(1-Discount_Applied),"Insufficient Data") -> Insufficient Data | Q86: =_xlfn.IFS(Rev_Recalc="Insufficient Data","Missing Information",Rev_Recalc<0,"Negative Revenue",Rev_Recalc=0,"No Recorded Revenue",Rev_Recalc>0,"Valid Revenue") -> Missing Information | R86: =IF(PC_NikeSales[[#This Row],[Rev_Verify]]="Valid Revenue","Include","Exclude") -> Exclude | S86: 45284 | T86: =IF(ISBLANK(Order_Date),"Missing Date",Order_Date) -> 45284 | U86: =IF(ISBLANK(Order_Date),"No","Yes") -> Yes | V86: Online | W86: Mumbai | X86: =PROPER(Region) -> Mumbai | Y86: 408.39 | Z86: =IF(PC_NikeSales[[#This Row],[Profit]]<0,"Loss Making Sales",IF(PC_NikeSales[[#This Row],[Profit]]=0,"No Recorded Profit",IF($Y84>$P84,"Invalid Profit", "Valid Profit"))) -> Valid Profit | AA86: =IF(PC_NikeSales[[#This Row],[Profit_Status]]="Valid Profit","Include","Exclude") -> Include
A87: 2085 | B87: Men | C87: Basketball | D87: Kyrie Flytrap | F87: =_xlfn.IFS(ISBLANK(Size),"Missing",ISNUMBER(Size),"Number",ISTEXT(Size),"Alphabet") -> Missing | G87: =IF(Size_Type ="Missing","Unknown",TRIM(Size)) -> Unknown | H87: =IF(Size_Verification="Unknown","No","Yes") -> No | J87: =_xlfn.IFS(Units_Sold<0,"Check Return/Refund",Units_Sold=" ",Invalid,Units_Sold=0,"Available",Units_Sold>0,"Sold") -> Available | K87: 7561.85 | M87: =IF(OR(Discount_Applied="",Discount_Applied>1,Discount_Applied<0),"Invalid","Valid") -> Invalid | N87: =IF(PC_NikeSales[[#This Row],[Discount_Verification]]="Valid","Include","Exclude") -> Exclude | O87: 0 | P87: =IF(AND(Units_Sold<>"",MRP<>"",Discount_Applied<1),Units_Sold*MRP*(1-Discount_Applied),"Insufficient Data") -> Insufficient Data | Q87: =_xlfn.IFS(Rev_Recalc="Insufficient Data","Missing Information",Rev_Recalc<0,"Negative Revenue",Rev_Recalc=0,"No Recorded Revenue",Rev_Recalc>0,"Valid Revenue") -> Missing Information | R87: =IF(PC_NikeSales[[#This Row],[Rev_Verify]]="Valid Revenue","Include","Exclude") -> Exclude | S87: 45643 | T87: =IF(ISBLANK(Order_Date),"Missing Date",Order_Date) -> 45643 | U87: =IF(ISBLANK(Order_Date),"No","Yes") -> Yes | V87: Retail | W87: Kolkata | X87: =PROPER(Region) -> Kolkata | Y87: 98.72 | Z87: =IF(PC_NikeSales[[#This Row],[Profit]]<0,"Loss Making Sales",IF(PC_NikeSales[[#This Row],[Profit]]=0,"No Recorded Profit",IF($Y85>$P85,"Invalid Profit", "Valid Profit"))) -> Valid Profit | AA87: =IF(PC_NikeSales[[#This Row],[Profit_Status]]="Valid Profit","Include","Exclude") -> Include
A88: 2086 | B88: Men | C88: Soccer | D88: Mercurial Superfly | E88: L | F88: =_xlfn.IFS(ISBLANK(Size),"Missing",ISNUMBER(Size),"Number",ISTEXT(Size),"Alphabet") -> Alphabet | G88: =IF(Size_Type ="Missing","Unknown",TRIM(Size)) -> L | H88: =IF(Size_Verification="Unknown","No","Yes") -> Yes | I88: 0 | J88: =_xlfn.IFS(Units_Sold<0,"Check Return/Refund",Units_Sold=" ",Invalid,Units_Sold=0,"Available",Units_Sold>0,"Sold") -> Available | L88: 0.45 | M88: =IF(OR(Discount_Applied="",Discount_Applied>1,Discount_Applied<0),"Invalid","Valid") -> Valid | N88: =IF(PC_NikeSales[[#This Row],[Discount_Verification]]="Valid","Include","Exclude") -> Include | O88: 0 | P88: =IF(AND(Units_Sold<>"",MRP<>"",Discount_Applied<1),Units_Sold*MRP*(1-Discount_Applied),"Insufficient Data") -> Insufficient Data | Q88: =_xlfn.IFS(Rev_Recalc="Insufficient Data","Missing Information",Rev_Recalc<0,"Negative Revenue",Rev_Recalc=0,"No Recorded Revenue",Rev_Recalc>0,"Valid Revenue") -> Missing Information | R88: =IF(PC_NikeSales[[#This Row],[Rev_Verify]]="Valid Revenue","Include","Exclude") -> Exclude | S88: 45576 | T88: =IF(ISBLANK(Order_Date),"Missing Date",Order_Date) -> 45576 | U88: =IF(ISBLANK(Order_Date),"No","Yes") -> Yes | V88: Online | W88: Kolkata | X88: =PROPER(Region) -> Kolkata | Y88: 1742.66 | Z88: =IF(PC_NikeSales[[#This Row],[Profit]]<0,"Loss Making Sales",IF(PC_NikeSales[[#This Row],[Profit]]=0,"No Recorded Profit",IF($Y86>$P86,"Invalid Profit", "Valid Profit"))) -> Valid Profit | AA88: =IF(PC_NikeSales[[#This Row],[Profit_Status]]="Valid Profit","Include","Exclude") -> Include
A89: 2087 | B89: Kids | C89: Basketball | D89: Zoom Freak | F89: =_xlfn.IFS(ISBLANK(Size),"Missing",ISNUMBER(Size),"Number",ISTEXT(Size),"Alphabet") -> Missing | G89: =IF(Size_Type ="Missing","Unknown",TRIM(Size)) -> Unknown | H89: =IF(Size_Verification="Unknown","No","Yes") -> No | J89: =_xlfn.IFS(Units_Sold<0,"Check Return/Refund",Units_Sold=" ",Invalid,Units_Sold=0,"Available",Units_Sold>0,"Sold") -> Available | K89: 4656.28 | M89: =IF(OR(Discount_Applied="",Discount_Applied>1,Discount_Applied<0),"Invalid","Valid") -> Invalid | N89: =IF(PC_NikeSales[[#This Row],[Discount_Verification]]="Valid","Include","Exclude") -> Exclude | O89: 0 | P89: =IF(AND(Units_Sold<>"",MRP<>"",Discount_Applied<1),Units_Sold*MRP*(1-Discount_Applied),"Insufficient Data") -> Insufficient Data | Q89: =_xlfn.IFS(Rev_Recalc="Insufficient Data","Missing Information",Rev_Recalc<0,"Negative Revenue",Rev_Recalc=0,"No Recorded Revenue",Rev_Recalc>0,"Valid Revenue") -> Missing Information | R89: =IF(PC_NikeSales[[#This Row],[Rev_Verify]]="Valid Revenue","Include","Exclude") -> Exclude | S89: 45597 | T89: =IF(ISBLANK(Order_Date),"Missing Date",Order_Date) -> 45597 | U89: =IF(ISBLANK(Order_Date),"No","Yes") -> Yes | V89: Online | W89: Kolkata | X89: =PROPER(Region) -> Kolkata | Y89: 3777.5 | Z89: =IF(PC_NikeSales[[#This Row],[Profit]]<0,"Loss Making Sales",IF(PC_NikeSales[[#This Row],[Profit]]=0,"No Recorded Profit",IF($Y87>$P87,"Invalid Profit", "Valid Profit"))) -> Valid Profit | AA89: =IF(PC_NikeSales[[#This Row],[Profit_Status]]="Valid Profit","Include","Exclude") -> Include
A90: 2088 | B90: Women | C90: Running | D90: Free RN | E90: XL | F90: =_xlfn.IFS(ISBLANK(Size),"Missing",ISNUMBER(Size),"Number",ISTEXT(Size),"Alphabet") -> Alphabet | G90: =IF(Size_Type ="Missing","Unknown",TRIM(Size)) -> XL | H90: =IF(Size_Verification="Unknown","No","Yes") -> Yes | I90: 4 | J90: =_xlfn.IFS(Units_Sold<0,"Check Return/Refund",Units_Sold=" ",Invalid,Units_Sold=0,"Available",Units_Sold>0,"Sold") -> Sold | M90: =IF(OR(Discount_Applied="",Discount_Applied>1,Discount_Applied<0),"Invalid","Valid") -> Invalid | N90: =IF(PC_NikeSales[[#This Row],[Discount_Verification]]="Valid","Include","Exclude") -> Exclude | O90: 0 | P90: =IF(AND(Units_Sold<>"",MRP<>"",Discount_Applied<1),Units_Sold*MRP*(1-Discount_Applied),"Insufficient Data") -> Insufficient Data | Q90: =_xlfn.IFS(Rev_Recalc="Insufficient Data","Missing Information",Rev_Recalc<0,"Negative Revenue",Rev_Recalc=0,"No Recorded Revenue",Rev_Recalc>0,"Valid Revenue") -> Missing Information | R90: =IF(PC_NikeSales[[#This Row],[Rev_Verify]]="Valid Revenue","Include","Exclude") -> Exclude | S90: 45773 | T90: =IF(ISBLANK(Order_Date),"Missing Date",Order_Date) -> 45773 | U90: =IF(ISBLANK(Order_Date),"No","Yes") -> Yes | V90: Online | W90: Bangalore | X90: =PROPER(Region) -> Bangalore | Y90: 2702.93 | Z90: =IF(PC_NikeSales[[#This Row],[Profit]]<0,"Loss Making Sales",IF(PC_NikeSales[[#This Row],[Profit]]=0,"No Recorded Profit",IF($Y88>$P88,"Invalid Profit", "Valid Profit"))) -> Valid Profit | AA90: =IF(PC_NikeSales[[#This Row],[Profit_Status]]="Valid Profit","Include","Exclude") -> Include
A91: 2089 | B91: Women | C91: Training | D91: Flex Trainer | E91: L | F91: =_xlfn.IFS(ISBLANK(Size),"Missing",ISNUMBER(Size),"Number",ISTEXT(Size),"Alphabet") -> Alphabet | G91: =IF(Size_Type ="Missing","Unknown",TRIM(Size)) -> L | H91: =IF(Size_Verification="Unknown","No","Yes") -> Yes | I91: 2 | J91: =_xlfn.IFS(Units_Sold<0,"Check Return/Refund",Units_Sold=" ",Invalid,Units_Sold=0,"Available",Units_Sold>0,"Sold") -> Sold | K91: 6874.77 | L91: 0.6 | M91: =IF(OR(Discount_Applied="",Discount_Applied>1,Discount_Applied<0),"Invalid","Valid") -> Valid | N91: =IF(PC_NikeSales[[#This Row],[Discount_Verification]]="Valid","Include","Exclude") -> Include | O91: 5499.82 | P91: =IF(AND(Units_Sold<>"",MRP<>"",Discount_Applied<1),Units_Sold*MRP*(1-Discount_Applied),"Insufficient Data") -> 5499.816 | Q91: =_xlfn.IFS(Rev_Recalc="Insufficient Data","Missing Information",Rev_Recalc<0,"Negative Revenue",Rev_Recalc=0,"No Recorded Revenue",Rev_Recalc>0,"Valid Revenue") -> Valid Revenue | R91: =IF(PC_NikeSales[[#This Row],[Rev_Verify]]="Valid Revenue","Include","Exclude") -> Include | S91: 45628 | T91: =IF(ISBLANK(Order_Date),"Missing Date",Order_Date) -> 45628 | U91: =IF(ISBLANK(Order_Date),"No","Yes") -> Yes | V91: Online | W91: Mumbai | X91: =PROPER(Region) -> Mumbai | Y91: -1076.66 | Z91: =IF(PC_NikeSales[[#This Row],[Profit]]<0,"Loss Making Sales",IF(PC_NikeSales[[#This Row],[Profit]]=0,"No Recorded Profit",IF(PC_NikeSales[[#This Row],[Profit]]>PC_NikeSales[Rev_Recalc],"Invalid Profit", "Valid Profit"))) -> Loss Making Sales | AA91: =IF(PC_NikeSales[[#This Row],[Profit_Status]]="Valid Profit","Include","Exclude") -> Exclude
A92: 2090 | B92: Kids | C92: Lifestyle | D92: Dunk Low | E92: 8 | F92: =_xlfn.IFS(ISBLANK(Size),"Missing",ISNUMBER(Size),"Number",ISTEXT(Size),"Alphabet") -> Number | G92: =IF(Size_Type ="Missing","Unknown",TRIM(Size)) -> 8 | H92: =IF(Size_Verification="Unknown","No","Yes") -> Yes | J92: =_xlfn.IFS(Units_Sold<0,"Check Return/Refund",Units_Sold=" ",Invalid,Units_Sold=0,"Available",Units_Sold>0,"Sold") -> Available | M92: =IF(OR(Discount_Applied="",Discount_Applied>1,Discount_Applied<0),"Invalid","Valid") -> Invalid | N92: =IF(PC_NikeSales[[#This Row],[Discount_Verification]]="Valid","Include","Exclude") -> Exclude | O92: 0 | P92: =IF(AND(Units_Sold<>"",MRP<>"",Discount_Applied<1),Units_Sold*MRP*(1-Discount_Applied),"Insufficient Data") -> Insufficient Data | Q92: =_xlfn.IFS(Rev_Recalc="Insufficient Data","Missing Information",Rev_Recalc<0,"Negative Revenue",Rev_Recalc=0,"No Recorded Revenue",Rev_Recalc>0,"Valid Revenue") -> Missing Information | R92: =IF(PC_NikeSales[[#This Row],[Rev_Verify]]="Valid Revenue","Include","Exclude") -> Exclude | T92: =IF(ISBLANK(Order_Date),"Missing Date",Order_Date) -> Missing Date | U92: =IF(ISBLANK(Order_Date),"No","Yes") -> No | V92: Retail | W92: Bangalore | X92: =PROPER(Region) -> Bangalore | Y92: 163.15 | Z92: =IF(PC_NikeSales[[#This Row],[Profit]]<0,"Loss Making Sales",IF(PC_NikeSales[[#This Row],[Profit]]=0,"No Recorded Profit",IF($Y90>$P90,"Invalid Profit", "Valid Profit"))) -> Valid Profit | AA92: =IF(PC_NikeSales[[#This Row],[Profit_Status]]="Valid Profit","Include","Exclude") -> Include
A93: 2091 | B93: Kids | C93: Running | D93: Air Zoom | E93: 11 | F93: =_xlfn.IFS(ISBLANK(Size),"Missing",ISNUMBER(Size),"Number",ISTEXT(Size),"Alphabet") -> Number | G93: =IF(Size_Type ="Missing","Unknown",TRIM(Size)) -> 11 | H93: =IF(Size_Verification="Unknown","No","Yes") -> Yes | J93: =_xlfn.IFS(Units_Sold<0,"Check Return/Refund",Units_Sold=" ",Invalid,Units_Sold=0,"Available",Units_Sold>0,"Sold") -> Available | K93: 9246.88 | M93: =IF(OR(Discount_Applied="",Discount_Applied>1,Discount_Applied<0),"Invalid","Valid") -> Invalid | N93: =IF(PC_NikeSales[[#This Row],[Discount_Verification]]="Valid","Include","Exclude") -> Exclude | O93: 0 | P93: =IF(AND(Units_Sold<>"",MRP<>"",Discount_Applied<1),Units_Sold*MRP*(1-Discount_Applied),"Insufficient Data") -> Insufficient Data | Q93: =_xlfn.IFS(Rev_Recalc="Insufficient Data","Missing Information",Rev_Recalc<0,"Negative Revenue",Rev_Recalc=0,"No Recorded Revenue",Rev_Recalc>0,"Valid Revenue") -> Missing Information | R93: =IF(PC_NikeSales[[#This Row],[Rev_Verify]]="Valid Revenue","Include","Exclude") -> Exclude | T93: =IF(ISBLANK(Order_Date),"Missing Date",Order_Date) -> Missing Date | U93: =IF(ISBLANK(Order_Date),"No","Yes") -> No | V93: Retail | W93: Mumbai | X93: =PROPER(Region) -> Mumbai | Y93: 1917.55 | Z93: =IF(PC_NikeSales[[#This Row],[Profit]]<0,"Loss Making Sales",IF(PC_NikeSales[[#This Row],[Profit]]=0,"No Recorded Profit",IF($Y91>$P91,"Invalid Profit", "Valid Profit"))) -> Valid Profit | AA93: =IF(PC_NikeSales[[#This Row],[Profit_Status]]="Valid Profit","Include","Exclude") -> Include
A94: 2092 | B94: Kids | C94: Basketball | D94: Zoom Freak | E94: XL | F94: =_xlfn.IFS(ISBLANK(Size),"Missing",ISNUMBER(Size),"Number",ISTEXT(Size),"Alphabet") -> Alphabet | G94: =IF(Size_Type ="Missing","Unknown",TRIM(Size)) -> XL | H94: =IF(Size_Verification="Unknown","No","Yes") -> Yes | I94: 2 | J94: =_xlfn.IFS(Units_Sold<0,"Check Return/Refund",Units_Sold=" ",Invalid,Units_Sold=0,"Available",Units_Sold>0,"Sold") -> Sold | L94: 1.13 | M94: =IF(OR(Discount_Applied="",Discount_Applied>1,Discount_Applied<0),"Invalid","Valid") -> Invalid | N94: =IF(PC_NikeSales[[#This Row],[Discount_Verification]]="Valid","Include","Exclude") -> Exclude | O94: 0 | P94: =IF(AND(Units_Sold<>"",MRP<>"",Discount_Applied<1),Units_Sold*MRP*(1-Discount_Applied),"Insufficient Data") -> Insufficient Data | Q94: =_xlfn.IFS(Rev_Recalc="Insufficient Data","Missing Information",Rev_Recalc<0,"Negative Revenue",Rev_Recalc=0,"No Recorded Revenue",Rev_Recalc>0,"Valid Revenue") -> Missing Information | R94: =IF(PC_NikeSales[[#This Row],[Rev_Verify]]="Valid Revenue","Include","Exclude") -> Exclude | T94: =IF(ISBLANK(Order_Date),"Missing Date",Order_Date) -> Missing Date | U94: =IF(ISBLANK(Order_Date),"No","Yes") -> No | V94: Online | W94: Delhi | X94: =PROPER(Region) -> Delhi | Y94: 207.2 | Z94: =IF(PC_NikeSales[[#This Row],[Profit]]<0,"Loss Making Sales",IF(PC_NikeSales[[#This Row],[Profit]]=0,"No Recorded Profit",IF($Y92>$P92,"Invalid Profit", "Valid Profit"))) -> Valid Profit | AA94: =IF(PC_NikeSales[[#This Row],[Profit_Status]]="Valid Profit","Include","Exclude") -> Include
A95: 2093 | B95: Men | C95: Running | D95: Free RN | E95: XL | F95: =_xlfn.IFS(ISBLANK(Size),"Missing",ISNUMBER(Size),"Number",ISTEXT(Size),"Alphabet") -> Alphabet | G95: =IF(Size_Type ="Missing","Unknown",TRIM(Size)) -> XL | H95: =IF(Size_Verification="Unknown","No","Yes") -> Yes | I95: 0 | J95: =_xlfn.IFS(Units_Sold<0,"Check Return/Refund",Units_Sold=" ",Invalid,Units_Sold=0,"Available",Units_Sold>0,"Sold") -> Available | L95: 0.29 | M95: =IF(OR(Discount_Applied="",Discount_Applied>1,Discount_Applied<0),"Invalid","Valid") -> Valid | N95: =IF(PC_NikeSales[[#This Row],[Discount_Verification]]="Valid","Include","Exclude") -> Include | O95: 0 | P95: =IF(AND(Units_Sold<>"",MRP<>"",Discount_Applied<1),Units_Sold*MRP*(1-Discount_Applied),"Insufficient Data") -> Insufficient Data | Q95: =_xlfn.IFS(Rev_Recalc="Insufficient Data","Missing Information",Rev_Recalc<0,"Negative Revenue",Rev_Recalc=0,"No Recorded Revenue",Rev_Recalc>0,"Valid Revenue") -> Missing Information | R95: =IF(PC_NikeSales[[#This Row],[Rev_Verify]]="Valid Revenue","Include","Exclude") -> Exclude | T95: =IF(ISBLANK(Order_Date),"Missing Date",Order_Date) -> Missing Date | U95: =IF(ISBLANK(Order_Date),"No","Yes") -> No | V95: Online | W95: Kolkata | X95: =PROPER(Region) -> Kolkata | Y95: -146.73 | Z95: =IF(PC_NikeSales[[#This Row],[Profit]]<0,"Loss Making Sales",IF(PC_NikeSales[[#This Row],[Profit]]=0,"No Recorded Profit",IF(PC_NikeSales[[#This Row],[Profit]]>PC_NikeSales[Rev_Recalc],"Invalid Profit", "Valid Profit"))) -> Loss Making Sales | AA95: =IF(PC_NikeSales[[#This Row],[Profit_Status]]="Valid Profit","Include","Exclude") -> Exclude
A96: 2094 | B96: Kids | C96: Training | D96: Flex Trainer | E96: 10 | F96: =_xlfn.IFS(ISBLANK(Size),"Missing",ISNUMBER(Size),"Number",ISTEXT(Size),"Alphabet") -> Number | G96: =IF(Size_Type ="Missing","Unknown",TRIM(Size)) -> 10 | H96: =IF(Size_Verification="Unknown","No","Yes") -> Yes | I96: 1 | J96: =_xlfn.IFS(Units_Sold<0,"Check Return/Refund",Units_Sold=" ",Invalid,Units_Sold=0,"Available",Units_Sold>0,"Sold") -> Sold | K96: 4276.36 | M96: =IF(OR(Discount_Applied="",Discount_Applied>1,Discount_Applied<0),"Invalid","Valid") -> Invalid | N96: =IF(PC_NikeSales[[#This Row],[Discount_Verification]]="Valid","Include","Exclude") -> Exclude | O96: 0 | P96: =IF(AND(Units_Sold<>"",MRP<>"",Discount_Applied<1),Units_Sold*MRP*(1-Discount_Applied),"Insufficient Data") -> 4276.36 | Q96: =_xlfn.IFS(Rev_Recalc="Insufficient Data","Missing Information",Rev_Recalc<0,"Negative Revenue",Rev_Recalc=0,"No Recorded Revenue",Rev_Recalc>0,"Valid Revenue") -> Valid Revenue | R96: =IF(PC_NikeSales[[#This Row],[Rev_Verify]]="Valid Revenue","Include","Exclude") -> Include | S96: 45606 | T96: =IF(ISBLANK(Order_Date),"Missing Date",Order_Date) -> 45606 | U96: =IF(ISBLANK(Order_Date),"No","Yes") -> Yes | V96: Retail | W96: Delhi | X96: =PROPER(Region) -> Delhi | Y96: 2974.58 | Z96: =IF(PC_NikeSales[[#This Row],[Profit]]<0,"Loss Making Sales",IF(PC_NikeSales[[#This Row],[Profit]]=0,"No Recorded Profit",IF($Y94>$P94,"Invalid Profit", "Valid Profit"))) -> Valid Profit | AA96: =IF(PC_NikeSales[[#This Row],[Profit_Status]]="Valid Profit","Include","Exclude") -> Include
A97: 2095 | B97: Men | C97: Lifestyle | D97: Waffle One | E97: M | F97: =_xlfn.IFS(ISBLANK(Size),"Missing",ISNUMBER(Size),"Number",ISTEXT(Size),"Alphabet") -> Alphabet | G97: =IF(Size_Type ="Missing","Unknown",TRIM(Size)) -> M | H97: =IF(Size_Verification="Unknown","No","Yes") -> Yes | J97: =_xlfn.IFS(Units_Sold<0,"Check Return/Refund",Units_Sold=" ",Invalid,Units_Sold=0,"Available",Units_Sold>0,"Sold") -> Available | M97: =IF(OR(Discount_Applied="",Discount_Applied>1,Discount_Applied<0),"Invalid","Valid") -> Invalid | N97: =IF(PC_NikeSales[[#This Row],[Discount_Verification]]="Valid","Include","Exclude") -> Exclude | O97: 0 | P97: =IF(AND(Units_Sold<>"",MRP<>"",Discount_Applied<1),Units_Sold*MRP*(1-Discount_Applied),"Insufficient Data") -> Insufficient Data | Q97: =_xlfn.IFS(Rev_Recalc="Insufficient Data","Missing Information",Rev_Recalc<0,"Negative Revenue",Rev_Recalc=0,"No Recorded Revenue",Rev_Recalc>0,"Valid Revenue") -> Missing Information | R97: =IF(PC_NikeSales[[#This Row],[Rev_Verify]]="Valid Revenue","Include","Exclude") -> Exclude | S97: 45581 | T97: =IF(ISBLANK(Order_Date),"Missing Date",Order_Date) -> 45581 | U97: =IF(ISBLANK(Order_Date),"No","Yes") -> Yes | V97: Online | W97: Delhi | X97: =PROPER(Region) -> Delhi | Y97: 880.57 | Z97: =IF(PC_NikeSales[[#This Row],[Profit]]<0,"Loss Making Sales",IF(PC_NikeSales[[#This Row],[Profit]]=0,"No Recorded Profit",IF($Y95>$P95,"Invalid Profit", "Valid Profit"))) -> Valid Profit | AA97: =IF(PC_NikeSales[[#This Row],[Profit_Status]]="Valid Profit","Include","Exclude") -> Include
A98: 2096 | B98: Men | C98: Running | D98: Pegasus Turbo | E98: XL | F98: =_xlfn.IFS(ISBLANK(Size),"Missing",ISNUMBER(Size),"Number",ISTEXT(Size),"Alphabet") -> Alphabet | G98: =IF(Size_Type ="Missing","Unknown",TRIM(Size)) -> XL | H98: =IF(Size_Verification="Unknown","No","Yes") -> Yes | I98: 2 | J98: =_xlfn.IFS(Units_Sold<0,"Check Return/Refund",Units_Sold=" ",Invalid,Units_Sold=0,"Available",Units_Sold>0,"Sold") -> Sold | M98: =IF(OR(Discount_Applied="",Discount_Applied>1,Discount_Applied<0),"Invalid","Valid") -> Invalid | N98: =IF(PC_NikeSales[[#This Row],[Discount_Verification]]="Valid","Include","Exclude") -> Exclude | O98: 0 | P98: =IF(AND(Units_Sold<>"",MRP<>"",Discount_Applied<1),Units_Sold*MRP*(1-Discount_Applied),"Insufficient Data") -> Insufficient Data | Q98: =_xlfn.IFS(Rev_Recalc="Insufficient Data","Missing Information",Rev_Recalc<0,"Negative Revenue",Rev_Recalc=0,"No Recorded Revenue",Rev_Recalc>0,"Valid Revenue") -> Missing Information | R98: =IF(PC_NikeSales[[#This Row],[Rev_Verify]]="Valid Revenue","Include","Exclude") -> Exclude | S98: 45650 | T98: =IF(ISBLANK(Order_Date),"Missing Date",Order_Date) -> 45650 | U98: =IF(ISBLANK(Order_Date),"No","Yes") -> Yes | V98: Online | W98: Kolkata | X98: =PROPER(Region) -> Kolkata | Y98: 288.66 | Z98: =IF(PC_NikeSales[[#This Row],[Profit]]<0,"Loss Making Sales",IF(PC_NikeSales[[#This Row],[Profit]]=0,"No Recorded Profit",IF($Y96>$P96,"Invalid Profit", "Valid Profit"))) -> Valid Profit | AA98: =IF(PC_NikeSales[[#This Row],[Profit_Status]]="Valid Profit","Include","Exclude") -> Include
A99: 2097 | B99: Women | C99: Training | D99: ZoomX Invincible | E99: XL | F99: =_xlfn.IFS(ISBLANK(Size),"Missing",ISNUMBER(Size),"Number",ISTEXT(Size),"Alphabet") -> Alphabet | G99: =IF(Size_Type ="Missing","Unknown",TRIM(Size)) -> XL | H99: =IF(Size_Verification="Unknown","No","Yes") -> Yes | J99: =_xlfn.IFS(Units_Sold<0,"Check Return/Refund",Units_Sold=" ",Invalid,Units_Sold=0,"Available",Units_Sold>0,"Sold") -> Available | K99: 7978.89 | M99: =IF(OR(Discount_Applied="",Discount_Applied>1,Discount_Applied<0),"Invalid","Valid") -> Invalid | N99: =IF(PC_NikeSales[[#This Row],[Discount_Verification]]="Valid","Include","Exclude") -> Exclude | O99: 0 | P99: =IF(AND(Units_Sold<>"",MRP<>"",Discount_Applied<1),Units_Sold*MRP*(1-Discount_Applied),"Insufficient Data") -> Insufficient Data | Q99: =_xlfn.IFS(Rev_Recalc="Insufficient Data","Missing Information",Rev_Recalc<0,"Negative Revenue",Rev_Recalc=0,"No Recorded Revenue",Rev_Recalc>0,"Valid Revenue") -> Missing Information | R99: =IF(PC_NikeSales[[#This Row],[Rev_Verify]]="Valid Revenue","Include","Exclude") -> Exclude | T99: =IF(ISBLANK(Order_Date),"Missing Date",Order_Date) -> Missing Date | U99: =IF(ISBLANK(Order_Date),"No","Yes") -> No | V99: Online | W99: Bangalore | X99: =PROPER(Region) -> Bangalore | Y99: 769.05 | Z99: =IF(PC_NikeSales[[#This Row],[Profit]]<0,"Loss Making Sales",IF(PC_NikeSales[[#This Row],[Profit]]=0,"No Recorded Profit",IF($Y97>$P97,"Invalid Profit", "Valid Profit"))) -> Valid Profit | AA99: =IF(PC_NikeSales[[#This Row],[Profit_Status]]="Valid Profit","Include","Exclude") -> Include
A100: 2098 | B100: Men | C100: Training | D100: ZoomX Invincible | E100: L | F100: =_xlfn.IFS(ISBLANK(Size),"Missing",ISNUMBER(Size),"Number",ISTEXT(Size),"Alphabet") -> Alphabet | G100: =IF(Size_Type ="Missing","Unknown",TRIM(Size)) -> L | H100: =IF(Size_Verification="Unknown","No","Yes") -> Yes | J100: =_xlfn.IFS(Units_Sold<0,"Check Return/Refund",Units_Sold=" ",Invalid,Units_Sold=0,"Available",Units_Sold>0,"Sold") -> Available | K100: 5690.69 | L100: 0.69 | M100: =IF(OR(Discount_Applied="",Discount_Applied>1,Discount_Applied<0),"Invalid","Valid") -> Valid | N100: =IF(PC_NikeSales[[#This Row],[Discount_Verification]]="Valid","Include","Exclude") -> Include | O100: 0 | P100: =IF(AND(Units_Sold<>"",MRP<>"",Discount_Applied<1),Units_Sold*MRP*(1-Discount_Applied),"Insufficient Data") -> Insufficient Data | Q100: =_xlfn.IFS(Rev_Recalc="Insufficient Data","Missing Information",Rev_Recalc<0,"Negative Revenue",Rev_Recalc=0,"No Recorded Revenue",Rev_Recalc>0,"Valid Revenue") -> Missing Information | R100: =IF(PC_NikeSales[[#This Row],[Rev_Verify]]="Valid Revenue","Include","Exclude") -> Exclude | S100: 45315 | T100: =IF(ISBLANK(Order_Date),"Missing Date",Order_Date) -> 45315 | U100: =IF(ISBLANK(Order_Date),"No","Yes") -> Yes | V100: Online | W100: Hyderabad | X100: =PROPER(Region) -> Hyderabad | Y100: 98.3 | Z100: =IF(PC_NikeSales[[#This Row],[Profit]]<0,"Loss Making Sales",IF(PC_NikeSales[[#This Row],[Profit]]=0,"No Recorded Profit",IF($Y98>$P98,"Invalid Profit", "Valid Profit"))) -> Valid Profit | AA100: =IF(PC_NikeSales[[#This Row],[Profit_Status]]="Valid Profit","Include","Exclude") -> Include
...

Sheet Change & Assumptions Log
A1: Area | B1: Issue Identified | C1: Action Taken | D1: Rationale | E1: Impact on Analysis | G1: Assumptions Made
A2: Table Structure | B2: No consistent reference for formulas | C2: Converted dataset into a named table using “Create from Selection” | D2: Improves formula readability, reduces hard-coded cell references | E2: Ensures scalability and reduces formula errors | G2: Discounts assumed between 0–1
A3: Revenue Accuracy | B3: Revenue values missing or inconsistent with Units Sold, MRP, and Discount | C3: Created Rev_Recalc using validated Units Sold, MRP, and Discount | D3: Raw revenue cannot be trusted without validation | E3: Enables accurate revenue comparison and verification | G3: Revenue recalculated only if validated
A4: Revenue Validation | B4: Zero, missing, and negative revenues mixed together | C4: Created Rev_Verify classification column | D4: Separates missing data from true zero or invalid values | E4: Prevents misleading revenue analysis | G4: Loss-making sales excluded from profit analysis
A5: Revenue Inclusion | B5: Invalid revenue rows included in analysis | C5: Created Revenue_Analysis Include/Exclude flag | D5: Analysts should not delete data, only control inclusion | E5: Ensures only valid revenue is used in reporting | G5: Cleaned_Nike_Sales Inclusion Criteria: Revenue_Analysis = "Include" → Revenue is valid, non-zero, and successfully recalculated using verified inputs. Valid_OD_Analysis = "Yes" → Order Date is present and suitable for time-based analysis. Valid_Size_Analysis = "Yes" → Product size information is available and verified for categorical analysis. Profit_Analysis = "Include" → Transaction reflects a valid (non-zero, non-negative) profit outcome suitable for profit analysis. Records failing any of the above criteria were retained in the raw dataset but excluded from analysis to prevent distortion of financial and operational insights.
A6: Discount Validity | B6: Discount values outside logical range (0–1) | C6: Created Discount_Verification and Discount_Analysis | D6: Prevents over/under-discount distortions | E6: Avoids incorrect revenue recalculation
A7: Size Consistency | B7: Size values inconsistent or missing | C7: Created Size_Verification and Valid_Size_Analysis | D7: Size inconsistencies affect product analysis | E7: Improves categorical accuracy
A8: Units Sold Integrity | B8: Negative, zero, or blank sales values present | C8: Created Product_Status classification | D8: Distinguishes sales vs availability vs returns | E8: Prevents misinterpretation of sales volume
A9: Order Date Completeness | B9: Missing order dates mixed with valid dates | C9: Created OD_Status and Valid_OD_Analysis | D9: Time-based analysis requires valid dates | E9: Ensures temporal analysis reliability
A10: Profit Evaluation | B10: Loss-making and zero-profit sales mixed with profitable ones | C10: Created Profit_Status and Profit_Analysis | D10: Losses are valid but unsuitable for profit KPIs | E10: Enables clean profit analysis without deleting data

Sheet Cleaned_Nike_Sales
A1: Order_ID | B1: Gender_Category | C1: Product_Line | D1: Product_Name | E1: Size | F1: Size_Type | G1: Size_Verification | H1: Valid_Size_Analysis | I1: Units_Sold | J1: Product_Status | K1: MRP | L1: Discount_Applied | M1: Discount_Verification | N1: Discount_Analysis | O1: Revenue | P1: DiscountCategory | Q1: Rev_Recalc | R1: Rev_Verify | S1: Revenue_Analysis | T1: Order_Date | U1: OD_Status | V1: Valid_OD_Analysis | W1: Sales_Channel | X1: Region | Y1: Region_Formatted | Z1: Profit | AA1: Profit Margin | AB1: Profit_Status | AC1: Profit_Analysis | AE1: Complete Entries Per Region | AF1: Number of Entries | AG1: Pre-Cleaned Entries | AH1: % of Entry Efficiency
A2: 2063 | B2: Women | C2: Basketball | D2: Air Jordan | E2: M | F2: Alphabet | G2: M | H2: Yes | I2: 1 | J2: Sold | K2: 9751 | L2: 0.16 | M2: Valid | N2: Include | O2: 8190.84 | P2: =_xlfn.IFS($L2<=0.2,"0-20%",$L2<=0.4,"20-40%",$L2<=0.6,"40-60%",$L2<=0.8,"60-80%",$L2<=1,"80-100%") -> 0-20% | Q2: 8190.84 | R2: Valid Revenue | S2: Include | T2: 45541 | U2: 45541 | V2: Yes | W2: Retail | X2: Pune | Y2: Pune | Z2: 1130.31 | AA2: =($Z2/$Q2)*100 -> 13.799684 | AB2: Valid Profit | AC2: Include | AE2: Pune | AF2: =COUNTIF($Y:$Y,"Pune") -> 6 | AG2: =COUNTIF(Nike_Sales_PreCleaned!$X:$X,"Pune") -> 388 | AH2: =($AF2/$AG2)*100 -> 1.5463918
A3: 2135 | B3: Men | C3: Basketball | D3: Zoom Freak | E3: L | F3: Alphabet | G3: L | H3: Yes | I3: 2 | J3: Sold | K3: 9106.61 | L3: 0.74 | M3: Valid | N3: Include | O3: 4735.44 | P3: =_xlfn.IFS($L3<=0.2,"0-20%",$L3<=0.4,"20-40%",$L3<=0.6,"40-60%",$L3<=0.8,"60-80%",$L3<=1,"80-100%") -> 60-80% | Q3: 4735.4372 | R3: Valid Revenue | S3: Include | T3: 45599 | U3: 45599 | V3: Yes | W3: Retail | X3: Hyderabad | Y3: Hyderabad | Z3: 2422.38 | AA3: =($Z3/$Q3)*100 -> 51.154305 | AB3: Valid Profit | AC3: Include | AE3: Hyderabad | AF3: =COUNTIF($Y:$Y,"Hyderabad") -> 7 | AG3: =COUNTIF(Nike_Sales_PreCleaned!$X:$X,"Hyderabad") -> 403 | AH3: =($AF3/$AG3)*100 -> 1.7369727
A4: 2150 | B4: Women | C4: Basketball | D4: LeBron 20 | E4: M | F4: Alphabet | G4: M | H4: Yes | I4: 2 | J4: Sold | K4: 3313.21 | L4: 0.48 | M4: Valid | N4: Include | O4: 3445.74 | P4: =_xlfn.IFS($L4<=0.2,"0-20%",$L4<=0.4,"20-40%",$L4<=0.6,"40-60%",$L4<=0.8,"60-80%",$L4<=1,"80-100%") -> 40-60% | Q4: 3445.7384 | R4: Valid Revenue | S4: Include | T4: 45844 | U4: 45844 | V4: Yes | W4: Online | X4: bengaluru | Y4: Bengaluru | Z4: 3221.62 | AA4: =($Z4/$Q4)*100 -> 93.49578 | AB4: Valid Profit | AC4: Include | AE4: Bengaluru | AF4: =COUNTIF($Y:$Y,"Bengaluru") -> 3 | AG4: =COUNTIF(Nike_Sales_PreCleaned!$X:$X,"Bengaluru") -> 220 | AH4: =($AF4/$AG4)*100 -> 1.3636364
A5: 2222 | B5: Men | C5: Training | D5: ZoomX Invincible | E5: XL | F5: Alphabet | G5: XL | H5: Yes | I5: 2 | J5: Sold | K5: 8897.19 | L5: 0.11 | M5: Valid | N5: Include | O5: 15837 | P5: =_xlfn.IFS($L5<=0.2,"0-20%",$L5<=0.4,"20-40%",$L5<=0.6,"40-60%",$L5<=0.8,"60-80%",$L5<=1,"80-100%") -> 0-20% | Q5: 15836.998 | R5: Valid Revenue | S5: Include | T5: 45647 | U5: 45647 | V5: Yes | W5: Retail | X5: Mumbai | Y5: Mumbai | Z5: 2821.69 | AA5: =($Z5/$Q5)*100 -> 17.817076 | AB5: Valid Profit | AC5: Include | AE5: Mumbai | AF5: =COUNTIF($Y:$Y,"Mumbai") -> 8 | AG5: =COUNTIF(Nike_Sales_PreCleaned!$X:$X,"Mumbai") -> 418 | AH5: =($AF5/$AG5)*100 -> 1.9138756
A6: 2300 | B6: Men | C6: Basketball | D6: Air Jordan | E6: L | F6: Alphabet | G6: L | H6: Yes | I6: 3 | J6: Sold | K6: 6331.64 | L6: 0.78 | M6: Valid | N6: Include | O6: 4178.88 | P6: =_xlfn.IFS($L6<=0.2,"0-20%",$L6<=0.4,"20-40%",$L6<=0.6,"40-60%",$L6<=0.8,"60-80%",$L6<=1,"80-100%") -> 60-80% | Q6: 4178.8824 | R6: Valid Revenue | S6: Include | T6: 45521 | U6: 45521 | V6: Yes | W6: Retail | X6: Delhi | Y6: Delhi | Z6: 3380.28 | AA6: =($Z6/$Q6)*100 -> 80.88957 | AB6: Valid Profit | AC6: Include | AE6: Kolkata | AF6: =COUNTIF($Y:$Y,"Kolkata") -> 7 | AG6: =COUNTIF(Nike_Sales_PreCleaned!$X:$X,"Kolkata") -> 417 | AH6: =($AF6/$AG6)*100 -> 1.6786571
A7: 2328 | B7: Men | C7: Lifestyle | D7: Waffle One | E7: 6 | F7: Number | G7: 6 | H7: Yes | I7: 2 | J7: Sold | K7: 6449.46 | L7: 0.29 | M7: Valid | N7: Include | O7: 9158.23 | P7: =_xlfn.IFS($L7<=0.2,"0-20%",$L7<=0.4,"20-40%",$L7<=0.6,"40-60%",$L7<=0.8,"60-80%",$L7<=1,"80-100%") -> 20-40% | Q7: 9158.2332 | R7: Valid Revenue | S7: Include | T7: 45605 | U7: 45605 | V7: Yes | W7: Online | X7: Mumbai | Y7: Mumbai | Z7: 39.69 | AA7: =($Z7/$Q7)*100 -> 0.43338053 | AB7: Valid Profit | AC7: Include | AE7: Delhi | AF7: =COUNTIF($Y:$Y,"Delhi") -> 6 | AG7: =COUNTIF(Nike_Sales_PreCleaned!$X:$X,"Delhi") -> 438 | AH7: =($AF7/$AG7)*100 -> 1.369863
A8: 2003 | B8: Women | C8: Lifestyle | D8: Waffle One | E8: XL | F8: Alphabet | G8: XL | H8: Yes | I8: 2 | J8: Sold | K8: 8516.45 | L8: 0.22 | M8: Valid | N8: Include | O8: 13285.66 | P8: =_xlfn.IFS($L8<=0.2,"0-20%",$L8<=0.4,"20-40%",$L8<=0.6,"40-60%",$L8<=0.8,"60-80%",$L8<=1,"80-100%") -> 20-40% | Q8: 13285.662 | R8: Valid Revenue | S8: Include | T8: 45199 | U8: 45199 | V8: Yes | W8: Online | X8: Kolkata | Y8: Kolkata | Z8: 1764.52 | AA8: =($Z8/$Q8)*100 -> 13.281386 | AB8: Valid Profit | AC8: Include
A9: 2481 | B9: Women | C9: Soccer | D9: Premier III | E9: 7 | F9: Number | G9: 7 | H9: Yes | I9: 1 | J9: Sold | K9: 9145.37 | L9: 0.07 | M9: Valid | N9: Include | O9: 8505.19 | P9: =_xlfn.IFS($L9<=0.2,"0-20%",$L9<=0.4,"20-40%",$L9<=0.6,"40-60%",$L9<=0.8,"60-80%",$L9<=1,"80-100%") -> 0-20% | Q9: 8505.1941 | R9: Valid Revenue | S9: Include | T9: 45764 | U9: 45764 | V9: Yes | W9: Online | X9: Pune | Y9: Pune | Z9: 1755.19 | AA9: =($Z9/$Q9)*100 -> 20.636684 | AB9: Valid Profit | AC9: Include
A10: 2487 | B10: Men | C10: Running | D10: Air Zoom | E10: L | F10: Alphabet | G10: L | H10: Yes | I10: 3 | J10: Sold | K10: 5881.13 | L10: 0.8 | M10: Valid | N10: Include | O10: 3528.68 | P10: =_xlfn.IFS($L10<=0.2,"0-20%",$L10<=0.4,"20-40%",$L10<=0.6,"40-60%",$L10<=0.8,"60-80%",$L10<=1,"80-100%") -> 60-80% | Q10: 3528.678 | R10: Valid Revenue | S10: Include | T10: 45747 | U10: 45747 | V10: Yes | W10: Online | X10: Hyderabad | Y10: Hyderabad | Z10: 2108.4 | AA10: =($Z10/$Q10)*100 -> 59.750422 | AB10: Valid Profit | AC10: Include
A11: 2496 | B11: Kids | C11: Running | D11: React Infinity | E11: M | F11: Alphabet | G11: M | H11: Yes | I11: 2 | J11: Sold | K11: 4110.72 | L11: 0.32 | M11: Valid | N11: Include | O11: 5590.58 | P11: =_xlfn.IFS($L11<=0.2,"0-20%",$L11<=0.4,"20-40%",$L11<=0.6,"40-60%",$L11<=0.8,"60-80%",$L11<=1,"80-100%") -> 20-40% | Q11: 5590.5792 | R11: Valid Revenue | S11: Include | T11: 45650 | U11: 45650 | V11: Yes | W11: Retail | X11: bengaluru | Y11: Bengaluru | Z11: 3894.95 | AA11: =($Z11/$Q11)*100 -> 69.669883 | AB11: Valid Profit | AC11: Include
A12: 2535 | B12: Men | C12: Soccer | D12: Tiempo Legend | E12: XL | F12: Alphabet | G12: XL | H12: Yes | I12: 2 | J12: Sold | K12: 2786.84 | L12: 0.21 | M12: Valid | N12: Include | O12: 4403.21 | P12: =_xlfn.IFS($L12<=0.2,"0-20%",$L12<=0.4,"20-40%",$L12<=0.6,"40-60%",$L12<=0.8,"60-80%",$L12<=1,"80-100%") -> 20-40% | Q12: 4403.2072 | R12: Valid Revenue | S12: Include | T12: 45682 | U12: 45682 | V12: Yes | W12: Online | X12: Mumbai | Y12: Mumbai | Z12: 3345.36 | AA12: =($Z12/$Q12)*100 -> 75.97553 | AB12: Valid Profit | AC12: Include
A13: 2550 | B13: Men | C13: Soccer | D13: Premier III | E13: XL | F13: Alphabet | G13: XL | H13: Yes | I13: 1 | J13: Sold | K13: 6121.21 | L13: 0.05 | M13: Valid | N13: Include | O13: 5815.15 | P13: =_xlfn.IFS($L13<=0.2,"0-20%",$L13<=0.4,"20-40%",$L13<=0.6,"40-60%",$L13<=0.8,"60-80%",$L13<=1,"80-100%") -> 0-20% | Q13: 5815.1495 | R13: Valid Revenue | S13: Include | T13: 45177 | U13: 45177 | V13: Yes | W13: Online | X13: Kolkata | Y13: Kolkata | Z13: 2470.08 | AA13: =($Z13/$Q13)*100 -> 42.476638 | AB13: Valid Profit | AC13: Include
A14: 2563 | B14: Men | C14: Soccer | D14: Mercurial Superfly | E14: M | F14: Alphabet | G14: M | H14: Yes | I14: 2 | J14: Sold | K14: 9443.35 | L14: 0.54 | M14: Valid | N14: Include | O14: 8687.88 | P14: =_xlfn.IFS($L14<=0.2,"0-20%",$L14<=0.4,"20-40%",$L14<=0.6,"40-60%",$L14<=0.8,"60-80%",$L14<=1,"80-100%") -> 40-60% | Q14: 8687.882 | R14: Valid Revenue | S14: Include | T14: 45760 | U14: 45760 | V14: Yes | W14: Retail | X14: Kolkata | Y14: Kolkata | Z14: 2706.61 | AA14: =($Z14/$Q14)*100 -> 31.153853 | AB14: Valid Profit | AC14: Include
A15: 2569 | B15: Women | C15: Basketball | D15: Air Jordan | E15: L | F15: Alphabet | G15: L | H15: Yes | I15: 2 | J15: Sold | K15: 9605.11 | L15: 0.88 | M15: Valid | N15: Include | O15: 2305.23 | P15: =_xlfn.IFS($L15<=0.2,"0-20%",$L15<=0.4,"20-40%",$L15<=0.6,"40-60%",$L15<=0.8,"60-80%",$L15<=1,"80-100%") -> 80-100% | Q15: 2305.2264 | R15: Valid Revenue | S15: Include | T15: 45528 | U15: 45528 | V15: Yes | W15: Online | X15: Hyderabad | Y15: Hyderabad | Z15: 128.89 | AA15: =($Z15/$Q15)*100 -> 5.5912079 | AB15: Valid Profit | AC15: Include
A16: 2594 | B16: Women | C16: Training | D16: ZoomX Invincible | E16: XL | F16: Alphabet | G16: XL | H16: Yes | I16: 3 | J16: Sold | K16: 7944.34 | L16: 0.67 | M16: Valid | N16: Include | O16: 7864.9 | P16: =_xlfn.IFS($L16<=0.2,"0-20%",$L16<=0.4,"20-40%",$L16<=0.6,"40-60%",$L16<=0.8,"60-80%",$L16<=1,"80-100%") -> 60-80% | Q16: 7864.8966 | R16: Valid Revenue | S16: Include | T16: 45345 | U16: 45345 | V16: Yes | W16: Retail | X16: Hyderabad | Y16: Hyderabad | Z16: 1534.91 | AA16: =($Z16/$Q16)*100 -> 19.515959 | AB16: Valid Profit | AC16: Include
A17: 2615 | B17: Women | C17: Soccer | D17: Phantom GT | E17: XL | F17: Alphabet | G17: XL | H17: Yes | I17: 3 | J17: Sold | K17: 3042.37 | L17: 0.12 | M17: Valid | N17: Include | O17: 8031.86 | P17: =_xlfn.IFS($L17<=0.2,"0-20%",$L17<=0.4,"20-40%",$L17<=0.6,"40-60%",$L17<=0.8,"60-80%",$L17<=1,"80-100%") -> 0-20% | Q17: 8031.8568 | R17: Valid Revenue | S17: Include | T17: 45740 | U17: 45740 | V17: Yes | W17: Online | X17: Pune | Y17: Pune | Z17: 2105.48 | AA17: =($Z17/$Q17)*100 -> 26.214113 | AB17: Valid Profit | AC17: Include
A18: 2709 | B18: Kids | C18: Running | D18: Free RN | E18: 10 | F18: Number | G18: 10 | H18: Yes | I18: 1 | J18: Sold | K18: 6302.98 | L18: 0.48 | M18: Valid | N18: Include | O18: 3277.55 | P18: =_xlfn.IFS($L18<=0.2,"0-20%",$L18<=0.4,"20-40%",$L18<=0.6,"40-60%",$L18<=0.8,"60-80%",$L18<=1,"80-100%") -> 40-60% | Q18: 3277.5496 | R18: Valid Revenue | S18: Include | T18: 45724 | U18: 45724 | V18: Yes | W18: Retail | X18: Delhi | Y18: Delhi | Z18: 2835.93 | AA18: =($Z18/$Q18)*100 -> 86.525922 | AB18: Valid Profit | AC18: Include
A19: 2781 | B19: Men | C19: Training | D19: Metcon 7 | E19: 12 | F19: Number | G19: 12 | H19: Yes | I19: 1 | J19: Sold | K19: 6546.59 | L19: 0.68 | M19: Valid | N19: Include | O19: 2094.91 | P19: =_xlfn.IFS($L19<=0.2,"0-20%",$L19<=0.4,"20-40%",$L19<=0.6,"40-60%",$L19<=0.8,"60-80%",$L19<=1,"80-100%") -> 60-80% | Q19: 2094.9088 | R19: Valid Revenue | S19: Include | T19: 45172 | U19: 45172 | V19: Yes | W19: Retail | X19: Bangalore | Y19: Bangalore | Z19: 1504.31 | AA19: =($Z19/$Q19)*100 -> 71.807899 | AB19: Valid Profit | AC19: Include
A20: 2904 | B20: Women | C20: Soccer | D20: Tiempo Legend | E20: 9 | F20: Number | G20: 9 | H20: Yes | I20: 2 | J20: Sold | K20: 8644.67 | L20: 0.54 | M20: Valid | N20: Include | O20: 7953.1 | P20: =_xlfn.IFS($L20<=0.2,"0-20%",$L20<=0.4,"20-40%",$L20<=0.6,"40-60%",$L20<=0.8,"60-80%",$L20<=1,"80-100%") -> 40-60% | Q20: 7953.0964 | R20: Valid Revenue | S20: Include | T20: 45776 | U20: 45776 | V20: Yes | W20: Online | X20: bengaluru | Y20: Bengaluru | Z20: 2711.75 | AA20: =($Z20/$Q20)*100 -> 34.096783 | AB20: Valid Profit | AC20: Include
A21: 3165 | B21: Women | C21: Soccer | D21: Phantom GT | E21: XL | F21: Alphabet | G21: XL | H21: Yes | I21: 2 | J21: Sold | K21: 2530.29 | L21: 0.29 | M21: Valid | N21: Include | O21: 3593.01 | P21: =_xlfn.IFS($L21<=0.2,"0-20%",$L21<=0.4,"20-40%",$L21<=0.6,"40-60%",$L21<=0.8,"60-80%",$L21<=1,"80-100%") -> 20-40% | Q21: 3593.0118 | R21: Valid Revenue | S21: Include | T21: 45705 | U21: 45705 | V21: Yes | W21: Online | X21: Kolkata | Y21: Kolkata | Z21: 3264.03 | AA21: =($Z21/$Q21)*100 -> 90.843843 | AB21: Valid Profit | AC21: Include
A22: 3274 | B22: Men | C22: Training | D22: SuperRep Go | E22: L | F22: Alphabet | G22: L | H22: Yes | I22: 3 | J22: Sold | K22: 6031.14 | L22: 0.15 | M22: Valid | N22: Include | O22: 15379.41 | P22: =_xlfn.IFS($L22<=0.2,"0-20%",$L22<=0.4,"20-40%",$L22<=0.6,"40-60%",$L22<=0.8,"60-80%",$L22<=1,"80-100%") -> 0-20% | Q22: 15379.407 | R22: Valid Revenue | S22: Include | T22: 45780 | U22: 45780 | V22: Yes | W22: Retail | X22: Hyderabad | Y22: Hyderabad | Z22: 169.05 | AA22: =($Z22/$Q22)*100 -> 1.0991971 | AB22: Valid Profit | AC22: Include
A23: 3279 | B23: Kids | C23: Soccer | D23: Mercurial Superfly | E23: XL | F23: Alphabet | G23: XL | H23: Yes | I23: 4 | J23: Sold | K23: 2572.41 | L23: 0.1 | M23: Valid | N23: Include | O23: 9260.68 | P23: =_xlfn.IFS($L23<=0.2,"0-20%",$L23<=0.4,"20-40%",$L23<=0.6,"40-60%",$L23<=0.8,"60-80%",$L23<=1,"80-100%") -> 0-20% | Q23: 9260.676 | R23: Valid Revenue | S23: Include | T23: 45605 | U23: 45605 | V23: Yes | W23: Retail | X23: Delhi | Y23: Delhi | Z23: 3098.28 | AA23: =($Z23/$Q23)*100 -> 33.456305 | AB23: Valid Profit | AC23: Include
A24: 3357 | B24: Kids | C24: Training | D24: Flex Trainer | E24: M | F24: Alphabet | G24: M | H24: Yes | I24: 4 | J24: Sold | K24: 6206.45 | L24: 0.5 | M24: Valid | N24: Include | O24: 12412.9 | P24: =_xlfn.IFS($L24<=0.2,"0-20%",$L24<=0.4,"20-40%",$L24<=0.6,"40-60%",$L24<=0.8,"60-80%",$L24<=1,"80-100%") -> 40-60% | Q24: 12412.9 | R24: Valid Revenue | S24: Include | T24: 45752 | U24: 45752 | V24: Yes | W24: Online | X24: Delhi | Y24: Delhi | Z24: 678.42 | AA24: =($Z24/$Q24)*100 -> 5.4654432 | AB24: Valid Profit | AC24: Include
A25: 3428 | B25: Women | C25: Basketball | D25: Air Jordan | E25: 6 | F25: Number | G25: 6 | H25: Yes | I25: 1 | J25: Sold | K25: 2825.86 | L25: 0.23 | M25: Valid | N25: Include | O25: 2175.91 | P25: =_xlfn.IFS($L25<=0.2,"0-20%",$L25<=0.4,"20-40%",$L25<=0.6,"40-60%",$L25<=0.8,"60-80%",$L25<=1,"80-100%") -> 20-40% | Q25: 2175.9122 | R25: Valid Revenue | S25: Include | T25: 45629 | U25: 45629 | V25: Yes | W25: Online | X25: Bangalore | Y25: Bangalore | Z25: 625.3 | AA25: =($Z25/$Q25)*100 -> 28.737373 | AB25: Valid Profit | AC25: Include
A26: 3672 | B26: Women | C26: Soccer | D26: Tiempo Legend | E26: 7 | F26: Number | G26: 7 | H26: Yes | I26: 3 | J26: Sold | K26: 7127.18 | L26: 0.32 | M26: Valid | N26: Include | O26: 14539.45 | P26: =_xlfn.IFS($L26<=0.2,"0-20%",$L26<=0.4,"20-40%",$L26<=0.6,"40-60%",$L26<=0.8,"60-80%",$L26<=1,"80-100%") -> 20-40% | Q26: 14539.447 | R26: Valid Revenue | S26: Include | T26: 45520 | U26: 45520 | V26: Yes | W26: Online | X26: Delhi | Y26: Delhi | Z26: 2651.63 | AA26: =($Z26/$Q26)*100 -> 18.237488 | AB26: Valid Profit | AC26: Include
A27: 3722 | B27: Kids | C27: Training | D27: ZoomX Invincible | E27: 7 | F27: Number | G27: 7 | H27: Yes | I27: 1 | J27: Sold | K27: 9335 | L27: 0.22 | M27: Valid | N27: Include | O27: 7281.3 | P27: =_xlfn.IFS($L27<=0.2,"0-20%",$L27<=0.4,"20-40%",$L27<=0.6,"40-60%",$L27<=0.8,"60-80%",$L27<=1,"80-100%") -> 20-40% | Q27: 7281.3 | R27: Valid Revenue | S27: Include | T27: 45251 | U27: 45251 | V27: Yes | W27: Retail | X27: Mumbai | Y27: Mumbai | Z27: 1787.45 | AA27: =($Z27/$Q27)*100 -> 24.548501 | AB27: Valid Profit | AC27: Include
A28: 3755 | B28: Women | C28: Soccer | D28: Phantom GT | E28: 8 | F28: Number | G28: 8 | H28: Yes | I28: 4 | J28: Sold | K28: 2342.16 | L28: 0.25 | M28: Valid | N28: Include | O28: 7026.48 | P28: =_xlfn.IFS($L28<=0.2,"0-20%",$L28<=0.4,"20-40%",$L28<=0.6,"40-60%",$L28<=0.8,"60-80%",$L28<=1,"80-100%") -> 20-40% | Q28: 7026.48 | R28: Valid Revenue | S28: Include | T28: 45767 | U28: 45767 | V28: Yes | W28: Retail | X28: Mumbai | Y28: Mumbai | Z28: 1007 | AA28: =($Z28/$Q28)*100 -> 14.3315 | AB28: Valid Profit | AC28: Include
A29: 3874 | B29: Women | C29: Basketball | D29: LeBron 20 | E29: XL | F29: Alphabet | G29: XL | H29: Yes | I29: 4 | J29: Sold | K29: 3305.6 | L29: 0.7 | M29: Valid | N29: Include | O29: 3966.72 | P29: =_xlfn.IFS($L29<=0.2,"0-20%",$L29<=0.4,"20-40%",$L29<=0.6,"40-60%",$L29<=0.8,"60-80%",$L29<=1,"80-100%") -> 60-80% | Q29: 3966.72 | R29: Valid Revenue | S29: Include | T29: 45531 | U29: 45531 | V29: Yes | W29: Online | X29: Kolkata | Y29: Kolkata | Z29: 1605.13 | AA29: =($Z29/$Q29)*100 -> 40.464918 | AB29: Valid Profit | AC29: Include
A30: 3906 | B30: Men | C30: Lifestyle | D30: Dunk Low | E30: XL | F30: Alphabet | G30: XL | H30: Yes | I30: 4 | J30: Sold | K30: 7588.77 | L30: 0.14 | M30: Valid | N30: Include | O30: 26105.37 | P30: =_xlfn.IFS($L30<=0.2,"0-20%",$L30<=0.4,"20-40%",$L30<=0.6,"40-60%",$L30<=0.8,"60-80%",$L30<=1,"80-100%") -> 0-20% | Q30: 26105.369 | R30: Valid Revenue | S30: Include | T30: 45539 | U30: 45539 | V30: Yes | W30: Online | X30: Hyderabad | Y30: Hyderabad | Z30: 3435.73 | AA30: =($Z30/$Q30)*100 -> 13.161009 | AB30: Valid Profit | AC30: Include
